Workbook
Name Agata_Bag: #REF!
Name Tshirt: #REF!
Name MARKETING: #REF!
Name Annie_Bag_Silk: #REF!
Name Charm_Bon.VI_x_AMI: #REF!
Name Airpods_Case_Con_Moschettone: #REF!
Name OPEX: #REF!
Name Annie_Bag_Pailletes_Con_Catena: #REF!
Name Annie_Bag_Pailletes: #REF!
Name Lea_Bag: #REF!
Name Annie_Bag_Pailletes_Con_Catena: #REF!
Name MARKETING: #REF!
Name A1A250: PRODUCT_MAP!$A$1
Name LOGISTICA: #REF!
Name Clessidra_Bag: #REF!
Name Valentina_Bag: #REF!
Name LOGISTICA: #REF!
Name Airpods_Case_Con_Moschettone: #REF!
Name Annie_Bag_Pailletes: #REF!
Name Lea_Bag: #REF!
Name Charm_Bon.VI_x_AMI: #REF!
Name Valentina_Bag: #REF!
Name Lola_Bag: #REF!
Name Tshirt: #REF!
Name Clessidra_Bag: #REF!
Name Agata_Bag: #REF!
Name Annie_Bag_Silk: #REF!
Name Lola_Bag: #REF!
Name OPEX: #REF!

Sheet ISTRUZIONI
A1: Conta fisica inventario Amimi
A2: Dati di riferimento aggiornati allo snapshot del 2026-06-16 03:27 (gestionale + Shopify).
A4: Come si compila il foglio CONTA (Benedetta / Ginny):
A5: Per ogni prodotto vedete gia': quante DOVREBBERO essercene (gestionale), quante sono CARICATE online (Shopify) e lo STATO su Shopify (ACTIVE = pubblicata, DRAFT = bozza).
A6: Contate i pezzi reali e scriveteli nella colonna gialla PEZZI CONTATI (scrivete 0 se finiti). Usate NOTE per qualsiasi cosa strana (difettoso, in showroom, prestato...).
A7: Le colonne Delta e Azione si compilano da sole: servono ad Ale per la riconciliazione. Voi potete ignorarle.
A8: Non toccate Shopify ne' il gestionale: basta questo file. Poi premete il bottone 🧾 Amimì > Registra conta.
A10: Le colonne, in breve:
A11: Dovrebbero essere = giacenza calcolata dal gestionale oggi. Caricate online = pezzi mostrati sul sito. Stato Shopify = ACTIVE/DRAFT/assente.
A12: Delta = contati meno dovrebbero. Negativo = mancano pezzi (Ale aggiunge righe in GIFT_OFFLINE). Positivo = trovati in piu' (riga ACQUISTI).
A14: NB: i numeri di riferimento sono dello snapshot 2026-06-16 03:27. Se la conta slitta di giorni, ripremete "Prepara foglio conta" per rigenerarli.

Sheet B2B_NEGOZI
A1: NOME | B1: CITTA | C1: CONTATTO | D1: TIPO_DEAL | E1: PERC_COMMISSIONE | F1: FEE_FISSA | G1: FEE_FREQUENZA | H1: DATA_INIZIO | I1: DATA_FINE | J1: STATO | K1: NOTE
A2: Test_Scheda_QA | B2: Milano | C2: QA Test | D2: commissione | E2: 0.35 | G2: settimana | J2: attivo | K2: TEST FASE D - perc modificata a 35

Sheet DB_B2B
A1: DATA | B1: ANNO | C1: MESE | D1: CODICE | E1: QUANTITA | F1: MODELLO | G1: TIPO_MOVIMENTO | H1: NEGOZIO | I1: PREZZO_RETAIL | J1: PERC_NEGOZIO | K1: RETAIL_TOT | L1: QUOTA_NEGOZIO | M1: INCASSO_AMIMI | N1: COGS | O1: NOTE | P1: MOV_ID | Q1: STATO
A2: 46192.625 | B2: {=IF(A2:A1015="","",YEAR(A2:A1015))} -> 2026 | C2: {=IF(A2:A1015="","",MONTH(A2:A1015))} -> 6 | D2: Nina_Bag_Maxi_STRIPES_REED | E2: 1 | F2: wholesale | G2: venduto | H2: Como | I2: 70 | J2: 0.5 | K2: {=IF(I2:I1015="","",I2:I1015*E2:E1015)} -> 70 | L2: {=IF(I2:I1015="","",K2:K1015*J2:J1015)} -> 35 | M2: {=IF(I2:I1015="","",K2:K1015-L2:L1015)} -> 35 | N2: {=IF(D2:D1015="","",E2:E1015*IFERROR(VLOOKUP(D2:D1015,'PRODUCT_COGS&PRICE'!$A:$E,5,FALSE),0))} -> 14.58 | O2: TEST B2B (alta giacenza, no rischio)
A3: 46192.625 | B3: 2026 | C3: 6 | D3: Nina_Bag_STRIPES_PETROL_BLUE | E3: 1 | F3: wholesale | G3: venduto | H3: Levanto | I3: 50 | J3: 0.5 | K3: 50 | L3: 25 | M3: 25 | N3: 10.71 | O3: TEST B2B (alta giacenza, no rischio)
A1001: 46193.625 | B1001: 2026 | C1001: 6 | D1001: Agata_Bag_FLORAL_DUSTY_PINK_EMBROIDERY | E1001: 1 | F1001: conto_vendita | G1001: invio | H1001: Como | I1001: 80 | J1001: 0.4 | K1001: 80 | L1001: 32 | M1001: 48 | N1001: 19 | P1001: Gsmqoaeldusxno-0
A1002: 46193.625 | B1002: 2026 | C1002: 6 | D1002: Nina_Bag_Maxi_STRIPES_REED | E1002: 3 | F1002: conto_vendita | G1002: invio | H1002: TEST_NEGOZIO_QA | I1002: 100 | J1002: 0.4 | K1002: 300 | L1002: 120 | M1002: 180 | N1002: 43.74 | P1002: GqaInvioA-0 | Q1002: annullato
A1003: 46193.625 | B1003: 2026 | C1003: 6 | D1003: Nina_Bag_Maxi_STRIPES_REED | E1003: 1 | F1003: conto_vendita | G1003: venduto | H1003: TEST_NEGOZIO_QA | I1003: 100 | J1003: 0.4 | K1003: 100 | L1003: 40 | M1003: 60 | N1003: 14.58 | P1003: GqaVendA-0
A1004: 46193.625 | B1004: 2026 | C1004: 6 | D1004: Nina_Bag_Maxi_STRIPES_REED | E1004: 1 | F1004: conto_vendita | G1004: reso | H1004: TEST_NEGOZIO_QA | I1004: 100 | J1004: 0.4 | K1004: 100 | L1004: 40 | M1004: 60 | N1004: 14.58 | P1004: GqaResoA-0
A1005: 46193.625 | B1005: 2026 | C1005: 6 | D1005: Nina_Bag_STRIPES_PETROL_BLUE | E1005: 2 | F1005: wholesale | G1005: venduto | H1005: TEST_NEGOZIO_QA | I1005: 50 | J1005: 0 | K1005: 100 | L1005: 0 | M1005: 100 | N1005: 21.42 | P1005: GqaWholeB-0
A1006: 46195.625 | B1006: 2026 | C1006: 6 | D1006: Agata_Bag_FLORAL_BORDEAUX_EMBROIDERY | E1006: 1 | F1006: wholesale | G1006: venduto | H1006: ZZ_TEST_NUOVO_2306 | I1006: 80 | J1006: 0 | K1006: 80 | L1006: 0 | M1006: 80 | N1006: 19 | O1006: test casi reali | P1006: Gwsnuovo2306-0 | Q1006: annullato
A1007: 46195.625 | B1007: 2026 | C1007: 6 | D1007: Agata_Bag_FLORAL_BORDEAUX_EMBROIDERY | E1007: 2 | F1007: conto_vendita | G1007: invio | H1007: ZZ_TEST_CONTO_2306 | I1007: 160 | J1007: 0.4 | K1007: 320 | L1007: 128 | M1007: 192 | N1007: 38 | O1007: test conto nuovo | P1007: Gcontonuovo2306-0 | Q1007: annullato
A1008: 46195.625 | B1008: 2026 | C1008: 6 | D1008: Agata_Bag_FLORAL_BORDEAUX_EMBROIDERY | E1008: 5 | F1008: conto_vendita | G1008: invio | H1008: ZZ_MATRIX_2306 | I1008: 160 | J1008: 0.4 | K1008: 800 | L1008: 320 | M1008: 480 | N1008: 95 | O1008: matrix | P1008: Gmx_invio-0 | Q1008: annullato
A1009: 46195.625 | B1009: 2026 | C1009: 6 | D1009: Agata_Bag_FLORAL_BORDEAUX_EMBROIDERY | E1009: 2 | F1009: conto_vendita | G1009: venduto | H1009: ZZ_MATRIX_2306 | I1009: 160 | J1009: 0.4 | K1009: 320 | L1009: 128 | M1009: 192 | N1009: 38 | O1009: matrix | P1009: Gmx_vend-0 | Q1009: annullato
A1010: 46195.625 | B1010: 2026 | C1010: 6 | D1010: Agata_Bag_FLORAL_BORDEAUX_EMBROIDERY | E1010: 1 | F1010: conto_vendita | G1010: reso | H1010: ZZ_MATRIX_2306 | I1010: 160 | J1010: 0.4 | K1010: 160 | L1010: 64 | M1010: 96 | N1010: 19 | O1010: matrix | P1010: Gmx_reso-0 | Q1010: annullato
A1011: 46156.625 | B1011: 2026 | C1011: 5 | D1011: Agata_Bag_FLORAL_BORDEAUX_EMBROIDERY | E1011: 1 | F1011: conto_vendita | G1011: invio | H1011: ZZ_MATRIX_2306 | I1011: 160 | J1011: 0.4 | K1011: 160 | L1011: 64 | M1011: 96 | N1011: 19 | O1011: backdate | P1011: Gmx_back-0 | Q1011: annullato
A1012: 46182.625 | B1012: 2026 | C1012: 6 | D1012: Agata_Bag_FLORAL_BORDEAUX_EMBROIDERY | E1012: 1 | F1012: conto_vendita | G1012: invio | H1012: ZZ_BK_2306 | I1012: 160 | J1012: 0.4 | K1012: 160 | L1012: 64 | M1012: 96 | N1012: 19 | O1012: backdate recente | P1012: Gmx_bk2-0 | Q1012: annullato
A1013: 46182.625 | B1013: 2026 | C1013: 6 | D1013: Agata_Bag_FLORAL_BORDEAUX_EMBROIDERY | E1013: 1 | F1013: conto_vendita | G1013: invio | H1013: ZZ_TZ_2306 | I1013: 160 | J1013: 0.4 | K1013: 160 | L1013: 64 | M1013: 96 | N1013: 19 | O1013: tz fix test | P1013: Gtz_fix1-0 | Q1013: annullato
A1014: 46183.125 | B1014: 2026 | C1014: 6 | D1014: Agata_Bag_FLORAL_BORDEAUX_EMBROIDERY | E1014: 1 | F1014: conto_vendita | G1014: invio | H1014: ZZ_TZ_2306 | I1014: 160 | J1014: 0.4 | K1014: 160 | L1014: 64 | M1014: 96 | N1014: 19 | O1014: tz fix2 | P1014: Gtz_fix2-0 | Q1014: annullato
A1015: 46196.125 | B1015: 2026 | C1015: 6 | D1015: Agata_Bag_FLORAL_BORDEAUX_EMBROIDERY | E1015: 1 | F1015: conto_vendita | G1015: invio | H1015: ZZ_TZ_2306 | I1015: 160 | J1015: 0.4 | K1015: 160 | L1015: 64 | M1015: 96 | N1015: 19 | O1015: oggi | P1015: Gtz_fix3-0 | Q1015: annullato

Sheet VARIANT_SYNC_LOG
A1: Timestamp | B1: Type | C1: Order_ID | D1: Detail
A2: 46172.551 | B2: BUILD_MAP | D2: 21 ACTIVE+published 2-variant Catena bags written
A3: 46172.568 | B3: BUILD_MAP | D3: 21 ACTIVE+published 2-variant Catena bags written
A4: 46172.585 | B4: FULL_SYNC | D4: Full sync: 0/21 OK | Errors: | AGATA BAG FLORAL BORDEAUX EMBROIDERY: [{"field":["input","ignoreCompareQuantity"],"message":"The compareQuantity argument must be given to each quantity or ignored using ignoreCompareQuantity."}] | AGATA BAG FLORAL DUSTY PINK EMBROIDERY: [{"field":["input","ignoreCompareQuantity"],"message":"The compareQuantity argument must be given to each quantity or ignored using ignoreCompareQuantity."}] | AGATA BAG FLORAL GREEN EMBROIDERY: [{"field":["input","ignoreCompareQuantity"],"message":"The compareQuantity argument must be given to each quantity or ignored using ignoreCompareQuantity."}] | AGATA BAG FLORAL ORANGE EMBROIDERY: [{"field":["input","ignoreCompareQuantity"],"message":"The compareQuantity argument must be given to each quantity or ignored using ignoreCompareQuantity."}] | AGATA BAG FLORAL PINK EMBROIDERY: [{"field":["input","ignoreCompareQuantity"],"message":"The compareQuantity argument must be given to each quantity or ignored using ignoreCompareQuantity."}] | AGATA BAG PAILLETTES PINK: [{"field":["input","ignoreCompareQuantity"],"message":"The compareQuantity argument must be given to each quantity or ignored using ignoreCompareQuantity."}] | AGATA BAG ROSE BLUE: [{"field":["input","ignoreCompareQuantity"],"message":"The compareQuantity argument must be given to each quantity or ignored using ignoreCompareQuantity."}] | AGATA BAG ROSE BUTTER: [{"field":["input","ignoreCompareQuantity"],"message":"The compareQuantity argument must be given to each quantity or ignored using ignoreCompareQuantity."}] | AGATA BAG ROSE PINK: [{"field":["input","ignoreCompareQuantity"],"message":"The compareQuantity argument must be given to each quantity or ignored using ignoreCompareQuantity."}] | AGATA BAG TIE DYE ORANGE: [{"field":["input","ignoreCompareQuantity"],"message":"The compareQuantity argument must be given to each quantity or ignored using ignoreCompareQuantity."}] | AGATA BAG TIE DYE PINK: [{"field":["input","ignoreCompareQuantity"],"message":"The compareQuantity argument must be given to each quantity or ignored using ignoreCompareQuantity."}] | ANNIE BAG BLUE: [{"field":["input","ignoreCompareQuantity"],"message":"The compareQuantity argument must be given to each quantity or ignored using ignoreCompareQuantity."}] | ANNIE BAG BROWN: [{"field":["input","ignoreCompareQuantity"],"message":"The compareQuantity argument must be given to each quantity or ignored using ignoreCompareQuantity."}] | ANNIE BAG LILAC: [{"field":["input","ignoreCompareQuantity"],"message":"The compareQuantity argument must be given to each quantity or ignored using ignoreCompareQuantity."}] | ANNIE BAG PAILLETTES LIGHT BLUE: [{"field":["input","ignoreCompareQuantity"],"message":"The compareQuantity argument must be given to each quantity or ignored using ignoreCompareQuantity."}] | ANNIE BAG PAILLETTES LIGHT GREEN: [{"field":["input","ignoreCompareQuantity"],"message":"The compareQuantity argument must be given to each quantity or ignored using ignoreCompareQuantity."}] | ANNIE BAG PAILLETTES NUDE: [{"field":["input","ignoreCompareQuantity"],"message":"The compareQuantity argument must be given to each quantity or ignored using ignoreCompareQuantity."}] | ANNIE BAG PAILLETTES PINK: [{"field":["input","ignoreCompareQuantity"],"message":"The compareQuantity argument must be given to each quantity or ignored using ignoreCompareQuantity."}] | ANNIE BAG PEARL GREY: [{"field":["input","ignoreCompareQuantity"],"message":"The compareQuantity argument must be given to each quantity or ignored using ignoreCompareQuantity."}] | ANNIE BAG PINK: [{"field":["input","ignoreCompareQuantity"],"message":"The compareQuantity argument must be given to each quantity or ignored using ignoreCompareQuantity."}] | ANNIE BAG STRIPES PINK: [{"field":["input","ignoreCompareQuantity"],"message":"The compareQuantity argument must be given to each quantity or ignored using ignoreCompareQuantity."}]
A5: 46172.585 | B5: WEBHOOK_REGISTER | D5: Registered orders/create webhook gid://shopify/WebhookSubscription/2221675708743 URL: https://script.google.com/macros/s/AKfycbzi1GmsPGj4qFeHiTPZVaj3K5ZgSjuWUqRQPd_v2tE3D9FPXSzOA17nDAYbxwdeurWXKQ/exec?token=1cf735f7-79ac-4a73-aea1-0df461dac6e5
A6: 46172.591 | B6: FULL_SYNC | D6: Full sync: 21/21 OK
A7: 46172.598 | B7: SYNCED | C7: 9999000001 | D7: AGATA BAG ROSE PINK -1 -> 3
A8: 46172.602 | B8: RESTOCK | D8: AGATA BAG ROSE PINK -> 4
A9: 46172.973 | B9: DAILY_REPORT | D9: risk=7 drift=0
A10: 46173.445 | B10: NO_MATCH | C10: 7786211606855 | D10: No Catena-pair bags in this order
A11: 46173.445 | B11: DUPLICATE | C11: 7786211606855 | D11: Already processed, skipped
A12: 46173.446 | B12: DUPLICATE | C12: 7786211606855 | D12: Already processed, skipped
A13: 46173.447 | B13: DUPLICATE | C13: 7786211606855 | D13: Already processed, skipped
A14: 46173.451 | B14: DUPLICATE | C14: 7786211606855 | D14: Already processed, skipped
A15: 46173.466 | B15: DUPLICATE | C15: 7786211606855 | D15: Already processed, skipped
A16: 46173.487 | B16: DUPLICATE | C16: 7786211606855 | D16: Already processed, skipped
A17: 46173.528 | B17: DUPLICATE | C17: 7786211606855 | D17: Already processed, skipped
A18: 46173.554 | B18: SYNCED | C18: 7786725081415 | D18: AGATA BAG FLORAL GREEN EMBROIDERY -1 -> 0; AGATA BAG FLORAL PINK EMBROIDERY -1 -> 3
A19: 46173.554 | B19: DUPLICATE | C19: 7786725081415 | D19: Already processed, skipped
A20: 46173.555 | B20: DUPLICATE | C20: 7786725081415 | D20: Already processed, skipped
A21: 46173.557 | B21: DUPLICATE | C21: 7786725081415 | D21: Already processed, skipped
... A31: 46173.973 | B31: DUPLICATE | C31: 7787347968327 | D31: Already processed, skipped
A32: 46173.973 | B32: DAILY_REPORT | D32: risk=6 drift=0
A33: 46173.977 | B33: DUPLICATE | C33: 7787347968327 | D33: Already processed, skipped
A34: 46173.992 | B34: DUPLICATE | C34: 7787347968327 | D34: Already processed, skipped
A35: 46174.013 | B35: DUPLICATE | C35: 7787347968327 | D35: Already processed, skipped
A36: 46174.055 | B36: DUPLICATE | C36: 7787347968327 | D36: Already processed, skipped
A37: 46174.117 | B37: NO_MATCH | C37: 7787787419975 | D37: No Catena-pair bags in this order
A38: 46174.117 | B38: DUPLICATE | C38: 7787787419975 | D38: Already processed, skipped
A39: 46174.118 | B39: DUPLICATE | C39: 7787787419975 | D39: Already processed, skipped
A40: 46174.119 | B40: DUPLICATE | C40: 7787787419975 | D40: Already processed, skipped
A41: 46174.123 | B41: DUPLICATE | C41: 7787787419975 | D41: Already processed, skipped
A42: 46174.138 | B42: DUPLICATE | C42: 7787347968327 | D42: Already processed, skipped
A43: 46174.138 | B43: DUPLICATE | C43: 7787787419975 | D43: Already processed, skipped
A44: 46174.159 | B44: DUPLICATE | C44: 7787787419975 | D44: Already processed, skipped
... A91: 46174.417 | B91: DUPLICATE | C91: 7788252725575 | D91: Already processed, skipped
A92: 46174.973 | B92: DAILY_REPORT | D92: risk=7 drift=1
A93: 46175.051 | B93: NO_MATCH | C93: 7790371373383 | D93: No Catena-pair bags in this order
A94: 46175.051 | B94: DUPLICATE | C94: 7790371373383 | D94: Already processed, skipped
A95: 46175.052 | B95: DUPLICATE | C95: 7790371373383 | D95: Already processed, skipped
A96: 46175.053 | B96: DUPLICATE | C96: 7790371373383 | D96: Already processed, skipped
A97: 46175.057 | B97: DUPLICATE | C97: 7790371373383 | D97: Already processed, skipped
A98: 46175.072 | B98: DUPLICATE | C98: 7790371373383 | D98: Already processed, skipped
A99: 46175.093 | B99: DUPLICATE | C99: 7790371373383 | D99: Already processed, skipped
A100: 46175.135 | B100: DUPLICATE | C100: 7790371373383 | D100: Already processed, skipped
A101: 46175.217 | B101: SYNCED | C101: 7790919942471 | D101: ANNIE BAG PAILLETTES NUDE -1 -> 1
A102: 46175.217 | B102: DUPLICATE | C102: 7790919942471 | D102: Already processed, skipped
A103: 46175.218 | B103: DUPLICATE | C103: 7790919942471 | D103: Already processed, skipped
A104: 46175.218 | B104: DUPLICATE | C104: 7790371373383 | D104: Already processed, skipped
... A128: 46175.662 | B128: DUPLICATE | C128: 7791833612615 | D128: Already processed, skipped
A129: 46175.973 | B129: DAILY_REPORT | D129: risk=6 drift=1
A130: 46176.008 | B130: SYNCED | C130: 7792659693895 | D130: ANNIE BAG PAILLETTES NUDE -1 -> 0
A131: 46176.008 | B131: DUPLICATE | C131: 7792659693895 | D131: Already processed, skipped
A132: 46176.009 | B132: DUPLICATE | C132: 7792659693895 | D132: Already processed, skipped
A133: 46176.01 | B133: DUPLICATE | C133: 7792659693895 | D133: Already processed, skipped
A134: 46176.013 | B134: DUPLICATE | C134: 7792659693895 | D134: Already processed, skipped
A135: 46176.029 | B135: DUPLICATE | C135: 7792659693895 | D135: Already processed, skipped
A136: 46176.044 | B136: SYNCED | C136: 7792763502919 | D136: ANNIE BAG PAILLETTES PINK -1 -> 1
A137: 46176.044 | B137: DUPLICATE | C137: 7792763502919 | D137: Already processed, skipped
A138: 46176.045 | B138: DUPLICATE | C138: 7792763502919 | D138: Already processed, skipped
A139: 46176.046 | B139: DUPLICATE | C139: 7792763502919 | D139: Already processed, skipped
A140: 46176.05 | B140: DUPLICATE | C140: 7792763502919 | D140: Already processed, skipped
A141: 46176.05 | B141: DUPLICATE | C141: 7792659693895 | D141: Already processed, skipped
... A210: 46176.789 | B210: DUPLICATE | C210: 7794561614151 | D210: Already processed, skipped
A211: 46176.973 | B211: DAILY_REPORT | D211: risk=5 drift=3
A212: 46177.282 | B212: NO_MATCH | C212: 7796977369415 | D212: No Catena-pair bags in this order
A213: 46177.282 | B213: DUPLICATE | C213: 7796977369415 | D213: Already processed, skipped
A214: 46177.283 | B214: DUPLICATE | C214: 7796977369415 | D214: Already processed, skipped
A215: 46177.283 | B215: SYNCED | C215: 7797044838727 | D215: ANNIE BAG PAILLETTES LIGHT BLUE -1 -> 0
A216: 46177.283 | B216: DUPLICATE | C216: 7797044838727 | D216: Already processed, skipped
A217: 46177.284 | B217: DUPLICATE | C217: 7797044838727 | D217: Already processed, skipped
A218: 46177.284 | B218: DUPLICATE | C218: 7796977369415 | D218: Already processed, skipped
A219: 46177.285 | B219: DUPLICATE | C219: 7797044838727 | D219: Already processed, skipped
A220: 46177.288 | B220: DUPLICATE | C220: 7796977369415 | D220: Already processed, skipped
A221: 46177.289 | B221: DUPLICATE | C221: 7797044838727 | D221: Already processed, skipped
A222: 46177.303 | B222: DUPLICATE | C222: 7796977369415 | D222: Already processed, skipped
A223: 46177.303 | B223: SYNCED | C223: 7797411283271 | D223: ANNIE BAG PAILLETTES LIGHT GREEN -1 -> 0
... A274: 46177.691 | B274: DUPLICATE | C274: 7801029722439 | D274: Already processed, skipped
A275: 46177.973 | B275: DAILY_REPORT | D275: risk=2 drift=2
A276: 46178.079 | B276: SYNCED | C276: 7804770812231 | D276: AGATA BAG ROSE BUTTER -1 -> 1
A277: 46178.079 | B277: DUPLICATE | C277: 7804770812231 | D277: Already processed, skipped
A278: 46178.08 | B278: DUPLICATE | C278: 7804770812231 | D278: Already processed, skipped
A279: 46178.082 | B279: DUPLICATE | C279: 7804770812231 | D279: Already processed, skipped
A280: 46178.082 | B280: NO_MATCH | C280: 7804808298823 | D280: No Catena-pair bags in this order
A281: 46178.082 | B281: DUPLICATE | C281: 7804808298823 | D281: Already processed, skipped
A282: 46178.083 | B282: DUPLICATE | C282: 7804808298823 | D282: Already processed, skipped
A283: 46178.085 | B283: DUPLICATE | C283: 7804808298823 | D283: Already processed, skipped
A284: 46178.085 | B284: DUPLICATE | C284: 7804770812231 | D284: Already processed, skipped
A285: 46178.088 | B285: DUPLICATE | C285: 7804808298823 | D285: Already processed, skipped
A286: 46178.1 | B286: DUPLICATE | C286: 7804770812231 | D286: Already processed, skipped
A287: 46178.103 | B287: DUPLICATE | C287: 7804808298823 | D287: Already processed, skipped
... A320: 46178.701 | B320: DUPLICATE | C320: 7808782041415 | D320: Already processed, skipped
A321: 46178.973 | B321: DAILY_REPORT | D321: risk=3 drift=1
A322: 46178.988 | B322: SYNCED | C322: 7809285718343 | D322: ANNIE BAG BLUE -1 -> 1
A323: 46178.988 | B323: DUPLICATE | C323: 7809285718343 | D323: Already processed, skipped
A324: 46178.989 | B324: DUPLICATE | C324: 7809285718343 | D324: Already processed, skipped
A325: 46178.991 | B325: DUPLICATE | C325: 7809285718343 | D325: Already processed, skipped
A326: 46178.994 | B326: DUPLICATE | C326: 7809285718343 | D326: Already processed, skipped
A327: 46179.009 | B327: DUPLICATE | C327: 7809285718343 | D327: Already processed, skipped
A328: 46179.03 | B328: DUPLICATE | C328: 7809285718343 | D328: Already processed, skipped
...

Sheet CONTA_INBOX
A1: timestamp | B1: data_conta | C1: CODICE | D1: modello | E1: variante | F1: contati | G1: giac_oggi | H1: delta | I1: chi | J1: nota | K1: stato
A2: 46189.141 | B2: 46189 | C2: Lea_Bag_COCCO_BLACK | D2: Lea Bag | E2: COCCO BLACK | F2: 3 | G2: 8 | H2: -5 | I2: cofounder | J2: | ammanco 5 >= soglia 3: serve indagine sulla causa | K2: ignorato (test 16-06)
A3: 46189.141 | B3: 46189 | C3: Lea_Bag_Zebra_Dark | D3: Lea Bag | E3: Zebra Dark | F3: 8 | G3: 6 | H3: 2 | I3: cofounder | J3: | surplus +2: possibile acquisto mancante / reso / errore conta (decisione umana) | K3: ignorato (test 16-06)

Sheet CONTA_INPUT
A1: Modello | B1: Variante / Descrizione | C1: CODICE_AMIIMI | D1: Dovrebbero essere (gestionale) | E1: Caricate online (Shopify) | F1: Stato Shopify | G1: PEZZI CONTATI | H1: Delta (contati - gestionale) | I1: Azione suggerita | J1: NOTE | K1: CONTA_APPLICATA
A2: Lea Bag | B2: LEOPARDO SAVANA | C2: Lea_Bag_LEOPARDO_SAVANA | D2: 8 | E2: 8 | F2: ACTIVE | H2: =IF(G2="","",G2-D2) | I2: =IF(G2="","Non ancora contato",IF(G2-D2=0,"OK",IF(G2-D2<0,IF(ABS(G2-D2)<3,"Rettifica -"&ABS(G2-D2)&" (GIFT_OFFLINE)","DA VERIFICARE: ammanco "&ABS(G2-D2)),"DA VERIFICARE: surplus +"&(G2-D2)))) -> Non ancora contato
A3: Lea Bag | B3: COCCO BLACK | C3: Lea_Bag_COCCO_BLACK | D3: 8 | E3: 8 | F3: ACTIVE | H3: =IF(G3="","",G3-D3) | I3: =IF(G3="","Non ancora contato",IF(G3-D3=0,"OK",IF(G3-D3<0,IF(ABS(G3-D3)<3,"Rettifica -"&ABS(G3-D3)&" (GIFT_OFFLINE)","DA VERIFICARE: ammanco "&ABS(G3-D3)),"DA VERIFICARE: surplus +"&(G3-D3)))) -> Non ancora contato
A4: Lea Bag | B4: Zebra Dark | C4: Lea_Bag_Zebra_Dark | D4: 6 | E4: 6 | F4: ACTIVE | H4: =IF(G4="","",G4-D4) | I4: =IF(G4="","Non ancora contato",IF(G4-D4=0,"OK",IF(G4-D4<0,IF(ABS(G4-D4)<3,"Rettifica -"&ABS(G4-D4)&" (GIFT_OFFLINE)","DA VERIFICARE: ammanco "&ABS(G4-D4)),"DA VERIFICARE: surplus +"&(G4-D4)))) -> Non ancora contato
A5: Lea Bag | B5: PONY COCCO BLACK | C5: Lea_Bag_PONY_COCCO_BLACK | D5: 0 | E5: 0 | F5: ACTIVE | H5: =IF(G5="","",G5-D5) | I5: =IF(G5="","Non ancora contato",IF(G5-D5=0,"OK",IF(G5-D5<0,IF(ABS(G5-D5)<3,"Rettifica -"&ABS(G5-D5)&" (GIFT_OFFLINE)","DA VERIFICARE: ammanco "&ABS(G5-D5)),"DA VERIFICARE: surplus +"&(G5-D5)))) -> Non ancora contato
A6: Lea Bag | B6: JUNGLE | C6: Lea_Bag_JUNGLE | D6: 1 | E6: 0 | F6: DRAFT | H6: =IF(G6="","",G6-D6) | I6: =IF(G6="","Non ancora contato",IF(G6-D6=0,"OK",IF(G6-D6<0,IF(ABS(G6-D6)<3,"Rettifica -"&ABS(G6-D6)&" (GIFT_OFFLINE)","DA VERIFICARE: ammanco "&ABS(G6-D6)),"DA VERIFICARE: surplus +"&(G6-D6)))) -> Non ancora contato
A7: Lea Bag | B7: GREEN MILITARY | C7: Lea_Bag_GREEN_MILITARY | D7: 1 | E7: 1 | F7: ACTIVE | H7: =IF(G7="","",G7-D7) | I7: =IF(G7="","Non ancora contato",IF(G7-D7=0,"OK",IF(G7-D7<0,IF(ABS(G7-D7)<3,"Rettifica -"&ABS(G7-D7)&" (GIFT_OFFLINE)","DA VERIFICARE: ammanco "&ABS(G7-D7)),"DA VERIFICARE: surplus +"&(G7-D7)))) -> Non ancora contato
A8: Lea Bag | B8: KAKI GREEN PONY | C8: Lea_Bag_KAKI_GREEN_PONY | D8: 1 | E8: 0 | F8: ACTIVE | H8: =IF(G8="","",G8-D8) | I8: =IF(G8="","Non ancora contato",IF(G8-D8=0,"OK",IF(G8-D8<0,IF(ABS(G8-D8)<3,"Rettifica -"&ABS(G8-D8)&" (GIFT_OFFLINE)","DA VERIFICARE: ammanco "&ABS(G8-D8)),"DA VERIFICARE: surplus +"&(G8-D8)))) -> Non ancora contato
A9: Lea Bag | B9: Cavallino Chocolate | C9: Lea_Bag_Cavallino_Chocolate | D9: 1 | E9: n/d | F9: n/d | H9: =IF(G9="","",G9-D9) | I9: =IF(G9="","Non ancora contato",IF(G9-D9=0,"OK",IF(G9-D9<0,IF(ABS(G9-D9)<3,"Rettifica -"&ABS(G9-D9)&" (GIFT_OFFLINE)","DA VERIFICARE: ammanco "&ABS(G9-D9)),"DA VERIFICARE: surplus +"&(G9-D9)))) -> Non ancora contato
A10: Lea Bag | B10: Cavallino Light Brown | C10: Lea_Bag_Cavallino_Light_Brown | D10: 1 | E10: 1 | F10: ACTIVE | H10: =IF(G10="","",G10-D10) | I10: =IF(G10="","Non ancora contato",IF(G10-D10=0,"OK",IF(G10-D10<0,IF(ABS(G10-D10)<3,"Rettifica -"&ABS(G10-D10)&" (GIFT_OFFLINE)","DA VERIFICARE: ammanco "&ABS(G10-D10)),"DA VERIFICARE: surplus +"&(G10-D10)))) -> Non ancora contato
A11: Lea Bag | B11: Cavallino Bordeaux | C11: Lea_Bag_Cavallino_Bordeaux | D11: 2 | E11: n/d | F11: n/d | H11: =IF(G11="","",G11-D11) | I11: =IF(G11="","Non ancora contato",IF(G11-D11=0,"OK",IF(G11-D11<0,IF(ABS(G11-D11)<3,"Rettifica -"&ABS(G11-D11)&" (GIFT_OFFLINE)","DA VERIFICARE: ammanco "&ABS(G11-D11)),"DA VERIFICARE: surplus +"&(G11-D11)))) -> Non ancora contato
A12: Lea Bag | B12: ESPRESSO PONY | C12: Lea_Bag_ESPRESSO_PONY | D12: 0 | E12: 0 | F12: DRAFT | H12: =IF(G12="","",G12-D12) | I12: =IF(G12="","Non ancora contato",IF(G12-D12=0,"OK",IF(G12-D12<0,IF(ABS(G12-D12)<3,"Rettifica -"&ABS(G12-D12)&" (GIFT_OFFLINE)","DA VERIFICARE: ammanco "&ABS(G12-D12)),"DA VERIFICARE: surplus +"&(G12-D12)))) -> Non ancora contato
A13: Lea Bag | B13: BLACK | C13: Lea_Bag_BLACK | D13: 2 | E13: 1 | F13: ACTIVE | H13: =IF(G13="","",G13-D13) | I13: =IF(G13="","Non ancora contato",IF(G13-D13=0,"OK",IF(G13-D13<0,IF(ABS(G13-D13)<3,"Rettifica -"&ABS(G13-D13)&" (GIFT_OFFLINE)","DA VERIFICARE: ammanco "&ABS(G13-D13)),"DA VERIFICARE: surplus +"&(G13-D13)))) -> Non ancora contato
A14: Maria Bag | B14: Red | C14: Maria_Bag_Red | D14: 0 | E14: 0 | F14: DRAFT | H14: =IF(G14="","",G14-D14) | I14: =IF(G14="","Non ancora contato",IF(G14-D14=0,"OK",IF(G14-D14<0,IF(ABS(G14-D14)<3,"Rettifica -"&ABS(G14-D14)&" (GIFT_OFFLINE)","DA VERIFICARE: ammanco "&ABS(G14-D14)),"DA VERIFICARE: surplus +"&(G14-D14)))) -> Non ancora contato
A15: Maria Bag | B15: RED PIERCING | C15: Maria_Bag_RED_PIERCING | D15: 4 | E15: 4 | F15: ACTIVE | H15: =IF(G15="","",G15-D15) | I15: =IF(G15="","Non ancora contato",IF(G15-D15=0,"OK",IF(G15-D15<0,IF(ABS(G15-D15)<3,"Rettifica -"&ABS(G15-D15)&" (GIFT_OFFLINE)","DA VERIFICARE: ammanco "&ABS(G15-D15)),"DA VERIFICARE: surplus +"&(G15-D15)))) -> Non ancora contato
A16: Valentina Bag | B16: CHOCOLATE | C16: Valentina_Bag_CHOCOLATE | D16: 21 | E16: 8 | F16: ACTIVE | H16: =IF(G16="","",G16-D16) | I16: =IF(G16="","Non ancora contato",IF(G16-D16=0,"OK",IF(G16-D16<0,IF(ABS(G16-D16)<3,"Rettifica -"&ABS(G16-D16)&" (GIFT_OFFLINE)","DA VERIFICARE: ammanco "&ABS(G16-D16)),"DA VERIFICARE: surplus +"&(G16-D16)))) -> Non ancora contato
A17: Nina Bag | B17: Stripes Strawberry | C17: Nina_Bag_Stripes_Strawberry | D17: 21 | E17: 19 | F17: ACTIVE | H17: =IF(G17="","",G17-D17) | I17: =IF(G17="","Non ancora contato",IF(G17-D17=0,"OK",IF(G17-D17<0,IF(ABS(G17-D17)<3,"Rettifica -"&ABS(G17-D17)&" (GIFT_OFFLINE)","DA VERIFICARE: ammanco "&ABS(G17-D17)),"DA VERIFICARE: surplus +"&(G17-D17)))) -> Non ancora contato
A18: Nina Bag | B18: PEACH | C18: Nina_Bag_PEACH | D18: 24 | E18: 22 | F18: ACTIVE | H18: =IF(G18="","",G18-D18) | I18: =IF(G18="","Non ancora contato",IF(G18-D18=0,"OK",IF(G18-D18<0,IF(ABS(G18-D18)<3,"Rettifica -"&ABS(G18-D18)&" (GIFT_OFFLINE)","DA VERIFICARE: ammanco "&ABS(G18-D18)),"DA VERIFICARE: surplus +"&(G18-D18)))) -> Non ancora contato
A19: Nina Bag | B19: Checks Navy Blue | C19: Nina_Bag_Checks_Navy_Blue | D19: 22 | E19: 20 | F19: ACTIVE | H19: =IF(G19="","",G19-D19) | I19: =IF(G19="","Non ancora contato",IF(G19-D19=0,"OK",IF(G19-D19<0,IF(ABS(G19-D19)<3,"Rettifica -"&ABS(G19-D19)&" (GIFT_OFFLINE)","DA VERIFICARE: ammanco "&ABS(G19-D19)),"DA VERIFICARE: surplus +"&(G19-D19)))) -> Non ancora contato
A20: Nina Bag | B20: Stripes Mint | C20: Nina_Bag_Stripes_Mint | D20: 5 | E20: 3 | F20: ACTIVE | H20: =IF(G20="","",G20-D20) | I20: =IF(G20="","Non ancora contato",IF(G20-D20=0,"OK",IF(G20-D20<0,IF(ABS(G20-D20)<3,"Rettifica -"&ABS(G20-D20)&" (GIFT_OFFLINE)","DA VERIFICARE: ammanco "&ABS(G20-D20)),"DA VERIFICARE: surplus +"&(G20-D20)))) -> Non ancora contato
A21: Lea Bag | B21: BLACK WHITE PONY | C21: Lea_Bag_BLACK_WHITE_PONY | D21: 0 | E21: 0 | F21: DRAFT | H21: =IF(G21="","",G21-D21) | I21: =IF(G21="","Non ancora contato",IF(G21-D21=0,"OK",IF(G21-D21<0,IF(ABS(G21-D21)<3,"Rettifica -"&ABS(G21-D21)&" (GIFT_OFFLINE)","DA VERIFICARE: ammanco "&ABS(G21-D21)),"DA VERIFICARE: surplus +"&(G21-D21)))) -> Non ancora contato
A22: Lea Bag | B22: RED PATENT | C22: Lea_Bag_RED_PATENT | D22: 8 | E22: 8 | F22: ACTIVE | H22: =IF(G22="","",G22-D22) | I22: =IF(G22="","Non ancora contato",IF(G22-D22=0,"OK",IF(G22-D22<0,IF(ABS(G22-D22)<3,"Rettifica -"&ABS(G22-D22)&" (GIFT_OFFLINE)","DA VERIFICARE: ammanco "&ABS(G22-D22)),"DA VERIFICARE: surplus +"&(G22-D22)))) -> Non ancora contato
A23: Lea Bag | B23: BLUE ELECTRIC | C23: Lea_Bag_BLUE_ELECTRIC | D23: 0 | E23: 0 | F23: DRAFT | H23: =IF(G23="","",G23-D23) | I23: =IF(G23="","Non ancora contato",IF(G23-D23=0,"OK",IF(G23-D23<0,IF(ABS(G23-D23)<3,"Rettifica -"&ABS(G23-D23)&" (GIFT_OFFLINE)","DA VERIFICARE: ammanco "&ABS(G23-D23)),"DA VERIFICARE: surplus +"&(G23-D23)))) -> Non ancora contato
... A30: Lea Bag | B30: VERNICE PURPLE PATENT | C30: Lea_Bag_VERNICE_PURPLE_PATENT | D30: 4 | E30: 2 | F30: ACTIVE | H30: =IF(G30="","",G30-D30) | I30: =IF(G30="","Non ancora contato",IF(G30-D30=0,"OK",IF(G30-D30<0,IF(ABS(G30-D30)<3,"Rettifica -"&ABS(G30-D30)&" (GIFT_OFFLINE)","DA VERIFICARE: ammanco "&ABS(G30-D30)),"DA VERIFICARE: surplus +"&(G30-D30)))) -> Non ancora contato
A31: Lea Bag | B31: TOASTED LEATHER GREEN | C31: Lea_Bag_TOASTED_LEATHER_GREEN | D31: 4 | E31: n/d | F31: n/d | H31: =IF(G31="","",G31-D31) | I31: =IF(G31="","Non ancora contato",IF(G31-D31=0,"OK",IF(G31-D31<0,IF(ABS(G31-D31)<3,"Rettifica -"&ABS(G31-D31)&" (GIFT_OFFLINE)","DA VERIFICARE: ammanco "&ABS(G31-D31)),"DA VERIFICARE: surplus +"&(G31-D31)))) -> Non ancora contato
A32: Lea Bag Maxi | B32: SUEDE CHOCOLATE CHARM | C32: Lea_Bag_Maxi_SUEDE_CHOCOLATE_CHARM | D32: -2 | E32: 0 | F32: ACTIVE | H32: =IF(G32="","",G32-D32) | I32: =IF(G32="","Non ancora contato",IF(G32-D32=0,"OK",IF(G32-D32<0,IF(ABS(G32-D32)<3,"Rettifica -"&ABS(G32-D32)&" (GIFT_OFFLINE)","DA VERIFICARE: ammanco "&ABS(G32-D32)),"DA VERIFICARE: surplus +"&(G32-D32)))) -> Non ancora contato
A33: Lea Bag Maxi | B33: SUEDE CHOCOLATE | C33: Lea_Bag_Maxi_SUEDE_CHOCOLATE | D33: 0 | E33: 0 | F33: ACTIVE | H33: =IF(G33="","",G33-D33) | I33: =IF(G33="","Non ancora contato",IF(G33-D33=0,"OK",IF(G33-D33<0,IF(ABS(G33-D33)<3,"Rettifica -"&ABS(G33-D33)&" (GIFT_OFFLINE)","DA VERIFICARE: ammanco "&ABS(G33-D33)),"DA VERIFICARE: surplus +"&(G33-D33)))) -> Non ancora contato
A34: Lea Bag Maxi | B34: COCCO BLACK | C34: Lea_Bag_Maxi_COCCO_BLACK | D34: 6 | E34: 6 | F34: ACTIVE | H34: =IF(G34="","",G34-D34) | I34: =IF(G34="","Non ancora contato",IF(G34-D34=0,"OK",IF(G34-D34<0,IF(ABS(G34-D34)<3,"Rettifica -"&ABS(G34-D34)&" (GIFT_OFFLINE)","DA VERIFICARE: ammanco "&ABS(G34-D34)),"DA VERIFICARE: surplus +"&(G34-D34)))) -> Non ancora contato
A35: Valentina Bag | B35: RED | C35: Valentina_Bag_RED | D35: 15 | E35: 6 | F35: ACTIVE | H35: =IF(G35="","",G35-D35) | I35: =IF(G35="","Non ancora contato",IF(G35-D35=0,"OK",IF(G35-D35<0,IF(ABS(G35-D35)<3,"Rettifica -"&ABS(G35-D35)&" (GIFT_OFFLINE)","DA VERIFICARE: ammanco "&ABS(G35-D35)),"DA VERIFICARE: surplus +"&(G35-D35)))) -> Non ancora contato
A36: Valentina Bag | B36: COCCO BLACK | C36: Valentina_Bag_COCCO_BLACK | D36: 7 | E36: 10 | F36: ACTIVE | H36: =IF(G36="","",G36-D36) | I36: =IF(G36="","Non ancora contato",IF(G36-D36=0,"OK",IF(G36-D36<0,IF(ABS(G36-D36)<3,"Rettifica -"&ABS(G36-D36)&" (GIFT_OFFLINE)","DA VERIFICARE: ammanco "&ABS(G36-D36)),"DA VERIFICARE: surplus +"&(G36-D36)))) -> Non ancora contato
A37: Valentina Bag | B37: GREEN MILITARY | C37: Valentina_Bag_GREEN_MILITARY | D37: 9 | E37: 7 | F37: ACTIVE | H37: =IF(G37="","",G37-D37) | I37: =IF(G37="","Non ancora contato",IF(G37-D37=0,"OK",IF(G37-D37<0,IF(ABS(G37-D37)<3,"Rettifica -"&ABS(G37-D37)&" (GIFT_OFFLINE)","DA VERIFICARE: ammanco "&ABS(G37-D37)),"DA VERIFICARE: surplus +"&(G37-D37)))) -> Non ancora contato
A38: Annie Bag | B38: BROWN | C38: Annie_Bag_BROWN | D38: 0 | E38: 0 | F38: DRAFT | H38: =IF(G38="","",G38-D38) | I38: =IF(G38="","Non ancora contato",IF(G38-D38=0,"OK",IF(G38-D38<0,IF(ABS(G38-D38)<3,"Rettifica -"&ABS(G38-D38)&" (GIFT_OFFLINE)","DA VERIFICARE: ammanco "&ABS(G38-D38)),"DA VERIFICARE: surplus +"&(G38-D38)))) -> Non ancora contato
A39: Annie Bag | B39: PAILLETTES PINK | C39: Annie_Bag_PAILLETTES_PINK | D39: 0 | E39: 0 | F39: ACTIVE | H39: =IF(G39="","",G39-D39) | I39: =IF(G39="","Non ancora contato",IF(G39-D39=0,"OK",IF(G39-D39<0,IF(ABS(G39-D39)<3,"Rettifica -"&ABS(G39-D39)&" (GIFT_OFFLINE)","DA VERIFICARE: ammanco "&ABS(G39-D39)),"DA VERIFICARE: surplus +"&(G39-D39)))) -> Non ancora contato
A40: Annie Bag | B40: BLUE | C40: Annie_Bag_BLUE | D40: 5 | E40: 5 | F40: ACTIVE | H40: =IF(G40="","",G40-D40) | I40: =IF(G40="","Non ancora contato",IF(G40-D40=0,"OK",IF(G40-D40<0,IF(ABS(G40-D40)<3,"Rettifica -"&ABS(G40-D40)&" (GIFT_OFFLINE)","DA VERIFICARE: ammanco "&ABS(G40-D40)),"DA VERIFICARE: surplus +"&(G40-D40)))) -> Non ancora contato
A41: Annie Bag | B41: PINK | C41: Annie_Bag_PINK | D41: 3 | E41: 3 | F41: ACTIVE | H41: =IF(G41="","",G41-D41) | I41: =IF(G41="","Non ancora contato",IF(G41-D41=0,"OK",IF(G41-D41<0,IF(ABS(G41-D41)<3,"Rettifica -"&ABS(G41-D41)&" (GIFT_OFFLINE)","DA VERIFICARE: ammanco "&ABS(G41-D41)),"DA VERIFICARE: surplus +"&(G41-D41)))) -> Non ancora contato
A42: Annie Bag | B42: PAILLETTES GREY | C42: Annie_Bag_PAILLETTES_GREY | D42: 0 | E42: 0 | F42: DRAFT | H42: =IF(G42="","",G42-D42) | I42: =IF(G42="","Non ancora contato",IF(G42-D42=0,"OK",IF(G42-D42<0,IF(ABS(G42-D42)<3,"Rettifica -"&ABS(G42-D42)&" (GIFT_OFFLINE)","DA VERIFICARE: ammanco "&ABS(G42-D42)),"DA VERIFICARE: surplus +"&(G42-D42)))) -> Non ancora contato
A43: Annie Bag | B43: PAILLETTES LIGHT BLUE | C43: Annie_Bag_PAILLETTES_LIGHT_BLUE | D43: 0 | E43: 0 | F43: ACTIVE | H43: =IF(G43="","",G43-D43) | I43: =IF(G43="","Non ancora contato",IF(G43-D43=0,"OK",IF(G43-D43<0,IF(ABS(G43-D43)<3,"Rettifica -"&ABS(G43-D43)&" (GIFT_OFFLINE)","DA VERIFICARE: ammanco "&ABS(G43-D43)),"DA VERIFICARE: surplus +"&(G43-D43)))) -> Non ancora contato
... A54: Annie Bag | B54: PEARL GREY | C54: Annie_Bag_PEARL_GREY | D54: 1 | E54: 1 | F54: ACTIVE | H54: =IF(G54="","",G54-D54) | I54: =IF(G54="","Non ancora contato",IF(G54-D54=0,"OK",IF(G54-D54<0,IF(ABS(G54-D54)<3,"Rettifica -"&ABS(G54-D54)&" (GIFT_OFFLINE)","DA VERIFICARE: ammanco "&ABS(G54-D54)),"DA VERIFICARE: surplus +"&(G54-D54)))) -> Non ancora contato
A55: Lea Bag | B55: Zebra Pony | C55: Lea_Bag_Zebra_Pony | D55: 8 | E55: n/d | F55: n/d | H55: =IF(G55="","",G55-D55) | I55: =IF(G55="","Non ancora contato",IF(G55-D55=0,"OK",IF(G55-D55<0,IF(ABS(G55-D55)<3,"Rettifica -"&ABS(G55-D55)&" (GIFT_OFFLINE)","DA VERIFICARE: ammanco "&ABS(G55-D55)),"DA VERIFICARE: surplus +"&(G55-D55)))) -> Non ancora contato
A56: Lea Bag | B56: COCCO_ORANGE | C56: Lea_Bag_COCCO_ORANGE | D56: 0 | E56: 0 | F56: ACTIVE | H56: =IF(G56="","",G56-D56) | I56: =IF(G56="","Non ancora contato",IF(G56-D56=0,"OK",IF(G56-D56<0,IF(ABS(G56-D56)<3,"Rettifica -"&ABS(G56-D56)&" (GIFT_OFFLINE)","DA VERIFICARE: ammanco "&ABS(G56-D56)),"DA VERIFICARE: surplus +"&(G56-D56)))) -> Non ancora contato
A57: Lea Bag | B57: COCCO_BEIGE | C57: Lea_Bag_COCCO_BEIGE | D57: 8 | E57: 6 | F57: ACTIVE | H57: =IF(G57="","",G57-D57) | I57: =IF(G57="","Non ancora contato",IF(G57-D57=0,"OK",IF(G57-D57<0,IF(ABS(G57-D57)<3,"Rettifica -"&ABS(G57-D57)&" (GIFT_OFFLINE)","DA VERIFICARE: ammanco "&ABS(G57-D57)),"DA VERIFICARE: surplus +"&(G57-D57)))) -> Non ancora contato
A58: Lea Bag | B58: COCCO_PURPLE | C58: Lea_Bag_COCCO_PURPLE | D58: 4 | E58: 2 | F58: ACTIVE | H58: =IF(G58="","",G58-D58) | I58: =IF(G58="","Non ancora contato",IF(G58-D58=0,"OK",IF(G58-D58<0,IF(ABS(G58-D58)<3,"Rettifica -"&ABS(G58-D58)&" (GIFT_OFFLINE)","DA VERIFICARE: ammanco "&ABS(G58-D58)),"DA VERIFICARE: surplus +"&(G58-D58)))) -> Non ancora contato
A59: Maria Bag | B59: BURRO_PIERCING | C59: Maria_Bag_BURRO_PIERCING | D59: 11 | E59: 9 | F59: ACTIVE | H59: =IF(G59="","",G59-D59) | I59: =IF(G59="","Non ancora contato",IF(G59-D59=0,"OK",IF(G59-D59<0,IF(ABS(G59-D59)<3,"Rettifica -"&ABS(G59-D59)&" (GIFT_OFFLINE)","DA VERIFICARE: ammanco "&ABS(G59-D59)),"DA VERIFICARE: surplus +"&(G59-D59)))) -> Non ancora contato
A60: Lea Bag Maxi | B60: COCCO CHOCOLATE | C60: Lea_Bag_Maxi_COCCO_CHOCOLATE | D60: 7 | E60: 5 | F60: ACTIVE | H60: =IF(G60="","",G60-D60) | I60: =IF(G60="","Non ancora contato",IF(G60-D60=0,"OK",IF(G60-D60<0,IF(ABS(G60-D60)<3,"Rettifica -"&ABS(G60-D60)&" (GIFT_OFFLINE)","DA VERIFICARE: ammanco "&ABS(G60-D60)),"DA VERIFICARE: surplus +"&(G60-D60)))) -> Non ancora contato
A61: Lea Bag | B61: COCCO PINK | C61: Lea_Bag_COCCO_PINK | D61: 3 | E61: 3 | F61: ACTIVE | H61: =IF(G61="","",G61-D61) | I61: =IF(G61="","Non ancora contato",IF(G61-D61=0,"OK",IF(G61-D61<0,IF(ABS(G61-D61)<3,"Rettifica -"&ABS(G61-D61)&" (GIFT_OFFLINE)","DA VERIFICARE: ammanco "&ABS(G61-D61)),"DA VERIFICARE: surplus +"&(G61-D61)))) -> Non ancora contato
A62: Lea Bag | B62: COCCO GREEN | C62: Lea_Bag_COCCO_GREEN | D62: 8 | E62: 6 | F62: ACTIVE | H62: =IF(G62="","",G62-D62) | I62: =IF(G62="","Non ancora contato",IF(G62-D62=0,"OK",IF(G62-D62<0,IF(ABS(G62-D62)<3,"Rettifica -"&ABS(G62-D62)&" (GIFT_OFFLINE)","DA VERIFICARE: ammanco "&ABS(G62-D62)),"DA VERIFICARE: surplus +"&(G62-D62)))) -> Non ancora contato
A63: Agata Bag | B63: ROSE BUTTER | C63: Agata_Bag_ROSE_BUTTER | D63: 1 | E63: 1 | F63: ACTIVE | H63: =IF(G63="","",G63-D63) | I63: =IF(G63="","Non ancora contato",IF(G63-D63=0,"OK",IF(G63-D63<0,IF(ABS(G63-D63)<3,"Rettifica -"&ABS(G63-D63)&" (GIFT_OFFLINE)","DA VERIFICARE: ammanco "&ABS(G63-D63)),"DA VERIFICARE: surplus +"&(G63-D63)))) -> Non ancora contato
A64: Agata Bag | B64: ROSE BUTTER GREEN | C64: Agata_Bag_ROSE_BUTTER_GREEN | D64: 1 | E64: 1 | F64: ACTIVE | H64: =IF(G64="","",G64-D64) | I64: =IF(G64="","Non ancora contato",IF(G64-D64=0,"OK",IF(G64-D64<0,IF(ABS(G64-D64)<3,"Rettifica -"&ABS(G64-D64)&" (GIFT_OFFLINE)","DA VERIFICARE: ammanco "&ABS(G64-D64)),"DA VERIFICARE: surplus +"&(G64-D64)))) -> Non ancora contato
A65: Agata Bag | B65: PAILLETTES PINK | C65: Agata_Bag_PAILLETTES_PINK | D65: 9 | E65: 7 | F65: ACTIVE | H65: =IF(G65="","",G65-D65) | I65: =IF(G65="","Non ancora contato",IF(G65-D65=0,"OK",IF(G65-D65<0,IF(ABS(G65-D65)<3,"Rettifica -"&ABS(G65-D65)&" (GIFT_OFFLINE)","DA VERIFICARE: ammanco "&ABS(G65-D65)),"DA VERIFICARE: surplus +"&(G65-D65)))) -> Non ancora contato
A66: Annie Bag | B66: PAILLETTES BEIGE | C66: Annie_Bag_PAILLETTES_BEIGE | D66: 0 | E66: n/d | F66: n/d | H66: =IF(G66="","",G66-D66) | I66: =IF(G66="","Non ancora contato",IF(G66-D66=0,"OK",IF(G66-D66<0,IF(ABS(G66-D66)<3,"Rettifica -"&ABS(G66-D66)&" (GIFT_OFFLINE)","DA VERIFICARE: ammanco "&ABS(G66-D66)),"DA VERIFICARE: surplus +"&(G66-D66)))) -> Non ancora contato
A67: Nina Bag | B67: STRIPES PETROL BLUE | C67: Nina_Bag_STRIPES_PETROL_BLUE | D67: 31 | E67: 29 | F67: ACTIVE | H67: =IF(G67="","",G67-D67) | I67: =IF(G67="","Non ancora contato",IF(G67-D67=0,"OK",IF(G67-D67<0,IF(ABS(G67-D67)<3,"Rettifica -"&ABS(G67-D67)&" (GIFT_OFFLINE)","DA VERIFICARE: ammanco "&ABS(G67-D67)),"DA VERIFICARE: surplus +"&(G67-D67)))) -> Non ancora contato
A68: Nina Bag | B68: STRIPES ICE GREEN | C68: Nina_Bag_STRIPES_ICE_GREEN | D68: 14 | E68: 12 | F68: ACTIVE | H68: =IF(G68="","",G68-D68) | I68: =IF(G68="","Non ancora contato",IF(G68-D68=0,"OK",IF(G68-D68<0,IF(ABS(G68-D68)<3,"Rettifica -"&ABS(G68-D68)&" (GIFT_OFFLINE)","DA VERIFICARE: ammanco "&ABS(G68-D68)),"DA VERIFICARE: surplus +"&(G68-D68)))) -> Non ancora contato
A69: Nina Bag | B69: STRIPES ORANGE RED | C69: Nina_Bag_STRIPES_ORANGE_RED | D69: 8 | E69: 6 | F69: ACTIVE | H69: =IF(G69="","",G69-D69) | I69: =IF(G69="","Non ancora contato",IF(G69-D69=0,"OK",IF(G69-D69<0,IF(ABS(G69-D69)<3,"Rettifica -"&ABS(G69-D69)&" (GIFT_OFFLINE)","DA VERIFICARE: ammanco "&ABS(G69-D69)),"DA VERIFICARE: surplus +"&(G69-D69)))) -> Non ancora contato
A70: Nina Bag | B70: STRIPES AZURE RED | C70: Nina_Bag_STRIPES_AZURE_RED | D70: 14 | E70: 12 | F70: ACTIVE | H70: =IF(G70="","",G70-D70) | I70: =IF(G70="","Non ancora contato",IF(G70-D70=0,"OK",IF(G70-D70<0,IF(ABS(G70-D70)<3,"Rettifica -"&ABS(G70-D70)&" (GIFT_OFFLINE)","DA VERIFICARE: ammanco "&ABS(G70-D70)),"DA VERIFICARE: surplus +"&(G70-D70)))) -> Non ancora contato
A71: Nina Bag | B71: STRIPES JUNGLE GREEN | C71: Nina_Bag_STRIPES_JUNGLE_GREEN | D71: 18 | E71: 16 | F71: ACTIVE | H71: =IF(G71="","",G71-D71) | I71: =IF(G71="","Non ancora contato",IF(G71-D71=0,"OK",IF(G71-D71<0,IF(ABS(G71-D71)<3,"Rettifica -"&ABS(G71-D71)&" (GIFT_OFFLINE)","DA VERIFICARE: ammanco "&ABS(G71-D71)),"DA VERIFICARE: surplus +"&(G71-D71)))) -> Non ancora contato
A72: Nina Bag | B72: POIS | C72: Nina_Bag_POIS | D72: 14 | E72: 12 | F72: ACTIVE | H72: =IF(G72="","",G72-D72) | I72: =IF(G72="","Non ancora contato",IF(G72-D72=0,"OK",IF(G72-D72<0,IF(ABS(G72-D72)<3,"Rettifica -"&ABS(G72-D72)&" (GIFT_OFFLINE)","DA VERIFICARE: ammanco "&ABS(G72-D72)),"DA VERIFICARE: surplus +"&(G72-D72)))) -> Non ancora contato
A73: Nina Bag Maxi | B73: STRIPES ICE GREEN | C73: Nina_Bag_Maxi_STRIPES_ICE_GREEN | D73: 19 | E73: 17 | F73: ACTIVE | H73: =IF(G73="","",G73-D73) | I73: =IF(G73="","Non ancora contato",IF(G73-D73=0,"OK",IF(G73-D73<0,IF(ABS(G73-D73)<3,"Rettifica -"&ABS(G73-D73)&" (GIFT_OFFLINE)","DA VERIFICARE: ammanco "&ABS(G73-D73)),"DA VERIFICARE: surplus +"&(G73-D73)))) -> Non ancora contato
A74: Nina Bag Maxi | B74: STRIPES ORANGE RED | C74: Nina_Bag_Maxi_STRIPES_ORANGE_RED | D74: 20 | E74: 18 | F74: ACTIVE | H74: =IF(G74="","",G74-D74) | I74: =IF(G74="","Non ancora contato",IF(G74-D74=0,"OK",IF(G74-D74<0,IF(ABS(G74-D74)<3,"Rettifica -"&ABS(G74-D74)&" (GIFT_OFFLINE)","DA VERIFICARE: ammanco "&ABS(G74-D74)),"DA VERIFICARE: surplus +"&(G74-D74)))) -> Non ancora contato
A75: Nina Bag Maxi | B75: STRIPES AZURE RED | C75: Nina_Bag_Maxi_STRIPES_AZURE_RED | D75: 20 | E75: 18 | F75: ACTIVE | H75: =IF(G75="","",G75-D75) | I75: =IF(G75="","Non ancora contato",IF(G75-D75=0,"OK",IF(G75-D75<0,IF(ABS(G75-D75)<3,"Rettifica -"&ABS(G75-D75)&" (GIFT_OFFLINE)","DA VERIFICARE: ammanco "&ABS(G75-D75)),"DA VERIFICARE: surplus +"&(G75-D75)))) -> Non ancora contato
A76: Nina Bag Maxi | B76: STRIPES JUNGLE GREEN | C76: Nina_Bag_Maxi_STRIPES_JUNGLE_GREEN | D76: 23 | E76: 21 | F76: ACTIVE | H76: =IF(G76="","",G76-D76) | I76: =IF(G76="","Non ancora contato",IF(G76-D76=0,"OK",IF(G76-D76<0,IF(ABS(G76-D76)<3,"Rettifica -"&ABS(G76-D76)&" (GIFT_OFFLINE)","DA VERIFICARE: ammanco "&ABS(G76-D76)),"DA VERIFICARE: surplus +"&(G76-D76)))) -> Non ancora contato
A77: Nina Bag Maxi | B77: STRIPES REED | C77: Nina_Bag_Maxi_STRIPES_REED | D77: 30 | E77: 28 | F77: ACTIVE | H77: =IF(G77="","",G77-D77) | I77: =IF(G77="","Non ancora contato",IF(G77-D77=0,"OK",IF(G77-D77<0,IF(ABS(G77-D77)<3,"Rettifica -"&ABS(G77-D77)&" (GIFT_OFFLINE)","DA VERIFICARE: ammanco "&ABS(G77-D77)),"DA VERIFICARE: surplus +"&(G77-D77)))) -> Non ancora contato
A78: Nina Bag Maxi | B78: CHECKS CHERRY YELLOW | C78: Nina_Bag_Maxi_CHECKS_CHERRY_YELLOW | D78: 20 | E78: 18 | F78: ACTIVE | H78: =IF(G78="","",G78-D78) | I78: =IF(G78="","Non ancora contato",IF(G78-D78=0,"OK",IF(G78-D78<0,IF(ABS(G78-D78)<3,"Rettifica -"&ABS(G78-D78)&" (GIFT_OFFLINE)","DA VERIFICARE: ammanco "&ABS(G78-D78)),"DA VERIFICARE: surplus +"&(G78-D78)))) -> Non ancora contato
... A109: Agata Bag | B109: FLORAL LIGHT GREY | C109: Agata_Bag_FLORAL_LIGHT_GREY | D109: 8 | E109: 0 | F109: DRAFT | H109: =IF(G109="","",G109-D109) | I109: =IF(G109="","Non ancora contato",IF(G109-D109=0,"OK",IF(G109-D109<0,IF(ABS(G109-D109)<3,"Rettifica -"&ABS(G109-D109)&" (GIFT_OFFLINE)","DA VERIFICARE: ammanco "&ABS(G109-D109)),"DA VERIFICARE: surplus +"&(G109-D109)))) -> Non ancora contato
A110: Annie Bag | B110: PERSONALIZZAZIONE Matrimonio | C110: Annie_Bag_PERSONALIZZAZIONE_Matrimonio | D110: 0 | E110: n/d | F110: n/d | H110: =IF(G110="","",G110-D110) | I110: =IF(G110="","Non ancora contato",IF(G110-D110=0,"OK",IF(G110-D110<0,IF(ABS(G110-D110)<3,"Rettifica -"&ABS(G110-D110)&" (GIFT_OFFLINE)","DA VERIFICARE: ammanco "&ABS(G110-D110)),"DA VERIFICARE: surplus +"&(G110-D110)))) -> Non ancora contato

Sheet SKU_HISTORY
A1: ts | B1: date | C1: json
A2: 46182.873 | B2: 46182 | C2: {"ts":"2026-06-09 20:57","date":"2026-06-09","total":214,"active":94,"draft":120,"archived":0,"active_instock":77,"active_oos":17,"instock_not_active":5,"var_active_instock":93,"by_line":{"AGATA":{"active":14,"active_instock":8,"active_oos":6},"AIRPODS":{"active":6,"active_instock":6,"active_oos":0},"ANNIE":{"active":11,"active_instock":4,"active_oos":7},"GIFT":{"active":1,"active_instock":0,"active_oos":1},"LAPTOP":{"active":7,"active_instock":7,"active_oos":0},"LEA":{"active":20,"active_instock":17,"active_oos":3},"MARIA":{"active":2,"active_instock":2,"active_oos":0},"MINI":{"active":6,"active_instock":6,"active_oos":0},"NINA":{"active":16,"active_instock":16,"active_oos":0},"SUNGLASS":{"active":6,"active_instock":6,"active_oos":0},"TIGER":{"active":1,"active_instock":1,"active_oos":0},"VALENTINA":{"active":4,"active_instock":4,"active_oos":0}},"by_macro":{"Tessuto":{"active":41,"active_instock":28,"active_oos":13},"Pelle":{"active":26,"active_instock":23,"active_oos":3},"Accessori":{"active":26,"active_instock":26,"active_oos":0},"Altro":{"active":1,"active_instock":0,"active_oos":1}}}
A3: 46182.884 | B3: 46182 | C3: {"ts":"2026-06-09 21:13","date":"2026-06-09","total":214,"active":94,"draft":120,"archived":0,"active_instock":77,"active_oos":17,"instock_not_active":5,"var_active_instock":93,"by_line":{"AGATA":{"active":14,"active_instock":8,"active_oos":6},"AIRPODS":{"active":6,"active_instock":6,"active_oos":0},"ANNIE":{"active":11,"active_instock":4,"active_oos":7},"GIFT":{"active":1,"active_instock":0,"active_oos":1},"LAPTOP":{"active":7,"active_instock":7,"active_oos":0},"LEA":{"active":20,"active_instock":17,"active_oos":3},"MARIA":{"active":2,"active_instock":2,"active_oos":0},"MINI":{"active":6,"active_instock":6,"active_oos":0},"NINA":{"active":16,"active_instock":16,"active_oos":0},"SUNGLASS":{"active":6,"active_instock":6,"active_oos":0},"TIGER":{"active":1,"active_instock":1,"active_oos":0},"VALENTINA":{"active":4,"active_instock":4,"active_oos":0}},"by_macro":{"Tessuto":{"active":41,"active_instock":28,"active_oos":13},"Pelle":{"active":26,"active_instock":23,"active_oos":3},"Accessori":{"active":26,"active_instock":26,"active_oos":0},"Altro":{"active":1,"active_instock":0,"active_oos":1}}}
A4: 46182.919 | B4: 46182 | C4: {"ts":"2026-06-09 22:03","date":"2026-06-09","total":214,"active":94,"draft":120,"archived":0,"active_instock":77,"active_oos":17,"instock_not_active":5,"var_active_instock":93,"by_line":{"AGATA":{"active":14,"active_instock":8,"active_oos":6},"AIRPODS":{"active":6,"active_instock":6,"active_oos":0},"ANNIE":{"active":11,"active_instock":4,"active_oos":7},"GIFT":{"active":1,"active_instock":0,"active_oos":1},"LAPTOP":{"active":7,"active_instock":7,"active_oos":0},"LEA":{"active":20,"active_instock":17,"active_oos":3},"MARIA":{"active":2,"active_instock":2,"active_oos":0},"MINI":{"active":6,"active_instock":6,"active_oos":0},"NINA":{"active":16,"active_instock":16,"active_oos":0},"SUNGLASS":{"active":6,"active_instock":6,"active_oos":0},"TIGER":{"active":1,"active_instock":1,"active_oos":0},"VALENTINA":{"active":4,"active_instock":4,"active_oos":0}},"by_macro":{"Tessuto":{"active":41,"active_instock":28,"active_oos":13},"Pelle":{"active":26,"active_instock":23,"active_oos":3},"Accessori":{"active":26,"active_instock":26,"active_oos":0},"Altro":{"active":1,"active_instock":0,"active_oos":1}}}
A5: 46182.992 | B5: 46182 | C5: {"ts":"2026-06-09 23:48","date":"2026-06-09","total":214,"active":94,"draft":120,"archived":0,"active_instock":79,"active_oos":15,"instock_not_active":5,"var_active_instock":96,"by_line":{"AGATA":{"active":14,"active_instock":8,"active_oos":6},"AIRPODS":{"active":6,"active_instock":6,"active_oos":0},"ANNIE":{"active":11,"active_instock":5,"active_oos":6},"GIFT":{"active":1,"active_instock":0,"active_oos":1},"LAPTOP":{"active":7,"active_instock":7,"active_oos":0},"LEA":{"active":20,"active_instock":18,"active_oos":2},"MARIA":{"active":2,"active_instock":2,"active_oos":0},"MINI":{"active":6,"active_instock":6,"active_oos":0},"NINA":{"active":16,"active_instock":16,"active_oos":0},"SUNGLASS":{"active":6,"active_instock":6,"active_oos":0},"TIGER":{"active":1,"active_instock":1,"active_oos":0},"VALENTINA":{"active":4,"active_instock":4,"active_oos":0}},"by_macro":{"Tessuto":{"active":41,"active_instock":29,"active_oos":12},"Pelle":{"active":26,"active_instock":24,"active_oos":2},"Accessori":{"active":26,"active_instock":26,"active_oos":0},"Altro":{"active":1,"active_instock":0,"active_oos":1}}}
A6: 46183.722 | B6: 46183 | C6: {"ts":"2026-06-10 17:19","date":"2026-06-10","total":214,"active":94,"draft":120,"archived":0,"active_instock":80,"active_oos":14,"instock_not_active":2,"var_active_instock":101,"by_line":{"AGATA":{"active":14,"active_instock":10,"active_oos":4},"AIRPODS":{"active":6,"active_instock":6,"active_oos":0},"ANNIE":{"active":11,"active_instock":7,"active_oos":4},"GIFT":{"active":1,"active_instock":0,"active_oos":1},"LAPTOP":{"active":7,"active_instock":7,"active_oos":0},"LEA":{"active":20,"active_instock":15,"active_oos":5},"MARIA":{"active":2,"active_instock":2,"active_oos":0},"MINI":{"active":6,"active_instock":6,"active_oos":0},"NINA":{"active":16,"active_instock":16,"active_oos":0},"SUNGLASS":{"active":6,"active_instock":6,"active_oos":0},"TIGER":{"active":1,"active_instock":1,"active_oos":0},"VALENTINA":{"active":4,"active_instock":4,"active_oos":0}},"by_macro":{"Tessuto":{"active":41,"active_instock":33,"active_oos":8},"Pelle":{"active":26,"active_instock":21,"active_oos":5},"Accessori":{"active":26,"active_instock":26,"active_oos":0},"Altro":{"active":1,"active_instock":0,"active_oos":1}}}
A7: 46183.928 | B7: 46183 | C7: {"ts":"2026-06-10 22:17","date":"2026-06-10","total":214,"active":94,"draft":120,"archived":0,"active_instock":80,"active_oos":14,"instock_not_active":2,"var_active_instock":101,"by_line":{"AGATA":{"active":14,"active_instock":10,"active_oos":4},"AIRPODS":{"active":6,"active_instock":6,"active_oos":0},"ANNIE":{"active":11,"active_instock":7,"active_oos":4},"GIFT":{"active":1,"active_instock":0,"active_oos":1},"LAPTOP":{"active":7,"active_instock":7,"active_oos":0},"LEA":{"active":20,"active_instock":15,"active_oos":5},"MARIA":{"active":2,"active_instock":2,"active_oos":0},"MINI":{"active":6,"active_instock":6,"active_oos":0},"NINA":{"active":16,"active_instock":16,"active_oos":0},"SUNGLASS":{"active":6,"active_instock":6,"active_oos":0},"TIGER":{"active":1,"active_instock":1,"active_oos":0},"VALENTINA":{"active":4,"active_instock":4,"active_oos":0}},"by_macro":{"Tessuto":{"active":41,"active_instock":33,"active_oos":8},"Pelle":{"active":26,"active_instock":21,"active_oos":5},"Accessori":{"active":26,"active_instock":26,"active_oos":0},"Altro":{"active":1,"active_instock":0,"active_oos":1}}}
A8: 46186.912 | B8: 46186 | C8: {"ts":"2026-06-13 21:54","date":"2026-06-13","total":214,"active":94,"draft":120,"archived":0,"active_instock":79,"active_oos":15,"instock_not_active":2,"var_active_instock":99,"by_line":{"AGATA":{"active":14,"active_instock":10,"active_oos":4},"AIRPODS":{"active":6,"active_instock":6,"active_oos":0},"ANNIE":{"active":11,"active_instock":6,"active_oos":5},"GIFT":{"active":1,"active_instock":0,"active_oos":1},"LAPTOP":{"active":7,"active_instock":7,"active_oos":0},"LEA":{"active":20,"active_instock":15,"active_oos":5},"MARIA":{"active":2,"active_instock":2,"active_oos":0},"MINI":{"active":6,"active_instock":6,"active_oos":0},"NINA":{"active":16,"active_instock":16,"active_oos":0},"SUNGLASS":{"active":6,"active_instock":6,"active_oos":0},"TIGER":{"active":1,"active_instock":1,"active_oos":0},"VALENTINA":{"active":4,"active_instock":4,"active_oos":0}},"by_macro":{"Tessuto":{"active":41,"active_instock":32,"active_oos":9},"Pelle":{"active":26,"active_instock":21,"active_oos":5},"Accessori":{"active":26,"active_instock":26,"active_oos":0},"Altro":{"active":1,"active_instock":0,"active_oos":1}}}
A9: 46187.559 | B9: 46187 | C9: {"ts":"2026-06-14 13:25","date":"2026-06-14","total":214,"active":94,"draft":120,"archived":0,"active_instock":75,"active_oos":19,"instock_not_active":2,"var_active_instock":92,"by_line":{"AGATA":{"active":14,"active_instock":8,"active_oos":6},"AIRPODS":{"active":6,"active_instock":6,"active_oos":0},"ANNIE":{"active":11,"active_instock":5,"active_oos":6},"GIFT":{"active":1,"active_instock":0,"active_oos":1},"LAPTOP":{"active":7,"active_instock":7,"active_oos":0},"LEA":{"active":20,"active_instock":14,"active_oos":6},"MARIA":{"active":2,"active_instock":2,"active_oos":0},"MINI":{"active":6,"active_instock":6,"active_oos":0},"NINA":{"active":16,"active_instock":16,"active_oos":0},"SUNGLASS":{"active":6,"active_instock":6,"active_oos":0},"TIGER":{"active":1,"active_instock":1,"active_oos":0},"VALENTINA":{"active":4,"active_instock":4,"active_oos":0}},"by_macro":{"Tessuto":{"active":41,"active_instock":29,"active_oos":12},"Pelle":{"active":26,"active_instock":20,"active_oos":6},"Accessori":{"active":26,"active_instock":26,"active_oos":0},"Altro":{"active":1,"active_instock":0,"active_oos":1}}}
A10: 46188.559 | B10: 46188 | C10: {"ts":"2026-06-15 13:25","date":"2026-06-15","total":214,"active":94,"draft":120,"archived":0,"active_instock":76,"active_oos":18,"instock_not_active":2,"var_active_instock":94,"by_line":{"AGATA":{"active":14,"active_instock":8,"active_oos":6},"AIRPODS":{"active":6,"active_instock":6,"active_oos":0},"ANNIE":{"active":11,"active_instock":6,"active_oos":5},"GIFT":{"active":1,"active_instock":0,"active_oos":1},"LAPTOP":{"active":7,"active_instock":7,"active_oos":0},"LEA":{"active":20,"active_instock":14,"active_oos":6},"MARIA":{"active":2,"active_instock":2,"active_oos":0},"MINI":{"active":6,"active_instock":6,"active_oos":0},"NINA":{"active":16,"active_instock":16,"active_oos":0},"SUNGLASS":{"active":6,"active_instock":6,"active_oos":0},"TIGER":{"active":1,"active_instock":1,"active_oos":0},"VALENTINA":{"active":4,"active_instock":4,"active_oos":0}},"by_macro":{"Tessuto":{"active":41,"active_instock":30,"active_oos":11},"Pelle":{"active":26,"active_instock":20,"active_oos":6},"Accessori":{"active":26,"active_instock":26,"active_oos":0},"Altro":{"active":1,"active_instock":0,"active_oos":1}}}
A11: 46189.559 | B11: 46189 | C11: {"ts":"2026-06-16 13:25","date":"2026-06-16","total":214,"active":94,"draft":120,"archived":0,"active_instock":76,"active_oos":18,"instock_not_active":2,"var_active_instock":94,"by_line":{"AGATA":{"active":14,"active_instock":8,"active_oos":6},"AIRPODS":{"active":6,"active_instock":6,"active_oos":0},"ANNIE":{"active":11,"active_instock":6,"active_oos":5},"GIFT":{"active":1,"active_instock":0,"active_oos":1},"LAPTOP":{"active":7,"active_instock":7,"active_oos":0},"LEA":{"active":20,"active_instock":14,"active_oos":6},"MARIA":{"active":2,"active_instock":2,"active_oos":0},"MINI":{"active":6,"active_instock":6,"active_oos":0},"NINA":{"active":16,"active_instock":16,"active_oos":0},"SUNGLASS":{"active":6,"active_instock":6,"active_oos":0},"TIGER":{"active":1,"active_instock":1,"active_oos":0},"VALENTINA":{"active":4,"active_instock":4,"active_oos":0}},"by_macro":{"Tessuto":{"active":41,"active_instock":30,"active_oos":11},"Pelle":{"active":26,"active_instock":20,"active_oos":6},"Accessori":{"active":26,"active_instock":26,"active_oos":0},"Altro":{"active":1,"active_instock":0,"active_oos":1}}}
A12: 46190.559 | B12: 46190 | C12: {"ts":"2026-06-17 13:25","date":"2026-06-17","total":214,"active":94,"draft":120,"archived":0,"active_instock":75,"active_oos":19,"instock_not_active":2,"var_active_instock":92,"by_line":{"AGATA":{"active":14,"active_instock":6,"active_oos":8},"AIRPODS":{"active":6,"active_instock":6,"active_oos":0},"ANNIE":{"active":11,"active_instock":7,"active_oos":4},"GIFT":{"active":1,"active_instock":0,"active_oos":1},"LAPTOP":{"active":7,"active_instock":7,"active_oos":0},"LEA":{"active":20,"active_instock":14,"active_oos":6},"MARIA":{"active":2,"active_instock":2,"active_oos":0},"MINI":{"active":6,"active_instock":6,"active_oos":0},"NINA":{"active":16,"active_instock":16,"active_oos":0},"SUNGLASS":{"active":6,"active_instock":6,"active_oos":0},"TIGER":{"active":1,"active_instock":1,"active_oos":0},"VALENTINA":{"active":4,"active_instock":4,"active_oos":0}},"by_macro":{"Tessuto":{"active":41,"active_instock":29,"active_oos":12},"Pelle":{"active":26,"active_instock":20,"active_oos":6},"Accessori":{"active":26,"active_instock":26,"active_oos":0},"Altro":{"active":1,"active_instock":0,"active_oos":1}}}
A13: 46191.559 | B13: 46191 | C13: {"ts":"2026-06-18 13:25","date":"2026-06-18","total":214,"active":94,"draft":120,"archived":0,"active_instock":76,"active_oos":18,"instock_not_active":2,"var_active_instock":90,"by_line":{"AGATA":{"active":14,"active_instock":6,"active_oos":8},"AIRPODS":{"active":6,"active_instock":6,"active_oos":0},"ANNIE":{"active":11,"active_instock":8,"active_oos":3},"GIFT":{"active":1,"active_instock":0,"active_oos":1},"LAPTOP":{"active":7,"active_instock":7,"active_oos":0},"LEA":{"active":20,"active_instock":14,"active_oos":6},"MARIA":{"active":2,"active_instock":2,"active_oos":0},"MINI":{"active":6,"active_instock":6,"active_oos":0},"NINA":{"active":16,"active_instock":16,"active_oos":0},"SUNGLASS":{"active":6,"active_instock":6,"active_oos":0},"TIGER":{"active":1,"active_instock":1,"active_oos":0},"VALENTINA":{"active":4,"active_instock":4,"active_oos":0}},"by_macro":{"Tessuto":{"active":41,"active_instock":30,"active_oos":11},"Pelle":{"active":26,"active_instock":20,"active_oos":6},"Accessori":{"active":26,"active_instock":26,"active_oos":0},"Altro":{"active":1,"active_instock":0,"active_oos":1}}}
... A27: 46205.559 | B27: 46205 | C27: {"ts":"2026-07-02 13:25","date":"2026-07-02","total":218,"active":93,"draft":125,"archived":0,"active_instock":71,"active_oos":22,"instock_not_active":2,"var_active_instock":80,"by_line":{"AGATA":{"active":16,"active_instock":5,"active_oos":11},"AIRPODS":{"active":6,"active_instock":6,"active_oos":0},"ANNIE":{"active":10,"active_instock":4,"active_oos":6},"GIFT":{"active":1,"active_instock":0,"active_oos":1},"LAPTOP":{"active":7,"active_instock":7,"active_oos":0},"LEA":{"active":15,"active_instock":11,"active_oos":4},"MARIA":{"active":5,"active_instock":5,"active_oos":0},"MINI":{"active":6,"active_instock":6,"active_oos":0},"NINA":{"active":16,"active_instock":16,"active_oos":0},"SUNGLASS":{"active":6,"active_instock":6,"active_oos":0},"TIGER":{"active":1,"active_instock":1,"active_oos":0},"VALENTINA":{"active":4,"active_instock":4,"active_oos":0}},"by_macro":{"Tessuto":{"active":42,"active_instock":25,"active_oos":17},"Pelle":{"active":24,"active_instock":20,"active_oos":4},"Accessori":{"active":26,"active_instock":26,"active_oos":0},"Altro":{"active":1,"active_instock":0,"active_oos":1}}}

Sheet CATALOG_SYNC_V2
A1: Product_Name | B1: Product_ID | C1: Variant_ID | D1: InventoryItem_ID | E1: Location_ID | F1: CODICE_AMIIMI | G1: Note | H1: Handle | I1: SKIP | J1: CONTA_VERIFICATA
A2: AIRPODS CASE CANDY PINK | B2: gid://shopify/Product/10795764023623 | C2: gid://shopify/ProductVariant/53909681406279 | D2: gid://shopify/InventoryItem/55500846301511 | E2: gid://shopify/Location/107986518343 | F2: Airpod_Cover_7X9_STRIPES_CANDY_PINK | H2: airpods-case-stripes-pink-olive
A3: AIRPODS CASE CHERRY PINK | B3: gid://shopify/Product/10795764220231 | C3: gid://shopify/ProductVariant/53909681701191 | D3: gid://shopify/InventoryItem/55500846596423 | E3: gid://shopify/Location/107986518343 | F3: Airpod_Cover_7X9_CHECKS_CHERRY_PINK | H3: airpods-case-checks-cherry-pink
A4: AIRPODS CASE FOREST GREEN | B4: gid://shopify/Product/10795764252999 | C4: gid://shopify/ProductVariant/53909681733959 | D4: gid://shopify/InventoryItem/55500846629191 | E4: gid://shopify/Location/107986518343 | F4: Airpod_Cover_7X9_CHECKS_FOREST_GREEN | H4: airpods-case-checks-olive-cream
A5: AIRPODS CASE LIGHT BLUE | B5: gid://shopify/Product/10795764154695 | C5: gid://shopify/ProductVariant/53909681602887 | D5: gid://shopify/InventoryItem/55500846498119 | E5: gid://shopify/Location/107986518343 | F5: Airpod_Cover_7X9_STRIPES_LIGHT_BLUE | H5: airpods-case-stripes-azure-red
A6: AIRPODS CASE LIME PINK | B6: gid://shopify/Product/10795763990855 | C6: gid://shopify/ProductVariant/53909681373511 | D6: gid://shopify/InventoryItem/55500846268743 | E6: gid://shopify/Location/107986518343 | F6: Airpod_Cover_7X9_STRIPES_LIME_PINK | H6: airpods-case-stripes-mustard-rose
A7: AIRPODS CASE RED | B7: gid://shopify/Product/10795764121927 | C7: gid://shopify/ProductVariant/53909681570119 | D7: gid://shopify/InventoryItem/55500846465351 | E7: gid://shopify/Location/107986518343 | F7: Airpod_Cover_7X9_STRIPES_RED | H7: airpods-case-stripes-reed
A8: LAPTOP COVER CANDY PINK | B8: gid://shopify/Product/10795763564871 | C8: gid://shopify/ProductVariant/53909680750919 | D8: gid://shopify/InventoryItem/55500845646151 | E8: gid://shopify/Location/107986518343 | F8: Laptop_Cover_26X37_STRIPES_CANDY_PINK | H8: laptop-cover-stripes-pink-olive
A9: LAPTOP COVER CHECKS ORANGE | B9: gid://shopify/Product/10795763794247 | C9: gid://shopify/ProductVariant/53909681209671 | D9: gid://shopify/InventoryItem/55500846104903 | E9: gid://shopify/Location/107986518343 | F9: Laptop_Cover_26X37_CHECKS_ORANGE | H9: laptop-cover-checks-cherry-yellow
A10: LAPTOP COVER CHERRY PINK | B10: gid://shopify/Product/10795763695943 | C10: gid://shopify/ProductVariant/53909681013063 | D10: gid://shopify/InventoryItem/55500845908295 | E10: gid://shopify/Location/107986518343 | F10: Laptop_Cover_26X37_STRIPES_CHERRY_PINK | H10: laptop-cover-stripes-cherry-pink
A11: LAPTOP COVER FOREST GREEN | B11: gid://shopify/Product/10795763761479 | C11: gid://shopify/ProductVariant/53909681078599 | D11: gid://shopify/InventoryItem/55500845973831 | E11: gid://shopify/Location/107986518343 | F11: Laptop_Cover_26X37_STRIPES_FOREST_GREEN | H11: laptop-cover-stripes-olive-cream
A12: LAPTOP COVER LIGHT BLUE | B12: gid://shopify/Product/10795763663175 | C12: gid://shopify/ProductVariant/53909680980295 | D12: gid://shopify/InventoryItem/55500845875527 | E12: gid://shopify/Location/107986518343 | F12: Laptop_Cover_26X37_STRIPES_LIGHT_BLUE | H12: laptop-cover-stripes-azure-red
A13: LAPTOP COVER LIME PINK | B13: gid://shopify/Product/10795763466567 | C13: gid://shopify/ProductVariant/53909680652615 | D13: gid://shopify/InventoryItem/55500845547847 | E13: gid://shopify/Location/107986518343 | F13: Laptop_Cover_26X37_STRIPES_LIME_PINK | H13: laptop-cover-stripes-mustard-rose
A14: LAPTOP COVER RED | B14: gid://shopify/Product/10795763630407 | C14: gid://shopify/ProductVariant/53909680849223 | D14: gid://shopify/InventoryItem/55500845744455 | E14: gid://shopify/Location/107986518343 | F14: Laptop_Cover_26X37_STRIPES_RED | H14: laptop-cover-stripes-reed
A15: LEA BAG BLACK COCCO | B15: gid://shopify/Product/10606557659463 | C15: gid://shopify/ProductVariant/53147874820423 | D15: gid://shopify/InventoryItem/54729895018823 | E15: gid://shopify/Location/107986518343 | F15: Lea_Bag_COCCO_BLACK | H15: lea-bag-cocco-black | J15: 46182.625
A16: LEA BAG BLACK PONY | B16: gid://shopify/Product/10606560084295 | C16: gid://shopify/ProductVariant/53147885240647 | D16: gid://shopify/InventoryItem/54729905275207 | E16: gid://shopify/Location/107986518343 | F16: Lea_Bag_BLACK | H16: lea-bag-black
A17: LEA BAG COCCO BEIGE | B17: gid://shopify/Product/10801084105031 | C17: gid://shopify/ProductVariant/53934512570695 | D17: gid://shopify/InventoryItem/55525765316935 | E17: gid://shopify/Location/107986518343 | F17: Lea_Bag_COCCO_BEIGE | H17: lea-bag-cocco-beige | J17: 46182.625
A18: LEA BAG COCCO GREEN | B18: gid://shopify/Product/10801085153607 | C18: gid://shopify/ProductVariant/53934518534471 | D18: gid://shopify/InventoryItem/55525771280711 | E18: gid://shopify/Location/107986518343 | F18: Lea_Bag_COCCO_GREEN | H18: lea-bag-cocco-green
A19: LEA BAG COCCO PINK | B19: gid://shopify/Product/10801084989767 | C19: gid://shopify/ProductVariant/53934518272327 | D19: gid://shopify/InventoryItem/55525771018567 | E19: gid://shopify/Location/107986518343 | F19: Lea_Bag_COCCO_PINK | H19: lea-bag-cocco-pink | J19: 46182.625
A20: LEA BAG COCCO PURPLE | B20: gid://shopify/Product/10801084629319 | C20: gid://shopify/ProductVariant/53934515290439 | D20: gid://shopify/InventoryItem/55525768036679 | E20: gid://shopify/Location/107986518343 | F20: Lea_Bag_COCCO_PURPLE | H20: lea-bag-cocco-purple | J20: 46182.625
A21: LEA BAG DARK ZEBRA PONY | B21: gid://shopify/Product/10606554874183 | C21: gid://shopify/ProductVariant/53147865547079 | D21: gid://shopify/InventoryItem/54729885909319 | E21: gid://shopify/Location/107986518343 | F21: Lea_Bag_Zebra_Dark | H21: lea-bag-dark-zebra-1 | J21: 46182.625
A22: LEA BAG LIGHT BROWN PONY | B22: gid://shopify/Product/10606560641351 | C22: gid://shopify/ProductVariant/53147885994311 | D22: gid://shopify/InventoryItem/54729905996103 | E22: gid://shopify/Location/107986518343 | F22: Lea_Bag_Cavallino_Light_Brown | H22: lea-bag-marron-chocolate | J22: 46182.625
A23: LEA BAG MAXI COCCO BLACK | B23: gid://shopify/Product/10695941652807 | C23: gid://shopify/ProductVariant/53495138058567 | D23: gid://shopify/InventoryItem/55079187611975 | E23: gid://shopify/Location/107986518343 | F23: Lea_Bag_Maxi_COCCO_BLACK | H23: lea-bag-maxi-cocco-black | J23: 46182.625
A24: LEA BAG MAXI COCCO CHOCOLATE | B24: gid://shopify/Product/10801081811271 | C24: gid://shopify/ProductVariant/53934503297351 | D24: gid://shopify/InventoryItem/55525756043591 | E24: gid://shopify/Location/107986518343 | F24: Lea_Bag_Maxi_COCCO_CHOCOLATE | H24: lea-bag-maxi-cocco-chocolate
A25: LEA BAG MAXI SUEDE CHOCOLATE | B25: gid://shopify/Product/10695954596167 | C25: gid://shopify/ProductVariant/53495186784583 | D25: gid://shopify/InventoryItem/55079238041927 | E25: gid://shopify/Location/107986518343 | F25: Lea_Bag_Maxi_SUEDE_CHOCOLATE | H25: lea-bag-maxi-suede-chocolate
A26: LEA BAG MAXI SUEDE CHOCOLATE CHARM | B26: gid://shopify/Product/10695962362183 | C26: gid://shopify/ProductVariant/53495234134343 | D26: gid://shopify/InventoryItem/55079286309191 | E26: gid://shopify/Location/107986518343 | F26: Lea_Bag_Maxi_SUEDE_CHOCOLATE_CHARM | H26: lea-bag-maxi-suede-chocolate-charm | J26: 46182.625
A27: LEA BAG RED PATENT | B27: gid://shopify/Product/10606559625543 | C27: gid://shopify/ProductVariant/53147884519751 | D27: gid://shopify/InventoryItem/54729904685383 | E27: gid://shopify/Location/107986518343 | F27: Lea_Bag_RED_PATENT | H27: lea-bag-vernice-rosso | J27: 46182.625
A28: LEA BAG SAVANA LEOPARD PONY | B28: gid://shopify/Product/10606560674119 | C28: gid://shopify/ProductVariant/53147886027079 | D28: gid://shopify/InventoryItem/54729906028871 | E28: gid://shopify/Location/107986518343 | F28: Lea_Bag_LEOPARDO_SAVANA | H28: lea-bag-leopardo | J28: 46182.625
A29: LEA BAG VERNICE PURPLE PATENT | B29: gid://shopify/Product/10606559035719 | C29: gid://shopify/ProductVariant/53147880587591 | D29: gid://shopify/InventoryItem/54729900753223 | E29: gid://shopify/Location/107986518343 | F29: Lea_Bag_VERNICE_PURPLE_PATENT | H29: lea-bag-vernice-viola-malva | J29: 46182.625
A30: MARIA BAG BLACK PIERCING | B30: gid://shopify/Product/10868713947463 | C30: gid://shopify/ProductVariant/54213275517255 | D30: gid://shopify/InventoryItem/55808339050823 | E30: gid://shopify/Location/107986518343 | F30: Maria_Bag_BLACK_PIERCING | H30: maria-bag-black-piercing
A31: MARIA BAG BURRO PIERCING | B31: gid://shopify/Product/10801086366023 | C31: gid://shopify/ProductVariant/53934519648583 | D31: gid://shopify/InventoryItem/55525772394823 | E31: gid://shopify/Location/107986518343 | F31: Maria_Bag_BURRO_PIERCING | H31: maria-bag-burro-piercing
A32: MARIA BAG GREEN PIERCING | B32: gid://shopify/Product/10868713619783 | C32: gid://shopify/ProductVariant/54213275091271 | D32: gid://shopify/InventoryItem/55808338624839 | E32: gid://shopify/Location/107986518343 | F32: Maria_Bag_GREEN_PIERCING | H32: maria-bag-green-piercing
A33: MARIA BAG ICE BLUE PIERCING | B33: gid://shopify/Product/10868713849159 | C33: gid://shopify/ProductVariant/54213275418951 | D33: gid://shopify/InventoryItem/55808338952519 | E33: gid://shopify/Location/107986518343 | F33: Maria_Bag_ICE_BLUE_PIERCING | H33: maria-bag-ice-blue-piercing
A34: MARIA BAG RED PIERCING | B34: gid://shopify/Product/10655260410183 | C34: gid://shopify/ProductVariant/53347013067079 | D34: gid://shopify/InventoryItem/54930251317575 | E34: gid://shopify/Location/107986518343 | F34: Maria_Bag_RED_PIERCING | H34: maria-bag-bordeaux | J34: 46182.625
A35: MINI CASE CANDY PINK | B35: gid://shopify/Product/10795764351303 | C35: gid://shopify/ProductVariant/53909682323783 | D35: gid://shopify/InventoryItem/55500847219015 | E35: gid://shopify/Location/107986518343 | F35: Airpod_Cover_9X11_STRIPES_CANDY_PINK | H35: mini-case-stripes-pink-olive
A36: MINI CASE CHERRY PINK | B36: gid://shopify/Product/10795764482375 | C36: gid://shopify/ProductVariant/53909682422087 | D36: gid://shopify/InventoryItem/55500847317319 | E36: gid://shopify/Location/107986518343 | F36: Airpod_Cover_9X11_CHECKS_CHERRY_PINK | H36: mini-case-checks-cherry-pink
A37: MINI CASE FOREST GREEN | B37: gid://shopify/Product/10795764613447 | C37: gid://shopify/ProductVariant/53909682553159 | D37: gid://shopify/InventoryItem/55500847448391 | E37: gid://shopify/Location/107986518343 | F37: Airpod_Cover_9X11_CHECKS_FOREST_GREEN | H37: mini-case-checks-olive-cream
A38: MINI CASE LIGHT BLUE | B38: gid://shopify/Product/10795764449607 | C38: gid://shopify/ProductVariant/53909682389319 | D38: gid://shopify/InventoryItem/55500847284551 | E38: gid://shopify/Location/107986518343 | F38: Airpod_Cover_9X11_STRIPES_LIGHT_BLUE | H38: mini-case-stripes-azure-red
A39: MINI CASE LIME PINK | B39: gid://shopify/Product/10795764285767 | C39: gid://shopify/ProductVariant/53909682258247 | D39: gid://shopify/InventoryItem/55500847153479 | E39: gid://shopify/Location/107986518343 | F39: Airpod_Cover_9X11_STRIPES_LIME_PINK | H39: mini-case-stripes-mustard-rose
A40: MINI CASE RED | B40: gid://shopify/Product/10795764384071 | C40: gid://shopify/ProductVariant/53909682356551 | D40: gid://shopify/InventoryItem/55500847251783 | E40: gid://shopify/Location/107986518343 | F40: Airpod_Cover_9X11_STRIPES_RED | H40: mini-case-stripes-reed
A41: NINA BAG CHECKS NAVY BLUE | B41: gid://shopify/Product/10606555234631 | C41: gid://shopify/ProductVariant/53147866169671 | D41: gid://shopify/InventoryItem/54729886564679 | E41: gid://shopify/Location/107986518343 | F41: Nina_Bag_Checks_Navy_Blue | H41: nina-bag-checks-navy-blue
A42: NINA BAG ICE | B42: gid://shopify/Product/10795765760327 | C42: gid://shopify/ProductVariant/53909684617543 | D42: gid://shopify/InventoryItem/55500849512775 | E42: gid://shopify/Location/107986518343 | F42: Nina_Bag_STRIPES_ICE_GREEN | H42: nina-bag-stripes-ice-green
A43: NINA BAG JUNGLE GREEN | B43: gid://shopify/Product/10795765858631 | C43: gid://shopify/ProductVariant/53909684715847 | D43: gid://shopify/InventoryItem/55500849611079 | E43: gid://shopify/Location/107986518343 | F43: Nina_Bag_STRIPES_JUNGLE_GREEN | H43: nina-bag-stripes-jungle-green
A44: NINA BAG LIGHT BLUE | B44: gid://shopify/Product/10795765825863 | C44: gid://shopify/ProductVariant/53909684683079 | D44: gid://shopify/InventoryItem/55500849578311 | E44: gid://shopify/Location/107986518343 | F44: Nina_Bag_STRIPES_AZURE_RED | H44: nina-bag-stripes-azure-red
A45: NINA BAG MAXI CHECK ORANGE | B45: gid://shopify/Product/10795766481223 | C45: gid://shopify/ProductVariant/53909686124871 | D45: gid://shopify/InventoryItem/55500851020103 | E45: gid://shopify/Location/107986518343 | F45: Nina_Bag_Maxi_CHECKS_CHERRY_YELLOW | H45: nina-bag-maxi-checks-cherry-yellow
A46: NINA BAG MAXI ICE | B46: gid://shopify/Product/10795766120775 | C46: gid://shopify/ProductVariant/53909685502279 | D46: gid://shopify/InventoryItem/55500850397511 | E46: gid://shopify/Location/107986518343 | F46: Nina_Bag_Maxi_STRIPES_ICE_GREEN | H46: nina-bag-maxi-stripes-ice-green
... A67: VALENTINA BAG RED | B67: gid://shopify/Product/10606561296711 | C67: gid://shopify/ProductVariant/53147888222535 | D67: gid://shopify/InventoryItem/54729908191559 | E67: gid://shopify/Location/107986518343 | F67: Valentina_Bag_RED | H67: valentina-bag

Sheet VARIANT_SYNC_V2_LOG
A1: Timestamp | B1: Type | C1: Bag | D1: Detail
A2: 46181.557 | B2: BUILD_MAP_V2 | D2: VARIANT_SYNC_V2 built: 23 bags, 0 senza CODICE risolto
A3: 46181.558 | B3: BUILD_MAP_V2 | D3: VARIANT_SYNC_V2 built: 23 bags, 0 senza CODICE risolto
A4: 46181.559 | B4: SIMULATE | C4: AGATA BAG FLORAL BORDEAUX EMBROIDERY | D4: 1 -> 2 (Agata_Bag_FLORAL_BORDEAUX_EMBROIDERY)
A5: 46181.559 | B5: SIMULATE | C5: AGATA BAG FLORAL DUSTY PINK EMBROIDERY | D5: 3 -> 5 (Agata_Bag_FLORAL_DUSTY_PINK_EMBROIDERY)
A6: 46181.559 | B6: SIMULATE | C6: AGATA BAG FLORAL GREEN EMBROIDERY | D6: 0 -> 1 (Agata_Bag_FLORAL_GREEN_EMBROIDERY)
A7: 46181.559 | B7: SKIP_NOT_IN_INV | C7: AGATA BAG FLORAL ORANGE EMBROIDERY | D7: CODICE Agata_Bag_floral_orange_embroidery assente in INVENTARIO
A8: 46181.559 | B8: CLAMP_NEG | C8: AGATA BAG FLORAL PINK EMBROIDERY | D8: INVENTARIO -2 -> 0 (Agata_Bag_FLORAL_PINK_EMBROIDERY)
A9: 46181.559 | B9: SIMULATE | C9: AGATA BAG PAILLETTES PINK | D9: 1 -> 9 (Agata_Bag_PAILLETTES_PINK)
A10: 46181.559 | B10: SIMULATE | C10: AGATA BAG ROSE PINK | D10: 1 -> 3 (Agata_Bag_ROSE_PINK)
A11: 46181.559 | B11: SIMULATE | C11: AGATA BAG TIE DYE PINK | D11: 3 -> 4 (Agata_Bag_TIE_DYE_PINK)
A12: 46181.559 | B12: SIMULATE | C12: ANNIE BAG BLUE | D12: 1 -> 7 (Annie_Bag_BLUE)
A13: 46181.559 | B13: SKIP_NOT_IN_INV | C13: ANNIE BAG LILAC | D13: CODICE Annie_Bag_LILAC assente in INVENTARIO
A14: 46181.559 | B14: SIMULATE | C14: ANNIE BAG PAILLETTES LIGHT BLUE | D14: 0 -> 5 (Annie_Bag_PAILLETTES_LIGHT_BLUE)
A15: 46181.559 | B15: SIMULATE | C15: ANNIE BAG PAILLETTES LIGHT GREEN | D15: 0 -> 1 (Annie_Bag_PAILLETTES_LIGHT_GREEN)
... A22: 46181.559 | B22: SKIP_NOT_IN_INV | C22: ANNIE BAG STRIPES PINK | D22: CODICE Annie_Bag_STRIPES_PINK assente in INVENTARIO
A23: 46181.559 | B23: RECONCILE_DONE | D23: [DRY-RUN] reconcile V2 — simulate=12, noop=7, skip=3, flagged=1, errors=0
A24: 46181.676 | B24: FLAG_VERIFICA2 | C24: AGATA BAG FLORAL BORDEAUX EMBROIDERY | D24: gestionale 2 -> sito 1 (Agata_Bag_FLORAL_BORDEAUX_EMBROIDERY)
A25: 46181.676 | B25: FLAG_VERIFICA2 | C25: AGATA BAG FLORAL GREY | D25: gestionale 2 -> sito 1 (Agata_Bag_FLORAL_GREY)
A26: 46181.676 | B26: SKIP_NOT_IN_INV | C26: AGATA BAG FLORAL ORANGE EMBROIDERY | D26: CODICE Agata_Bag_floral_orange_embroidery assente in INVENTARIO
A27: 46181.676 | B27: FLAG_NEGATIVO | C27: AGATA BAG FLORAL PINK EMBROIDERY | D27: gestionale -2 -> sito 0 (Agata_Bag_FLORAL_PINK_EMBROIDERY)
A28: 46181.676 | B28: CHANGE_SKIPPED | C28: AGATA BAG PAILLETTES PINK | D28: sito 1 -> 7 (delta 6) — safe-mode: NON applicato, rivedi
A29: 46181.676 | B29: FLAG_VERIFICA2 | C29: AGATA BAG ROSE BLUE | D29: gestionale 2 -> sito 1 (Agata_Bag_ROSE_BLUE)
A30: 46181.676 | B30: SET | C30: AGATA BAG ROSE BLUE | D30: 2 -> 1
A31: 46181.676 | B31: FLAG_VERIFICA2 | C31: AGATA BAG ROSE BUTTER | D31: gestionale 2 -> sito 1 (Agata_Bag_ROSE_BUTTER)
A32: 46181.676 | B32: SET | C32: AGATA BAG ROSE BUTTER | D32: 2 -> 1
A33: 46181.676 | B33: SET | C33: AGATA BAG ROSE BUTTER GREEN | D33: 5 -> 3
A34: 46181.676 | B34: SET | C34: AGATA BAG TIE DYE PINK | D34: 3 -> 2
A35: 46181.676 | B35: CHANGE_SKIPPED | C35: ANNIE BAG BLUE | D35: sito 1 -> 5 (delta 4) — safe-mode: NON applicato, rivedi
... A43: 46181.676 | B43: SKIP_NOT_IN_INV | C43: ANNIE BAG STRIPES PINK | D43: CODICE Annie_Bag_STRIPES_PINK assente in INVENTARIO
A44: 46181.676 | B44: RECONCILE_DONE | D44: [APPLY] reconcile V2 — set=4, noop=10, skip=3, flagged=6, errors=0
A45: 46181.696 | B45: FLAG_VERIFICA2 | C45: AGATA BAG FLORAL BORDEAUX EMBROIDERY | D45: gestionale 2 -> sito 1 (Agata_Bag_FLORAL_BORDEAUX_EMBROIDERY)
A46: 46181.696 | B46: FLAG_VERIFICA2 | C46: AGATA BAG FLORAL GREY | D46: gestionale 2 -> sito 1 (Agata_Bag_FLORAL_GREY)
A47: 46181.696 | B47: SKIP_NOT_IN_INV | C47: AGATA BAG FLORAL ORANGE EMBROIDERY | D47: CODICE Agata_Bag_floral_orange_embroidery assente in INVENTARIO
A48: 46181.696 | B48: FLAG_NEGATIVO | C48: AGATA BAG FLORAL PINK EMBROIDERY | D48: gestionale -2 -> sito 0 (Agata_Bag_FLORAL_PINK_EMBROIDERY)
A49: 46181.696 | B49: CHANGE_SKIPPED | C49: AGATA BAG PAILLETTES PINK | D49: sito 1 -> 7 (delta 6) — safe-mode: NON applicato, rivedi
A50: 46181.696 | B50: FLAG_VERIFICA2 | C50: AGATA BAG ROSE BLUE | D50: gestionale 2 -> sito 1 (Agata_Bag_ROSE_BLUE)
A51: 46181.696 | B51: FLAG_VERIFICA2 | C51: AGATA BAG ROSE BUTTER | D51: gestionale 2 -> sito 1 (Agata_Bag_ROSE_BUTTER)
A52: 46181.696 | B52: CHANGE_SKIPPED | C52: ANNIE BAG BLUE | D52: sito 1 -> 5 (delta 4) — safe-mode: NON applicato, rivedi
A53: 46181.696 | B53: SKIP_NOT_IN_INV | C53: ANNIE BAG LILAC | D53: CODICE Annie_Bag_LILAC assente in INVENTARIO
A54: 46181.696 | B54: CHANGE_SKIPPED | C54: ANNIE BAG PAILLETTES LIGHT BLUE | D54: sito 0 -> 3 (delta 3) — safe-mode: NON applicato, rivedi
A55: 46181.696 | B55: FLAG_NEGATIVO | C55: ANNIE BAG PAILLETTES NUDE | D55: gestionale -3 -> sito 0 (Annie_Bag_PAILLETTES_NUDE)
A56: 46181.697 | B56: CHANGE_SKIPPED | C56: ANNIE BAG PAILLETTES PINK | D56: sito 0 -> 6 (delta 6) — safe-mode: NON applicato, rivedi
... A60: 46181.697 | B60: SKIP_NOT_IN_INV | C60: ANNIE BAG STRIPES PINK | D60: CODICE Annie_Bag_STRIPES_PINK assente in INVENTARIO
A61: 46181.697 | B61: RECONCILE_DONE | D61: [APPLY] reconcile V2 — set=0, noop=14, skip=3, flagged=6, errors=0
A62: 46181.738 | B62: FLAG_VERIFICA2 | C62: AGATA BAG FLORAL BORDEAUX EMBROIDERY | D62: gestionale 2 -> sito 1 (Agata_Bag_FLORAL_BORDEAUX_EMBROIDERY)
A63: 46181.738 | B63: FLAG_VERIFICA2 | C63: AGATA BAG FLORAL GREY | D63: gestionale 2 -> sito 1 (Agata_Bag_FLORAL_GREY)
A64: 46181.738 | B64: SKIP_NOT_IN_INV | C64: AGATA BAG FLORAL ORANGE EMBROIDERY | D64: CODICE Agata_Bag_floral_orange_embroidery assente in INVENTARIO
A65: 46181.738 | B65: FLAG_NEGATIVO | C65: AGATA BAG FLORAL PINK EMBROIDERY | D65: gestionale -2 -> sito 0 (Agata_Bag_FLORAL_PINK_EMBROIDERY)
A66: 46181.738 | B66: CHANGE_SKIPPED | C66: AGATA BAG PAILLETTES PINK | D66: sito 1 -> 7 (delta 6) — safe-mode: NON applicato, rivedi
A67: 46181.738 | B67: FLAG_VERIFICA2 | C67: AGATA BAG ROSE BLUE | D67: gestionale 2 -> sito 1 (Agata_Bag_ROSE_BLUE)
A68: 46181.738 | B68: FLAG_VERIFICA2 | C68: AGATA BAG ROSE BUTTER | D68: gestionale 2 -> sito 1 (Agata_Bag_ROSE_BUTTER)
A69: 46181.738 | B69: CHANGE_SKIPPED | C69: ANNIE BAG BLUE | D69: sito 1 -> 5 (delta 4) — safe-mode: NON applicato, rivedi
A70: 46181.738 | B70: SKIP_NOT_IN_INV | C70: ANNIE BAG LILAC | D70: CODICE Annie_Bag_LILAC assente in INVENTARIO
A71: 46181.738 | B71: CHANGE_SKIPPED | C71: ANNIE BAG PAILLETTES LIGHT BLUE | D71: sito 0 -> 3 (delta 3) — safe-mode: NON applicato, rivedi
A72: 46181.738 | B72: FLAG_NEGATIVO | C72: ANNIE BAG PAILLETTES NUDE | D72: gestionale -3 -> sito 0 (Annie_Bag_PAILLETTES_NUDE)
A73: 46181.738 | B73: CHANGE_SKIPPED | C73: ANNIE BAG PAILLETTES PINK | D73: sito 0 -> 6 (delta 6) — safe-mode: NON applicato, rivedi
... A77: 46181.738 | B77: SKIP_NOT_IN_INV | C77: ANNIE BAG STRIPES PINK | D77: CODICE Annie_Bag_STRIPES_PINK assente in INVENTARIO
A78: 46181.738 | B78: RECONCILE_DONE | D78: [APPLY] reconcile V2 — set=0, noop=14, skip=3, flagged=6, errors=0
A79: 46181.78 | B79: FLAG_VERIFICA2 | C79: AGATA BAG FLORAL BORDEAUX EMBROIDERY | D79: gestionale 2 -> sito 1 (Agata_Bag_FLORAL_BORDEAUX_EMBROIDERY)
A80: 46181.78 | B80: FLAG_VERIFICA2 | C80: AGATA BAG FLORAL GREY | D80: gestionale 2 -> sito 1 (Agata_Bag_FLORAL_GREY)
A81: 46181.78 | B81: SKIP_NOT_IN_INV | C81: AGATA BAG FLORAL ORANGE EMBROIDERY | D81: CODICE Agata_Bag_floral_orange_embroidery assente in INVENTARIO
A82: 46181.78 | B82: FLAG_NEGATIVO | C82: AGATA BAG FLORAL PINK EMBROIDERY | D82: gestionale -2 -> sito 0 (Agata_Bag_FLORAL_PINK_EMBROIDERY)
A83: 46181.78 | B83: CHANGE_SKIPPED | C83: AGATA BAG PAILLETTES PINK | D83: sito 1 -> 7 (delta 6) — safe-mode: NON applicato, rivedi
A84: 46181.78 | B84: FLAG_VERIFICA2 | C84: AGATA BAG ROSE BLUE | D84: gestionale 2 -> sito 1 (Agata_Bag_ROSE_BLUE)
A85: 46181.78 | B85: FLAG_VERIFICA2 | C85: AGATA BAG ROSE BUTTER | D85: gestionale 2 -> sito 1 (Agata_Bag_ROSE_BUTTER)
A86: 46181.78 | B86: CHANGE_SKIPPED | C86: ANNIE BAG BLUE | D86: sito 1 -> 5 (delta 4) — safe-mode: NON applicato, rivedi
A87: 46181.78 | B87: SKIP_NOT_IN_INV | C87: ANNIE BAG LILAC | D87: CODICE Annie_Bag_LILAC assente in INVENTARIO
A88: 46181.78 | B88: CHANGE_SKIPPED | C88: ANNIE BAG PAILLETTES LIGHT BLUE | D88: sito 0 -> 3 (delta 3) — safe-mode: NON applicato, rivedi
A89: 46181.78 | B89: FLAG_NEGATIVO | C89: ANNIE BAG PAILLETTES NUDE | D89: gestionale -3 -> sito 0 (Annie_Bag_PAILLETTES_NUDE)
A90: 46181.78 | B90: CHANGE_SKIPPED | C90: ANNIE BAG PAILLETTES PINK | D90: sito 0 -> 6 (delta 6) — safe-mode: NON applicato, rivedi
... A94: 46181.78 | B94: SKIP_NOT_IN_INV | C94: ANNIE BAG STRIPES PINK | D94: CODICE Annie_Bag_STRIPES_PINK assente in INVENTARIO
A95: 46181.78 | B95: RECONCILE_DONE | D95: [APPLY] reconcile V2 — set=0, noop=14, skip=3, flagged=6, errors=0
A96: 46181.821 | B96: SET | C96: AGATA BAG FLORAL BORDEAUX EMBROIDERY | D96: 1 -> 0
A97: 46181.821 | B97: SET | C97: AGATA BAG FLORAL GREY | D97: 1 -> 0
A98: 46181.822 | B98: SKIP_NOT_IN_INV | C98: AGATA BAG FLORAL ORANGE EMBROIDERY | D98: CODICE Agata_Bag_floral_orange_embroidery assente in INVENTARIO
A99: 46181.822 | B99: FLAG_NEGATIVO | C99: AGATA BAG FLORAL PINK EMBROIDERY | D99: gestionale -2 -> sito 0 (Agata_Bag_FLORAL_PINK_EMBROIDERY)
A100: 46181.822 | B100: CHANGE_SKIPPED | C100: AGATA BAG PAILLETTES PINK | D100: sito 1 -> 7 (delta 6) — safe-mode: NON applicato, rivedi
A101: 46181.822 | B101: FLAG_VERIFICA2 | C101: AGATA BAG ROSE BLUE | D101: gestionale 2 -> sito 1 (Agata_Bag_ROSE_BLUE)
A102: 46181.822 | B102: FLAG_VERIFICA2 | C102: AGATA BAG ROSE BUTTER | D102: gestionale 2 -> sito 1 (Agata_Bag_ROSE_BUTTER)
A103: 46181.822 | B103: FLAG_VERIFICA2 | C103: AGATA BAG ROSE PINK | D103: gestionale 2 -> sito 1 (Agata_Bag_ROSE_PINK)
A104: 46181.822 | B104: CHANGE_SKIPPED | C104: ANNIE BAG BLUE | D104: sito 1 -> 5 (delta 4) — safe-mode: NON applicato, rivedi
A105: 46181.822 | B105: SKIP_NOT_IN_INV | C105: ANNIE BAG LILAC | D105: CODICE Annie_Bag_LILAC assente in INVENTARIO
A106: 46181.822 | B106: CHANGE_SKIPPED | C106: ANNIE BAG PAILLETTES LIGHT BLUE | D106: sito 0 -> 3 (delta 3) — safe-mode: NON applicato, rivedi
A107: 46181.822 | B107: FLAG_NEGATIVO | C107: ANNIE BAG PAILLETTES NUDE | D107: gestionale -3 -> sito 0 (Annie_Bag_PAILLETTES_NUDE)
... A112: 46181.822 | B112: SKIP_NOT_IN_INV | C112: ANNIE BAG STRIPES PINK | D112: CODICE Annie_Bag_STRIPES_PINK assente in INVENTARIO
A113: 46181.822 | B113: RECONCILE_DONE | D113: [APPLY] reconcile V2 — set=2, noop=12, skip=3, flagged=6, errors=0
A114: 46181.863 | B114: SKIP_NOT_IN_INV | C114: AGATA BAG FLORAL ORANGE EMBROIDERY | D114: CODICE Agata_Bag_floral_orange_embroidery assente in INVENTARIO
A115: 46181.863 | B115: FLAG_NEGATIVO | C115: AGATA BAG FLORAL PINK EMBROIDERY | D115: gestionale -2 -> sito 0 (Agata_Bag_FLORAL_PINK_EMBROIDERY)
A116: 46181.863 | B116: CHANGE_SKIPPED | C116: AGATA BAG PAILLETTES PINK | D116: sito 1 -> 7 (delta 6) — safe-mode: NON applicato, rivedi
A117: 46181.863 | B117: FLAG_VERIFICA2 | C117: AGATA BAG ROSE BLUE | D117: gestionale 2 -> sito 1 (Agata_Bag_ROSE_BLUE)
A118: 46181.863 | B118: FLAG_VERIFICA2 | C118: AGATA BAG ROSE BUTTER | D118: gestionale 2 -> sito 1 (Agata_Bag_ROSE_BUTTER)
A119: 46181.863 | B119: FLAG_VERIFICA2 | C119: AGATA BAG ROSE PINK | D119: gestionale 2 -> sito 1 (Agata_Bag_ROSE_PINK)
A120: 46181.863 | B120: CHANGE_SKIPPED | C120: ANNIE BAG BLUE | D120: sito 1 -> 5 (delta 4) — safe-mode: NON applicato, rivedi
A121: 46181.863 | B121: SKIP_NOT_IN_INV | C121: ANNIE BAG LILAC | D121: CODICE Annie_Bag_LILAC assente in INVENTARIO
A122: 46181.863 | B122: CHANGE_SKIPPED | C122: ANNIE BAG PAILLETTES LIGHT BLUE | D122: sito 0 -> 3 (delta 3) — safe-mode: NON applicato, rivedi
A123: 46181.863 | B123: FLAG_NEGATIVO | C123: ANNIE BAG PAILLETTES NUDE | D123: gestionale -3 -> sito 0 (Annie_Bag_PAILLETTES_NUDE)
A124: 46181.863 | B124: CHANGE_SKIPPED | C124: ANNIE BAG PAILLETTES PINK | D124: sito 0 -> 6 (delta 6) — safe-mode: NON applicato, rivedi
A125: 46181.863 | B125: CHANGE_SKIPPED | C125: ANNIE BAG PAILLETTES PURPLE | D125: sito 5 -> 8 (delta 3) — safe-mode: NON applicato, rivedi
... A128: 46181.863 | B128: SKIP_NOT_IN_INV | C128: ANNIE BAG STRIPES PINK | D128: CODICE Annie_Bag_STRIPES_PINK assente in INVENTARIO
...

Sheet VARIANT_SYNC_V2
A1: Bag_Name | B1: Product_ID | C1: SC_Variant_ID | D1: SC_InventoryItem_ID | E1: CC_Variant_ID | F1: CC_InventoryItem_ID | G1: Location_ID | H1: CODICE_AMIIMI | I1: Note | J1: Handle | K1: CONTA_VERIFICATA
A2: AGATA BAG EMBROIDERY WHITE | B2: gid://shopify/Product/10881080983879 | C2: gid://shopify/ProductVariant/54254925971783 | D2: gid://shopify/InventoryItem/55850551214407 | E2: gid://shopify/ProductVariant/54254926725447 | F2: gid://shopify/InventoryItem/55850551968071 | G2: gid://shopify/Location/107986518343 | H2: Agata_Bag_EMBROIDERY_WHITE | J2: agata-bag-embroidery-white
A3: AGATA BAG FLORAL BORDEAUX EMBROIDERY | B3: gid://shopify/Product/10606554448199 | C3: gid://shopify/ProductVariant/53147863810375 | D3: gid://shopify/InventoryItem/54729884205383 | E3: gid://shopify/ProductVariant/53147863843143 | F3: gid://shopify/InventoryItem/54729884238151 | G3: gid://shopify/Location/107986518343 | H3: Agata_Bag_FLORAL_BORDEAUX_EMBROIDERY | J3: agata-bag-floral-dusty-pink-embroidery-copia | K3: 46182.625
A4: AGATA BAG FLORAL DUSTY PINK EMBROIDERY | B4: gid://shopify/Product/10606554480967 | C4: gid://shopify/ProductVariant/53147863908679 | D4: gid://shopify/InventoryItem/54729884303687 | E4: gid://shopify/ProductVariant/53147863941447 | F4: gid://shopify/InventoryItem/54729884336455 | G4: gid://shopify/Location/107986518343 | H4: Agata_Bag_FLORAL_DUSTY_PINK_EMBROIDERY | J4: agata-bag
A5: AGATA BAG FLORAL GREEN EMBROIDERY | B5: gid://shopify/Product/10606555595079 | C5: gid://shopify/ProductVariant/53147866857799 | D5: gid://shopify/InventoryItem/54729887252807 | E5: gid://shopify/ProductVariant/53147866890567 | F5: gid://shopify/InventoryItem/54729887285575 | G5: gid://shopify/Location/107986518343 | H5: Agata_Bag_FLORAL_GREEN_EMBROIDERY | J5: agata-bag-floral-green-embroidery | K5: 46182.625
A6: AGATA BAG FLORAL GREY | B6: gid://shopify/Product/10842502758727 | C6: gid://shopify/ProductVariant/54103244833095 | D6: gid://shopify/InventoryItem/55696991617351 | E6: gid://shopify/ProductVariant/54103244865863 | F6: gid://shopify/InventoryItem/55696991650119 | G6: gid://shopify/Location/107986518343 | H6: Agata_Bag_FLORAL_GREY | J6: agata-bag-floral-grey | K6: 46182.625
A7: AGATA BAG FLORAL LIGHT BLUE | B7: gid://shopify/Product/10842502725959 | C7: gid://shopify/ProductVariant/54103244570951 | D7: gid://shopify/InventoryItem/55696991355207 | E7: gid://shopify/ProductVariant/54103244603719 | F7: gid://shopify/InventoryItem/55696991387975 | G7: gid://shopify/Location/107986518343 | H7: Agata_Bag_FLORAL_LIGHT_BLUE | J7: agata-bag-floral-light-blue
A8: AGATA BAG FLORAL LIGHT GREY | B8: gid://shopify/Product/10843855749447 | C8: gid://shopify/ProductVariant/54106970259783 | D8: gid://shopify/InventoryItem/55700730675527 | E8: gid://shopify/ProductVariant/54106970292551 | F8: gid://shopify/InventoryItem/55700730708295 | G8: gid://shopify/Location/107986518343 | H8: Agata_Bag_FLORAL_LIGHT_GREY | J8: agata-bag-floral-light-grey
A9: AGATA BAG FLORAL ORANGE EMBROIDERY | B9: gid://shopify/Product/10606553268551 | C9: gid://shopify/ProductVariant/53147861778759 | D9: gid://shopify/InventoryItem/54729882042695 | E9: gid://shopify/ProductVariant/53147861811527 | F9: gid://shopify/InventoryItem/54729882075463 | G9: gid://shopify/Location/107986518343 | H9: Agata_Bag_floral_orange_embroidery | J9: agata-bag-floral-orange-embroidery | K9: 46182.625
A10: AGATA BAG FLORAL PINK EMBROIDERY | B10: gid://shopify/Product/10606555627847 | C10: gid://shopify/ProductVariant/53147866956103 | D10: gid://shopify/InventoryItem/54729887351111 | E10: gid://shopify/ProductVariant/53147866988871 | F10: gid://shopify/InventoryItem/54729887383879 | G10: gid://shopify/Location/107986518343 | H10: Agata_Bag_FLORAL_PINK_EMBROIDERY | J10: agata-bag-pink-pearl
A11: AGATA BAG PAILLETTES PINK | B11: gid://shopify/Product/10819276833095 | C11: gid://shopify/ProductVariant/54012891857223 | D11: gid://shopify/InventoryItem/55605296103751 | E11: gid://shopify/ProductVariant/54012891889991 | F11: gid://shopify/InventoryItem/55605296136519 | G11: gid://shopify/Location/107986518343 | H11: Agata_Bag_PAILLETTES_PINK | I11: risolto da nome base prodotto | J11: agata-bag-paillettes-pink
A12: AGATA BAG ROSE BLUE | B12: gid://shopify/Product/10606556348743 | C12: gid://shopify/ProductVariant/53147871543623 | D12: gid://shopify/InventoryItem/54729891840327 | E12: gid://shopify/ProductVariant/53147871576391 | F12: gid://shopify/InventoryItem/54729891873095 | G12: gid://shopify/Location/107986518343 | H12: Agata_Bag_ROSE_BLUE | J12: agata-bag-rose-blue | K12: 46182.625
A13: AGATA BAG ROSE BUTTER | B13: gid://shopify/Product/10816781156679 | C13: gid://shopify/ProductVariant/53999357002055 | D13: gid://shopify/InventoryItem/55591563788615 | E13: gid://shopify/ProductVariant/53999357034823 | F13: gid://shopify/InventoryItem/55591563821383 | G13: gid://shopify/Location/107986518343 | H13: Agata_Bag_ROSE_BUTTER | J13: agata-bag-rose-butter | K13: 46182.625
A14: AGATA BAG ROSE BUTTER GREEN | B14: gid://shopify/Product/10842502398279 | C14: gid://shopify/ProductVariant/54103244112199 | D14: gid://shopify/InventoryItem/55696990896455 | E14: gid://shopify/ProductVariant/54103244144967 | F14: gid://shopify/InventoryItem/55696990929223 | G14: gid://shopify/Location/107986518343 | H14: Agata_Bag_ROSE_BUTTER_GREEN | J14: agata-bag-rose-butter-green | K14: 46182.625
A15: AGATA BAG ROSE PINK | B15: gid://shopify/Product/10606556283207 | C15: gid://shopify/ProductVariant/53147871445319 | D15: gid://shopify/InventoryItem/54729891742023 | E15: gid://shopify/ProductVariant/53147871478087 | F15: gid://shopify/InventoryItem/54729891774791 | G15: gid://shopify/Location/107986518343 | H15: Agata_Bag_ROSE_PINK | J15: agata-bag-rose-pink | K15: 46182.625
A16: AGATA BAG TIE DYE ORANGE | B16: gid://shopify/Product/10606556447047 | C16: gid://shopify/ProductVariant/53147871772999 | D16: gid://shopify/InventoryItem/54729892036935 | E16: gid://shopify/ProductVariant/53147871805767 | F16: gid://shopify/InventoryItem/54729892069703 | G16: gid://shopify/Location/107986518343 | H16: Agata_Bag_TIE_DYE_ORANGE | J16: agata-bag-tie-dye-orange
A17: AGATA BAG TIE DYE PINK | B17: gid://shopify/Product/10606556479815 | C17: gid://shopify/ProductVariant/53147871838535 | D17: gid://shopify/InventoryItem/54729892102471 | E17: gid://shopify/ProductVariant/53147871871303 | F17: gid://shopify/InventoryItem/54729892135239 | G17: gid://shopify/Location/107986518343 | H17: Agata_Bag_TIE_DYE_PINK | J17: agata-bag-tie-dye-pink | K17: 46182.625
A18: ANNIE BAG BLUE | B18: gid://shopify/Product/10757208211783 | C18: gid://shopify/ProductVariant/53752082891079 | D18: gid://shopify/InventoryItem/55341449183559 | E18: gid://shopify/ProductVariant/53752082923847 | F18: gid://shopify/InventoryItem/55341449216327 | G18: gid://shopify/Location/107986518343 | H18: Annie_Bag_BLUE | J18: annie-bag-seta-blu | K18: 46182.625
A19: ANNIE BAG BROWN SILK | B19: gid://shopify/Product/10606556184903 | C19: gid://shopify/ProductVariant/53147871019335 | D19: gid://shopify/InventoryItem/54729891348807 | E19: gid://shopify/ProductVariant/53147871052103 | F19: gid://shopify/InventoryItem/54729891381575 | G19: gid://shopify/Location/107986518343 | H19: Annie_Bag_BROWN | J19: annie-bag-brown-silk
A20: ANNIE BAG PAILLETTES CANDY PINK | B20: gid://shopify/Product/10842502824263 | C20: gid://shopify/ProductVariant/54103245062471 | D20: gid://shopify/InventoryItem/55696991846727 | E20: gid://shopify/ProductVariant/54103245095239 | F20: gid://shopify/InventoryItem/55696991879495 | G20: gid://shopify/Location/107986518343 | H20: Annie_Bag_PAILLETTES_CANDY_PINK | J20: annie-bag-paillettes-candy-pink
A21: ANNIE BAG PAILLETTES LIGHT BLUE | B21: gid://shopify/Product/10606557233479 | C21: gid://shopify/ProductVariant/53746540478791 | D21: gid://shopify/InventoryItem/55335876264263 | E21: gid://shopify/ProductVariant/53746540446023 | F21: gid://shopify/InventoryItem/55335876231495 | G21: gid://shopify/Location/107986518343 | H21: Annie_Bag_PAILLETTES_LIGHT_BLUE | J21: annie-bag-paillettes-light-blue-new | K21: 46182.625
A22: ANNIE BAG PAILLETTES LIGHT GREEN | B22: gid://shopify/Product/10606557462855 | C22: gid://shopify/ProductVariant/53746566988103 | D22: gid://shopify/InventoryItem/55335902773575 | E22: gid://shopify/ProductVariant/53746566955335 | F22: gid://shopify/InventoryItem/55335902740807 | G22: gid://shopify/Location/107986518343 | H22: Annie_Bag_PAILLETTES_LIGHT_GREEN | J22: annie-bag-paillettes-verde-new | K22: 46182.625
A23: ANNIE BAG PAILLETTES NUDE | B23: gid://shopify/Product/10606559822151 | C23: gid://shopify/ProductVariant/53746531631431 | D23: gid://shopify/InventoryItem/55335867416903 | E23: gid://shopify/ProductVariant/53746531598663 | F23: gid://shopify/InventoryItem/55335867384135 | G23: gid://shopify/Location/107986518343 | H23: Annie_Bag_PAILLETTES_NUDE | J23: annie-bag-paillettes-beige
A24: ANNIE BAG PAILLETTES PINK | B24: gid://shopify/Product/10606557397319 | C24: gid://shopify/ProductVariant/53746523078983 | D24: gid://shopify/InventoryItem/55335858864455 | E24: gid://shopify/ProductVariant/53746523046215 | F24: gid://shopify/InventoryItem/55335858831687 | G24: gid://shopify/Location/107986518343 | H24: Annie_Bag_PAILLETTES_PINK | J24: annie-bag-paillettes-pink-new | K24: 46182.625
A25: ANNIE BAG PAILLETTES PURPLE | B25: gid://shopify/Product/10606557331783 | C25: gid://shopify/ProductVariant/53147874427207 | D25: gid://shopify/InventoryItem/54729894625607 | E25: gid://shopify/ProductVariant/53147874459975 | F25: gid://shopify/InventoryItem/54729894658375 | G25: gid://shopify/Location/107986518343 | H25: Annie_Bag_PAILLETTES_PURPLE | J25: annie-bag-paillettes-purple-new | K25: 46182.625
A26: ANNIE BAG PINK | B26: gid://shopify/Product/10757204574535 | C26: gid://shopify/ProductVariant/53752058511687 | D26: gid://shopify/InventoryItem/55341424705863 | E26: gid://shopify/ProductVariant/53752058544455 | F26: gid://shopify/InventoryItem/55341424738631 | G26: gid://shopify/Location/107986518343 | H26: Annie_Bag_PINK | J26: annie-bag-seta-rosa | K26: 46182.625
A27: ANNIE BAG STRIPES PINK | B27: gid://shopify/Product/10757201953095 | C27: gid://shopify/ProductVariant/53752036065607 | D27: gid://shopify/InventoryItem/55341402030407 | E27: gid://shopify/ProductVariant/53752036098375 | F27: gid://shopify/InventoryItem/55341402063175 | G27: gid://shopify/Location/107986518343 | H27: Annie_Bag_STRIPES_PINK | I27: risolto da nome base prodotto | J27: annie-bag-seta-rosa-antico | K27: 46188.625

Sheet VARIANT_SYNC
A1: Bag_Name | B1: Product_ID | C1: SC_Variant_ID | D1: SC_InventoryItem_ID | E1: CC_Variant_ID | F1: CC_InventoryItem_ID | G1: Location_ID | H1: Giacenza_Reale | I1: Note | J1: Handle
A2: AGATA BAG FLORAL BORDEAUX EMBROIDERY | B2: gid://shopify/Product/10606554448199 | C2: gid://shopify/ProductVariant/53147863810375 | D2: gid://shopify/InventoryItem/54729884205383 | E2: gid://shopify/ProductVariant/53147863843143 | F2: gid://shopify/InventoryItem/54729884238151 | G2: gid://shopify/Location/107986518343 | H2: 1 | J2: agata-bag-floral-dusty-pink-embroidery-copia
A3: AGATA BAG FLORAL DUSTY PINK EMBROIDERY | B3: gid://shopify/Product/10606554480967 | C3: gid://shopify/ProductVariant/53147863908679 | D3: gid://shopify/InventoryItem/54729884303687 | E3: gid://shopify/ProductVariant/53147863941447 | F3: gid://shopify/InventoryItem/54729884336455 | G3: gid://shopify/Location/107986518343 | H3: 3 | J3: agata-bag
A4: AGATA BAG FLORAL GREEN EMBROIDERY | B4: gid://shopify/Product/10606555595079 | C4: gid://shopify/ProductVariant/53147866857799 | D4: gid://shopify/InventoryItem/54729887252807 | E4: gid://shopify/ProductVariant/53147866890567 | F4: gid://shopify/InventoryItem/54729887285575 | G4: gid://shopify/Location/107986518343 | H4: 0 | J4: agata-bag-floral-green-embroidery
A5: AGATA BAG FLORAL GREY | B5: gid://shopify/Product/10842502758727 | C5: gid://shopify/ProductVariant/54103244833095 | D5: gid://shopify/InventoryItem/55696991617351 | E5: gid://shopify/ProductVariant/54103244865863 | F5: gid://shopify/InventoryItem/55696991650119 | G5: gid://shopify/Location/107986518343 | H5: 1 | J5: agata-bag-floral-grey
A6: AGATA BAG FLORAL ORANGE EMBROIDERY | B6: gid://shopify/Product/10606553268551 | C6: gid://shopify/ProductVariant/53147861778759 | D6: gid://shopify/InventoryItem/54729882042695 | E6: gid://shopify/ProductVariant/53147861811527 | F6: gid://shopify/InventoryItem/54729882075463 | G6: gid://shopify/Location/107986518343 | H6: 1 | J6: agata-bag-floral-orange-embroidery
A7: AGATA BAG FLORAL PINK EMBROIDERY | B7: gid://shopify/Product/10606555627847 | C7: gid://shopify/ProductVariant/53147866956103 | D7: gid://shopify/InventoryItem/54729887351111 | E7: gid://shopify/ProductVariant/53147866988871 | F7: gid://shopify/InventoryItem/54729887383879 | G7: gid://shopify/Location/107986518343 | H7: 0 | J7: agata-bag-pink-pearl
A8: AGATA BAG PAILLETTES PINK | B8: gid://shopify/Product/10819276833095 | C8: gid://shopify/ProductVariant/54012891857223 | D8: gid://shopify/InventoryItem/55605296103751 | E8: gid://shopify/ProductVariant/54012891889991 | F8: gid://shopify/InventoryItem/55605296136519 | G8: gid://shopify/Location/107986518343 | H8: 1 | J8: agata-bag-paillettes-pink
A9: AGATA BAG ROSE BLUE | B9: gid://shopify/Product/10606556348743 | C9: gid://shopify/ProductVariant/53147871543623 | D9: gid://shopify/InventoryItem/54729891840327 | E9: gid://shopify/ProductVariant/53147871576391 | F9: gid://shopify/InventoryItem/54729891873095 | G9: gid://shopify/Location/107986518343 | H9: 2 | J9: agata-bag-rose-blue
A10: AGATA BAG ROSE BUTTER | B10: gid://shopify/Product/10816781156679 | C10: gid://shopify/ProductVariant/53999357002055 | D10: gid://shopify/InventoryItem/55591563788615 | E10: gid://shopify/ProductVariant/53999357034823 | F10: gid://shopify/InventoryItem/55591563821383 | G10: gid://shopify/Location/107986518343 | H10: 2 | J10: agata-bag-rose-butter
A11: AGATA BAG ROSE BUTTER GREEN | B11: gid://shopify/Product/10842502398279 | C11: gid://shopify/ProductVariant/54103244112199 | D11: gid://shopify/InventoryItem/55696990896455 | E11: gid://shopify/ProductVariant/54103244144967 | F11: gid://shopify/InventoryItem/55696990929223 | G11: gid://shopify/Location/107986518343 | H11: 5 | J11: agata-bag-rose-butter-green
A12: AGATA BAG ROSE PINK | B12: gid://shopify/Product/10606556283207 | C12: gid://shopify/ProductVariant/53147871445319 | D12: gid://shopify/InventoryItem/54729891742023 | E12: gid://shopify/ProductVariant/53147871478087 | F12: gid://shopify/InventoryItem/54729891774791 | G12: gid://shopify/Location/107986518343 | H12: 1 | J12: agata-bag-rose-pink
A13: AGATA BAG TIE DYE ORANGE | B13: gid://shopify/Product/10606556447047 | C13: gid://shopify/ProductVariant/53147871772999 | D13: gid://shopify/InventoryItem/54729892036935 | E13: gid://shopify/ProductVariant/53147871805767 | F13: gid://shopify/InventoryItem/54729892069703 | G13: gid://shopify/Location/107986518343 | H13: 0 | J13: agata-bag-tie-dye-orange
... A24: ANNIE BAG STRIPES PINK | B24: gid://shopify/Product/10757201953095 | C24: gid://shopify/ProductVariant/53752036065607 | D24: gid://shopify/InventoryItem/55341402030407 | E24: gid://shopify/ProductVariant/53752036098375 | F24: gid://shopify/InventoryItem/55341402063175 | G24: gid://shopify/Location/107986518343 | H24: 3 | J24: annie-bag-seta-rosa-antico

Sheet META_ADS_LOG
A1: timestamp | B1: context | C1: message
A2: 2026-05-24T05:29:29.356Z | B2: dailyMetaPull/fatal | C2: HTTP 400 — {"error":{"message":"API access blocked.","type":"OAuthException","code":200,"fbtrace_id":"Av3SY0BLx51VlALgADhsQNt"}}
A3: 2026-05-25T05:29:32.488Z | B3: dailyMetaPull/fatal | C3: HTTP 400 — {"error":{"message":"API access blocked.","type":"OAuthException","code":200,"fbtrace_id":"ARsk6USPcefTpnZXmoH21m4"}}
A4: 2026-05-26T05:29:28.831Z | B4: dailyMetaPull/fatal | C4: HTTP 400 — {"error":{"message":"API access blocked.","type":"OAuthException","code":200,"fbtrace_id":"Aw40kuRGyYfM3dW1g35I7VR"}}
A5: 2026-05-27T05:29:28.533Z | B5: dailyMetaPull/fatal | C5: HTTP 400 — {"error":{"message":"API access blocked.","type":"OAuthException","code":200,"fbtrace_id":"A7NWX-5M1Gr2nXrQxMJoQ5z"}}
A6: 2026-05-28T05:29:27.801Z | B6: dailyMetaPull/fatal | C6: HTTP 400 — {"error":{"message":"API access blocked.","type":"OAuthException","code":200,"fbtrace_id":"AQVnG9_p070eej4PySK4enM"}}
A7: 2026-05-29T05:29:28.309Z | B7: dailyMetaPull/fatal | C7: HTTP 400 — {"error":{"message":"API access blocked.","type":"OAuthException","code":200,"fbtrace_id":"AYsCvxif8JYvxrs24zvOnPu"}}
A8: 2026-05-30T05:29:55.685Z | B8: dailyMetaPull/fatal | C8: HTTP 400 — {"error":{"message":"API access blocked.","type":"OAuthException","code":200,"fbtrace_id":"AYxqpZbXTz9-hFL2ayNFiv6"}}
A9: 2026-05-30T13:38:23.605Z | B9: dailyMetaPull/fatal | C9: HTTP 400 — {"error":{"message":"API access blocked.","type":"OAuthException","code":200,"fbtrace_id":"Aj0ybGaD0IDEjEn7u1gUsri"}}
A10: 2026-05-30T13:50:17.612Z | B10: dailyMetaPull/fatal | C10: HTTP 400 — {"error":{"message":"API access blocked.","type":"OAuthException","code":200,"fbtrace_id":"AIXI0PDj8-ffiPiRdPIrn2W"}}

Sheet META_ADS_DAILY
A1: date | B1: campaign_id | C1: campaign_name | D1: campaign_status | E1: campaign_objective | F1: spend_eur | G1: impressions | H1: reach | I1: frequency | J1: clicks | K1: link_clicks | L1: ctr | M1: cpc | N1: cpm | O1: landing_page_views | P1: view_content | Q1: add_to_cart | R1: initiate_checkout | S1: add_payment_info | T1: purchases | U1: purchase_value_eur | V1: cpa_eur | W1: roas | X1: pulled_at
A2: 46135 | B2: 120241930909210731 | C2: SUPER HOT | D2: ACTIVE | E2: OUTCOME_SALES | F2: 2.65 | G2: 895 | H2: 623 | I2: 1.436597 | J2: 17 | K2: 8 | L2: 1.899441 | M2: 0.155882 | N2: 2.960894 | O2: 5 | P2: 34 | Q2: 1 | R2: 1 | S2: 0 | T2: 0 | U2: 0 | W2: 0 | X2: 2026-05-22T22:13:28.980Z
A3: 46136 | B3: 120241930909210731 | C3: SUPER HOT | D3: ACTIVE | E3: OUTCOME_SALES | F3: 2.46 | G3: 1040 | H3: 801 | I3: 1.298377 | J3: 24 | K3: 13 | L3: 2.307692 | M3: 0.1025 | N3: 2.365385 | O3: 12 | P3: 37 | Q3: 0 | R3: 0 | S3: 0 | T3: 0 | U3: 0 | W3: 0 | X3: 2026-05-22T22:13:32.367Z
A4: 46137 | B4: 120241930909210731 | C4: SUPER HOT | D4: ACTIVE | E4: OUTCOME_SALES | F4: 3.19 | G4: 1156 | H4: 901 | I4: 1.283019 | J4: 27 | K4: 16 | L4: 2.33564 | M4: 0.118148 | N4: 2.759516 | O4: 8 | P4: 31 | Q4: 0 | R4: 0 | S4: 0 | T4: 0 | U4: 0 | W4: 0 | X4: 2026-05-22T22:13:35.835Z
A5: 46138 | B5: 120241930909210731 | C5: SUPER HOT | D5: ACTIVE | E5: OUTCOME_SALES | F5: 4.32 | G5: 1503 | H5: 760 | I5: 1.977632 | J5: 36 | K5: 22 | L5: 2.39521 | M5: 0.12 | N5: 2.874252 | O5: 8 | P5: 34 | Q5: 2 | R5: 1 | S5: 1 | T5: 1 | U5: 170 | V5: 4.32 | W5: 39.351852 | X5: 2026-05-22T22:13:38.790Z
A6: 46139 | B6: 120241930909210731 | C6: SUPER HOT | D6: ACTIVE | E6: OUTCOME_SALES | F6: 2.5 | G6: 838 | H6: 426 | I6: 1.967136 | J6: 25 | K6: 17 | L6: 2.983294 | M6: 0.1 | N6: 2.983294 | O6: 10 | P6: 47 | Q6: 0 | R6: 0 | S6: 0 | T6: 0 | U6: 0 | W6: 0 | X6: 2026-05-22T22:13:42.425Z
A7: 46140 | B7: 120241930909210731 | C7: SUPER HOT | D7: ACTIVE | E7: OUTCOME_SALES | F7: 1.56 | G7: 526 | H7: 354 | I7: 1.485876 | J7: 9 | K7: 8 | L7: 1.711027 | M7: 0.173333 | N7: 2.965779 | O7: 6 | P7: 24 | Q7: 0 | R7: 0 | S7: 0 | T7: 0 | U7: 0 | W7: 0 | X7: 2026-05-22T22:13:45.308Z
A8: 46141 | B8: 120241930909210731 | C8: SUPER HOT | D8: ACTIVE | E8: OUTCOME_SALES | F8: 1.51 | G8: 534 | H8: 390 | I8: 1.369231 | J8: 14 | K8: 9 | L8: 2.621723 | M8: 0.107857 | N8: 2.827715 | O8: 2 | P8: 8 | Q8: 1 | R8: 2 | S8: 0 | T8: 0 | U8: 0 | W8: 0 | X8: 2026-05-22T22:13:48.236Z
A9: 46142 | B9: 120241930909210731 | C9: SUPER HOT | D9: ACTIVE | E9: OUTCOME_SALES | F9: 5.1 | G9: 1494 | H9: 974 | I9: 1.533881 | J9: 37 | K9: 24 | L9: 2.476573 | M9: 0.137838 | N9: 3.413655 | O9: 17 | P9: 77 | Q9: 1 | R9: 1 | S9: 1 | T9: 1 | U9: 120 | V9: 5.1 | W9: 23.529412 | X9: 2026-05-22T22:13:51.273Z
A10: 46143 | B10: 120241930909210731 | C10: SUPER HOT | D10: ACTIVE | E10: OUTCOME_SALES | F10: 3.51 | G10: 1178 | H10: 628 | I10: 1.875796 | J10: 29 | K10: 17 | L10: 2.4618 | M10: 0.121034 | N10: 2.979626 | O10: 11 | P10: 23 | Q10: 0 | R10: 0 | S10: 0 | T10: 0 | U10: 0 | W10: 0 | X10: 2026-05-22T22:13:54.659Z
A11: 46144 | B11: 120241930909210731 | C11: SUPER HOT | D11: ACTIVE | E11: OUTCOME_SALES | F11: 2.46 | G11: 1138 | H11: 727 | I11: 1.565337 | J11: 13 | K11: 10 | L11: 1.142355 | M11: 0.189231 | N11: 2.161687 | O11: 8 | P11: 15 | Q11: 2 | R11: 2 | S11: 0 | T11: 0 | U11: 0 | W11: 0 | X11: 2026-05-22T22:13:57.510Z
A12: 46145 | B12: 120241930909210731 | C12: SUPER HOT | D12: ACTIVE | E12: OUTCOME_SALES | F12: 3.06 | G12: 1487 | H12: 958 | I12: 1.552192 | J12: 37 | K12: 20 | L12: 2.488231 | M12: 0.082703 | N12: 2.057835 | O12: 13 | P12: 40 | Q12: 2 | R12: 1 | S12: 1 | T12: 1 | U12: 75.9 | V12: 3.06 | W12: 24.803922 | X12: 2026-05-22T22:14:00.706Z
A13: 46146 | B13: 120241930909210731 | C13: SUPER HOT | D13: ACTIVE | E13: OUTCOME_SALES | F13: 3.47 | G13: 1305 | H13: 781 | I13: 1.670935 | J13: 28 | K13: 19 | L13: 2.145594 | M13: 0.123929 | N13: 2.659004 | O13: 15 | P13: 38 | Q13: 1 | R13: 4 | S13: 1 | T13: 1 | U13: 72 | V13: 3.47 | W13: 20.74928 | X13: 2026-05-22T22:14:05.289Z
A14: 46147 | B14: 120244032235930731 | C14: COLD | D14: ACTIVE | E14: OUTCOME_SALES | F14: 23.55 | G14: 8119 | H14: 5462 | I14: 1.486452 | J14: 208 | K14: 127 | L14: 2.561892 | M14: 0.113221 | N14: 2.900604 | O14: 55 | P14: 100 | Q14: 1 | R14: 1 | S14: 0 | T14: 0 | U14: 0 | W14: 0 | X14: 2026-05-22T22:14:08.037Z
A15: 46147 | B15: 120241930909210731 | C15: SUPER HOT | D15: ACTIVE | E15: OUTCOME_SALES | F15: 2.85 | G15: 912 | H15: 624 | I15: 1.461538 | J15: 26 | K15: 14 | L15: 2.850877 | M15: 0.109615 | N15: 3.125 | O15: 11 | P15: 43 | Q15: 1 | R15: 2 | S15: 1 | T15: 1 | U15: 84.9 | V15: 2.85 | W15: 29.789474 | X15: 2026-05-22T22:14:09.243Z
A16: 46148 | B16: 120244032235930731 | C16: COLD | D16: ACTIVE | E16: OUTCOME_SALES | F16: 4.43 | G16: 2217 | H16: 1882 | I16: 1.178002 | J16: 61 | K16: 33 | L16: 2.751466 | M16: 0.072623 | N16: 1.998196 | O16: 14 | P16: 36 | Q16: 0 | R16: 0 | S16: 0 | T16: 0 | U16: 0 | W16: 0 | X16: 2026-05-22T22:14:12.053Z
A17: 46148 | B17: 120241930909210731 | C17: SUPER HOT | D17: ACTIVE | E17: OUTCOME_SALES | F17: 3.59 | G17: 1377 | H17: 1066 | I17: 1.291745 | J17: 54 | K17: 35 | L17: 3.921569 | M17: 0.066481 | N17: 2.607117 | O17: 26 | P17: 49 | Q17: 1 | R17: 1 | S17: 1 | T17: 1 | U17: 108 | V17: 3.59 | W17: 30.083565 | X17: 2026-05-22T22:14:12.930Z
A18: 46149 | B18: 120241930909210731 | C18: SUPER HOT | D18: ACTIVE | E18: OUTCOME_SALES | F18: 3.17 | G18: 1147 | H18: 800 | I18: 1.43375 | J18: 44 | K18: 30 | L18: 3.836094 | M18: 0.072045 | N18: 2.763731 | O18: 31 | P18: 50 | Q18: 3 | R18: 2 | S18: 0 | T18: 0 | U18: 0 | W18: 0 | X18: 2026-05-22T22:14:16.066Z
A19: 46150 | B19: 120241930909210731 | C19: SUPER HOT | D19: ACTIVE | E19: OUTCOME_SALES | F19: 2.84 | G19: 963 | H19: 696 | I19: 1.383621 | J19: 25 | K19: 13 | L19: 2.596054 | M19: 0.1136 | N19: 2.949117 | O19: 8 | P19: 35 | Q19: 1 | R19: 1 | S19: 1 | T19: 1 | U19: 153 | V19: 2.84 | W19: 53.873239 | X19: 2026-05-22T22:14:19.283Z
A20: 46151 | B20: 120241930909210731 | C20: SUPER HOT | D20: ACTIVE | E20: OUTCOME_SALES | F20: 1.98 | G20: 688 | H20: 479 | I20: 1.436326 | J20: 23 | K20: 13 | L20: 3.343023 | M20: 0.086087 | N20: 2.877907 | O20: 9 | P20: 57 | Q20: 0 | R20: 0 | S20: 0 | T20: 0 | U20: 0 | W20: 0 | X20: 2026-05-22T22:14:21.939Z
A21: 46152 | B21: 120241930909210731 | C21: SUPER HOT | D21: ACTIVE | E21: OUTCOME_SALES | F21: 3.05 | G21: 1157 | H21: 675 | I21: 1.714074 | J21: 35 | K21: 18 | L21: 3.025065 | M21: 0.087143 | N21: 2.636128 | O21: 9 | P21: 70 | Q21: 1 | R21: 1 | S21: 1 | T21: 1 | U21: 84.9 | V21: 3.05 | W21: 27.836066 | X21: 2026-05-22T22:14:25.073Z
A22: 46153 | B22: 120244032235930731 | C22: COLD | D22: ACTIVE | E22: OUTCOME_SALES | F22: 31.73 | G22: 9488 | H22: 5778 | I22: 1.642091 | J22: 318 | K22: 196 | L22: 3.351602 | M22: 0.09978 | N22: 3.344224 | O22: 141 | P22: 239 | Q22: 3 | R22: 0 | S22: 0 | T22: 0 | U22: 0 | W22: 0 | X22: 2026-05-22T22:14:27.555Z
A23: 46153 | B23: 120241930909210731 | C23: SUPER HOT | D23: ACTIVE | E23: OUTCOME_SALES | F23: 1.56 | G23: 575 | H23: 470 | I23: 1.223404 | J23: 7 | K23: 4 | L23: 1.217391 | M23: 0.222857 | N23: 2.713043 | O23: 4 | P23: 17 | Q23: 3 | R23: 0 | S23: 0 | T23: 1 | U23: 120 | V23: 1.56 | W23: 76.923077 | X23: 2026-05-22T22:14:28.433Z
A24: 46154 | B24: 120244032235930731 | C24: COLD | D24: ACTIVE | E24: OUTCOME_SALES | F24: 28.74 | G24: 8415 | H24: 4528 | I24: 1.858436 | J24: 259 | K24: 164 | L24: 3.077837 | M24: 0.110965 | N24: 3.41533 | O24: 101 | P24: 172 | Q24: 2 | R24: 1 | S24: 1 | T24: 1 | U24: 84.9 | V24: 28.74 | W24: 2.954071 | X24: 2026-05-22T22:14:31.695Z
A25: 46154 | B25: 120241930909210731 | C25: SUPER HOT | D25: ACTIVE | E25: OUTCOME_SALES | F25: 3.58 | G25: 1126 | H25: 757 | I25: 1.48745 | J25: 29 | K25: 18 | L25: 2.575488 | M25: 0.123448 | N25: 3.179396 | O25: 15 | P25: 34 | Q25: 0 | R25: 0 | S25: 0 | T25: 0 | U25: 0 | W25: 0 | X25: 2026-05-22T22:14:32.646Z
A26: 46155 | B26: 120244032235930731 | C26: COLD | D26: ACTIVE | E26: OUTCOME_SALES | F26: 25.8 | G26: 6061 | H26: 3587 | I26: 1.689713 | J26: 236 | K26: 157 | L26: 3.893747 | M26: 0.109322 | N26: 4.256723 | O26: 93 | P26: 172 | Q26: 2 | R26: 0 | S26: 0 | T26: 0 | U26: 0 | W26: 0 | X26: 2026-05-22T22:14:34.957Z
A27: 46155 | B27: 120241930909210731 | C27: SUPER HOT | D27: ACTIVE | E27: OUTCOME_SALES | F27: 3.75 | G27: 1015 | H27: 642 | I27: 1.580997 | J27: 38 | K27: 26 | L27: 3.743842 | M27: 0.098684 | N27: 3.694581 | O27: 17 | P27: 60 | Q27: 2 | R27: 1 | S27: 1 | T27: 1 | U27: 170 | V27: 3.75 | W27: 45.333333 | X27: 2026-05-22T22:14:36.045Z
A28: 46156 | B28: 120244032235930731 | C28: COLD | D28: ACTIVE | E28: OUTCOME_SALES | F28: 23.34 | G28: 5073 | H28: 3145 | I28: 1.613037 | J28: 210 | K28: 132 | L28: 4.139562 | M28: 0.111143 | N28: 4.600828 | O28: 79 | P28: 173 | Q28: 3 | R28: 0 | S28: 0 | T28: 0 | U28: 0 | W28: 0 | X28: 2026-05-22T22:14:38.755Z
A29: 46156 | B29: 120241930909210731 | C29: SUPER HOT | D29: ACTIVE | E29: OUTCOME_SALES | F29: 3.08 | G29: 927 | H29: 674 | I29: 1.375371 | J29: 26 | K29: 16 | L29: 2.804746 | M29: 0.118462 | N29: 3.322546 | O29: 6 | P29: 27 | Q29: 0 | R29: 0 | S29: 0 | T29: 0 | U29: 0 | W29: 0 | X29: 2026-05-22T22:14:39.645Z
A30: 46157 | B30: 120244032235930731 | C30: COLD | D30: ACTIVE | E30: OUTCOME_SALES | F30: 22.01 | G30: 4664 | H30: 3016 | I30: 1.546419 | J30: 183 | K30: 104 | L30: 3.923671 | M30: 0.120273 | N30: 4.719125 | O30: 68 | P30: 158 | Q30: 5 | R30: 4 | S30: 3 | T30: 3 | U30: 288.8 | V30: 7.3366667 | W30: 13.121308 | X30: 2026-05-22T22:14:42.075Z
A31: 46157 | B31: 120241930909210731 | C31: SUPER HOT | D31: ACTIVE | E31: OUTCOME_SALES | F31: 2.96 | G31: 668 | H31: 475 | I31: 1.406316 | J31: 20 | K31: 15 | L31: 2.994012 | M31: 0.148 | N31: 4.431138 | O31: 13 | P31: 15 | Q31: 0 | R31: 0 | S31: 0 | T31: 0 | U31: 0 | W31: 0 | X31: 2026-05-22T22:14:43.023Z
A32: 46158 | B32: 120244032235930731 | C32: COLD | D32: ACTIVE | E32: OUTCOME_SALES | F32: 21.84 | G32: 4776 | H32: 2816 | I32: 1.696023 | J32: 184 | K32: 127 | L32: 3.852596 | M32: 0.118696 | N32: 4.572864 | O32: 78 | P32: 167 | Q32: 3 | R32: 0 | S32: 0 | T32: 0 | U32: 0 | W32: 0 | X32: 2026-05-22T22:14:45.232Z
A33: 46158 | B33: 120241930909210731 | C33: SUPER HOT | D33: ACTIVE | E33: OUTCOME_SALES | F33: 2.98 | G33: 969 | H33: 756 | I33: 1.281746 | J33: 41 | K33: 26 | L33: 4.231166 | M33: 0.072683 | N33: 3.075335 | O33: 17 | P33: 61 | Q33: 0 | R33: 0 | S33: 0 | T33: 0 | U33: 0 | W33: 0 | X33: 2026-05-22T22:14:46.193Z
A34: 46159 | B34: 120244032235930731 | C34: COLD | D34: ACTIVE | E34: OUTCOME_SALES | F34: 21.82 | G34: 4999 | H34: 2851 | I34: 1.75342 | J34: 198 | K34: 130 | L34: 3.960792 | M34: 0.110202 | N34: 4.364873 | O34: 87 | P34: 188 | Q34: 2 | R34: 2 | S34: 4 | T34: 1 | U34: 100 | V34: 21.82 | W34: 4.5829514 | X34: 2026-05-22T22:14:48.817Z
A35: 46159 | B35: 120241930909210731 | C35: SUPER HOT | D35: ACTIVE | E35: OUTCOME_SALES | F35: 3.58 | G35: 1080 | H35: 583 | I35: 1.852487 | J35: 34 | K35: 23 | L35: 3.148148 | M35: 0.105294 | N35: 3.314815 | O35: 12 | P35: 22 | Q35: 3 | R35: 3 | S35: 2 | T35: 1 | U35: 108 | V35: 3.58 | W35: 30.167598 | X35: 2026-05-22T22:14:50.283Z
A36: 46160 | B36: 120244032235930731 | C36: COLD | D36: ACTIVE | E36: OUTCOME_SALES | F36: 22.32 | G36: 5390 | H36: 3480 | I36: 1.548851 | J36: 198 | K36: 129 | L36: 3.673469 | M36: 0.112727 | N36: 4.141002 | O36: 76 | P36: 154 | Q36: 2 | R36: 3 | S36: 2 | T36: 2 | U36: 156.9 | V36: 11.16 | W36: 7.0295699 | X36: 2026-05-22T22:14:52.400Z
A37: 46160 | B37: 120241930909210731 | C37: SUPER HOT | D37: ACTIVE | E37: OUTCOME_SALES | F37: 3 | G37: 951 | H37: 660 | I37: 1.440909 | J37: 26 | K37: 17 | L37: 2.733964 | M37: 0.115385 | N37: 3.154574 | O37: 12 | P37: 25 | Q37: 0 | R37: 0 | S37: 0 | T37: 0 | U37: 0 | W37: 0 | X37: 2026-05-22T22:14:53.454Z
A38: 46161 | B38: 120244032235930731 | C38: COLD | D38: ACTIVE | E38: OUTCOME_SALES | F38: 22.66 | G38: 4888 | H38: 3238 | I38: 1.509574 | J38: 175 | K38: 116 | L38: 3.580196 | M38: 0.129486 | N38: 4.635843 | O38: 73 | P38: 131 | Q38: 0 | R38: 0 | S38: 0 | T38: 0 | U38: 0 | W38: 0 | X38: 2026-05-22T22:14:55.773Z
A39: 46161 | B39: 120241930909210731 | C39: SUPER HOT | D39: ACTIVE | E39: OUTCOME_SALES | F39: 3.31 | G39: 845 | H39: 524 | I39: 1.612595 | J39: 31 | K39: 20 | L39: 3.668639 | M39: 0.106774 | N39: 3.91716 | O39: 12 | P39: 40 | Q39: 0 | R39: 0 | S39: 0 | T39: 0 | U39: 0 | W39: 0 | X39: 2026-05-22T22:14:56.665Z
A40: 46162 | B40: 120244032235930731 | C40: COLD | D40: ACTIVE | E40: OUTCOME_SALES | F40: 21.28 | G40: 4154 | H40: 2929 | I40: 1.418231 | J40: 168 | K40: 112 | L40: 4.044295 | M40: 0.126667 | N40: 5.122773 | O40: 72 | P40: 120 | Q40: 2 | R40: 1 | S40: 2 | T40: 2 | U40: 275 | V40: 10.64 | W40: 12.922932 | X40: 2026-05-22T22:14:58.742Z
A41: 46162 | B41: 120241930909210731 | C41: SUPER HOT | D41: ACTIVE | E41: OUTCOME_SALES | F41: 2.98 | G41: 738 | H41: 506 | I41: 1.458498 | J41: 20 | K41: 11 | L41: 2.710027 | M41: 0.149 | N41: 4.03794 | O41: 9 | P41: 40 | Q41: 1 | R41: 0 | S41: 0 | T41: 0 | U41: 0 | W41: 0 | X41: 2026-05-22T22:14:59.633Z
A42: 46163 | B42: 120244032235930731 | C42: COLD | D42: ACTIVE | E42: OUTCOME_SALES | F42: 20.97 | G42: 4307 | H42: 2878 | I42: 1.496525 | J42: 135 | K42: 85 | L42: 3.134432 | M42: 0.155333 | N42: 4.868818 | O42: 49 | P42: 139 | Q42: 3 | R42: 2 | S42: 0 | T42: 0 | U42: 0 | W42: 0 | X42: 2026-05-22T22:15:01.874Z
A43: 46163 | B43: 120241930909210731 | C43: SUPER HOT | D43: ACTIVE | E43: OUTCOME_SALES | F43: 2.92 | G43: 680 | H43: 455 | I43: 1.494505 | J43: 21 | K43: 12 | L43: 3.088235 | M43: 0.139048 | N43: 4.294118 | O43: 11 | P43: 60 | Q43: 1 | R43: 2 | S43: 1 | T43: 1 | U43: 108 | V43: 2.92 | W43: 36.986301 | X43: 2026-05-22T22:15:02.863Z
A44: 46164 | B44: 120244032235930731 | C44: COLD | D44: ACTIVE | E44: OUTCOME_SALES | F44: 20.68 | G44: 4133 | H44: 2673 | I44: 1.546203 | J44: 142 | K44: 89 | L44: 3.435761 | M44: 0.145634 | N44: 5.003629 | O44: 43 | P44: 83 | Q44: 0 | R44: 0 | S44: 0 | T44: 0 | U44: 0 | W44: 0 | X44: 2026-05-22T22:15:05.413Z
A45: 46164 | B45: 120241930909210731 | C45: SUPER HOT | D45: ACTIVE | E45: OUTCOME_SALES | F45: 2.79 | G45: 616 | H45: 360 | I45: 1.711111 | J45: 16 | K45: 10 | L45: 2.597403 | M45: 0.174375 | N45: 4.529221 | O45: 5 | P45: 26 | Q45: 1 | R45: 1 | S45: 0 | T45: 0 | U45: 0 | W45: 0 | X45: 2026-05-22T22:15:06.302Z
A46: 46171 | B46: 120244032235930731 | C46: COLD | D46: ACTIVE | E46: OUTCOME_SALES | F46: 19.91 | G46: 4563 | H46: 3186 | I46: 1.432203 | J46: 146 | K46: 91 | L46: 3.199649 | M46: 0.13637 | N46: 4.363357 | O46: 52 | P46: 81 | Q46: 0 | R46: 0 | S46: 0 | T46: 0 | U46: 0 | W46: 0 | X46: 2026-05-30T21:39:17.069Z
A47: 46171 | B47: 120241930909210731 | C47: SUPER HOT | D47: ACTIVE | E47: OUTCOME_SALES | F47: 2.87 | G47: 552 | H47: 307 | I47: 1.798046 | J47: 13 | K47: 8 | L47: 2.355072 | M47: 0.220769 | N47: 5.199275 | O47: 5 | P47: 55 | Q47: 3 | R47: 2 | S47: 2 | T47: 0 | U47: 0 | W47: 0 | X47: 2026-05-30T21:39:18.170Z
A48: 46171 | B48: 120244032235930731 | C48: COLD | D48: ACTIVE | E48: OUTCOME_SALES | F48: 19.91 | G48: 4563 | H48: 3186 | I48: 1.432203 | J48: 146 | K48: 91 | L48: 3.199649 | M48: 0.13637 | N48: 4.363357 | O48: 52 | P48: 81 | Q48: 0 | R48: 0 | S48: 0 | T48: 0 | U48: 0 | W48: 0 | X48: 2026-05-30T21:39:29.949Z
A49: 46171 | B49: 120241930909210731 | C49: SUPER HOT | D49: ACTIVE | E49: OUTCOME_SALES | F49: 2.87 | G49: 552 | H49: 307 | I49: 1.798046 | J49: 13 | K49: 8 | L49: 2.355072 | M49: 0.220769 | N49: 5.199275 | O49: 5 | P49: 55 | Q49: 3 | R49: 2 | S49: 2 | T49: 0 | U49: 0 | W49: 0 | X49: 2026-05-30T21:39:31.013Z
A50: 46165 | B50: 120244032235930731 | C50: COLD | D50: ACTIVE | E50: OUTCOME_SALES | F50: 23.77 | G50: 5150 | H50: 3255 | I50: 1.582181 | J50: 185 | K50: 116 | L50: 3.592233 | M50: 0.128486 | N50: 4.615534 | O50: 75 | P50: 126 | Q50: 0 | R50: 0 | S50: 0 | T50: 0 | U50: 0 | W50: 0 | X50: 2026-05-30T21:39:46.977Z
A51: 46165 | B51: 120241930909210731 | C51: SUPER HOT | D51: ACTIVE | E51: OUTCOME_SALES | F51: 2.39 | G51: 617 | H51: 480 | I51: 1.285417 | J51: 16 | K51: 11 | L51: 2.593193 | M51: 0.149375 | N51: 3.873582 | O51: 6 | P51: 26 | Q51: 1 | R51: 1 | S51: 0 | T51: 0 | U51: 0 | W51: 0 | X51: 2026-05-30T21:39:48.040Z
A52: 46166 | B52: 120244032235930731 | C52: COLD | D52: ACTIVE | E52: OUTCOME_SALES | F52: 23.22 | G52: 5300 | H52: 3250 | I52: 1.630769 | J52: 141 | K52: 100 | L52: 2.660377 | M52: 0.164681 | N52: 4.381132 | O52: 57 | P52: 104 | Q52: 1 | R52: 0 | S52: 0 | T52: 0 | U52: 0 | W52: 0 | X52: 2026-05-30T21:39:55.111Z
A53: 46166 | B53: 120241930909210731 | C53: SUPER HOT | D53: ACTIVE | E53: OUTCOME_SALES | F53: 3.52 | G53: 1005 | H53: 548 | I53: 1.833942 | J53: 37 | K53: 18 | L53: 3.681592 | M53: 0.095135 | N53: 3.502488 | O53: 11 | P53: 36 | Q53: 0 | R53: 0 | S53: 0 | T53: 0 | U53: 0 | W53: 0 | X53: 2026-05-30T21:39:56.113Z
A54: 46167 | B54: 120244032235930731 | C54: COLD | D54: ACTIVE | E54: OUTCOME_SALES | F54: 23.3 | G54: 6079 | H54: 3890 | I54: 1.562725 | J54: 202 | K54: 129 | L54: 3.322915 | M54: 0.115347 | N54: 3.832867 | O54: 72 | P54: 156 | Q54: 1 | R54: 1 | S54: 0 | T54: 0 | U54: 0 | W54: 0 | X54: 2026-05-30T21:40:01.822Z
A55: 46167 | B55: 120241930909210731 | C55: SUPER HOT | D55: ACTIVE | E55: OUTCOME_SALES | F55: 3.13 | G55: 819 | H55: 503 | I55: 1.628231 | J55: 26 | K55: 18 | L55: 3.174603 | M55: 0.120385 | N55: 3.821734 | O55: 11 | P55: 33 | Q55: 0 | R55: 0 | S55: 0 | T55: 0 | U55: 0 | W55: 0 | X55: 2026-05-30T21:40:03.077Z
A56: 46168 | B56: 120244032235930731 | C56: COLD | D56: ACTIVE | E56: OUTCOME_SALES | F56: 22.52 | G56: 4643 | H56: 2802 | I56: 1.657031 | J56: 137 | K56: 79 | L56: 2.950678 | M56: 0.16438 | N56: 4.850312 | O56: 47 | P56: 108 | Q56: 0 | R56: 0 | S56: 0 | T56: 0 | U56: 0 | W56: 0 | X56: 2026-05-30T21:40:09.384Z
A57: 46168 | B57: 120241930909210731 | C57: SUPER HOT | D57: ACTIVE | E57: OUTCOME_SALES | F57: 1.66 | G57: 518 | H57: 417 | I57: 1.242206 | J57: 9 | K57: 5 | L57: 1.737452 | M57: 0.184444 | N57: 3.204633 | O57: 1 | P57: 14 | Q57: 1 | R57: 2 | S57: 1 | T57: 1 | U57: 90 | V57: 1.66 | W57: 54.216867 | X57: 2026-05-30T21:40:10.526Z
A58: 46169 | B58: 120244032235930731 | C58: COLD | D58: ACTIVE | E58: OUTCOME_SALES | F58: 22.15 | G58: 5034 | H58: 3412 | I58: 1.475381 | J58: 175 | K58: 118 | L58: 3.476361 | M58: 0.126571 | N58: 4.400079 | O58: 73 | P58: 144 | Q58: 3 | R58: 0 | S58: 0 | T58: 0 | U58: 0 | W58: 0 | X58: 2026-05-30T21:40:16.947Z
A59: 46169 | B59: 120241930909210731 | C59: SUPER HOT | D59: ACTIVE | E59: OUTCOME_SALES | F59: 3.68 | G59: 795 | H59: 504 | I59: 1.577381 | J59: 29 | K59: 13 | L59: 3.647799 | M59: 0.126897 | N59: 4.628931 | O59: 6 | P59: 133 | Q59: 4 | R59: 7 | S59: 6 | T59: 3 | U59: 348 | V59: 1.2266667 | W59: 94.565217 | X59: 2026-05-30T21:40:18.204Z
A60: 46170 | B60: 120244032235930731 | C60: COLD | D60: ACTIVE | E60: OUTCOME_SALES | F60: 21.15 | G60: 4890 | H60: 3545 | I60: 1.379408 | J60: 180 | K60: 110 | L60: 3.680982 | M60: 0.1175 | N60: 4.325153 | O60: 60 | P60: 175 | Q60: 4 | R60: 3 | S60: 0 | T60: 0 | U60: 0 | W60: 0 | X60: 2026-05-30T21:40:23.706Z
A61: 46170 | B61: 120241930909210731 | C61: SUPER HOT | D61: ACTIVE | E61: OUTCOME_SALES | F61: 3.86 | G61: 903 | H61: 494 | I61: 1.827935 | J61: 18 | K61: 9 | L61: 1.993355 | M61: 0.214444 | N61: 4.27464 | O61: 4 | P61: 55 | Q61: 9 | R61: 6 | S61: 3 | T61: 2 | U61: 228 | V61: 1.93 | W61: 59.067358 | X61: 2026-05-30T21:40:24.801Z
A62: 46172 | B62: 120244032235930731 | C62: COLD | D62: ACTIVE | E62: OUTCOME_SALES | F62: 21.72 | G62: 5888 | H62: 4232 | I62: 1.391304 | J62: 150 | K62: 102 | L62: 2.547554 | M62: 0.1448 | N62: 3.688859 | O62: 52 | P62: 156 | Q62: 3 | R62: 4 | S62: 1 | T62: 2 | U62: 297 | V62: 10.86 | W62: 13.674033 | X62: 2026-05-31T05:29:30.715Z
A63: 46172 | B63: 120241930909210731 | C63: SUPER HOT | D63: ACTIVE | E63: OUTCOME_SALES | F63: 1.95 | G63: 526 | H63: 402 | I63: 1.308458 | J63: 13 | K63: 10 | L63: 2.471483 | M63: 0.15 | N63: 3.707224 | O63: 5 | P63: 28 | Q63: 2 | R63: 4 | S63: 1 | T63: 0 | U63: 0 | W63: 0 | X63: 2026-05-31T05:29:31.830Z
A64: 46173 | B64: 120244032235930731 | C64: COLD | D64: ACTIVE | E64: OUTCOME_SALES | F64: 27.5 | G64: 6112 | H64: 3522 | I64: 1.735378 | J64: 213 | K64: 133 | L64: 3.484948 | M64: 0.129108 | N64: 4.499346 | O64: 85 | P64: 227 | Q64: 4 | R64: 2 | S64: 1 | T64: 0 | U64: 0 | W64: 0 | X64: 2026-06-01T05:29:35.400Z
A65: 46173 | B65: 120241930909210731 | C65: SUPER HOT | D65: ACTIVE | E65: OUTCOME_SALES | F65: 3.32 | G65: 1017 | H65: 783 | I65: 1.298851 | J65: 43 | K65: 29 | L65: 4.228122 | M65: 0.077209 | N65: 3.264503 | O65: 16 | P65: 43 | Q65: 0 | R65: 1 | S65: 0 | T65: 0 | U65: 0 | W65: 0 | X65: 2026-06-01T05:29:36.934Z
A66: 46174 | B66: 120244032235930731 | C66: COLD | D66: ACTIVE | E66: OUTCOME_SALES | F66: 22.3 | G66: 5067 | H66: 3360 | I66: 1.508036 | J66: 179 | K66: 116 | L66: 3.532662 | M66: 0.124581 | N66: 4.401026 | O66: 56 | P66: 126 | Q66: 2 | R66: 5 | S66: 4 | T66: 0 | U66: 0 | W66: 0 | X66: 2026-06-02T05:29:31.461Z
A67: 46174 | B67: 120241930909210731 | C67: SUPER HOT | D67: ACTIVE | E67: OUTCOME_SALES | F67: 3.41 | G67: 918 | H67: 459 | I67: 2 | J67: 22 | K67: 16 | L67: 2.396514 | M67: 0.155 | N67: 3.714597 | O67: 11 | P67: 57 | Q67: 6 | R67: 7 | S67: 4 | T67: 2 | U67: 183.9 | V67: 1.705 | W67: 53.929619 | X67: 2026-06-02T05:29:32.599Z
A68: 46175 | B68: 120244032235930731 | C68: COLD | D68: ACTIVE | E68: OUTCOME_SALES | F68: 28.76 | G68: 11842 | H68: 9049 | I68: 1.308653 | J68: 282 | K68: 167 | L68: 2.381355 | M68: 0.101986 | N68: 2.428644 | O68: 117 | P68: 255 | Q68: 3 | R68: 1 | S68: 1 | T68: 1 | U68: 315 | V68: 28.76 | W68: 10.952712 | X68: 2026-06-03T05:29:29.711Z
A69: 46175 | B69: 120241930909210731 | C69: SUPER HOT | D69: ACTIVE | E69: OUTCOME_SALES | F69: 3.18 | G69: 1025 | H69: 650 | I69: 1.576923 | J69: 33 | K69: 24 | L69: 3.219512 | M69: 0.096364 | N69: 3.102439 | O69: 13 | P69: 84 | Q69: 0 | R69: 1 | S69: 0 | T69: 0 | U69: 0 | W69: 0 | X69: 2026-06-03T05:29:31.115Z
A70: 46176 | B70: 120244032235930731 | C70: COLD | D70: ACTIVE | E70: OUTCOME_SALES | F70: 28.77 | G70: 9455 | H70: 7233 | I70: 1.307203 | J70: 245 | K70: 138 | L70: 2.591222 | M70: 0.117429 | N70: 3.042834 | O70: 71 | P70: 213 | Q70: 3 | R70: 7 | S70: 5 | T70: 1 | U70: 108 | V70: 28.77 | W70: 3.7539103 | X70: 2026-06-04T05:29:31.519Z
A71: 46176 | B71: 120241930909210731 | C71: SUPER HOT | D71: ACTIVE | E71: OUTCOME_SALES | F71: 2.19 | G71: 624 | H71: 361 | I71: 1.728532 | J71: 11 | K71: 5 | L71: 1.762821 | M71: 0.199091 | N71: 3.509615 | O71: 2 | P71: 27 | Q71: 2 | R71: 3 | S71: 2 | T71: 2 | U71: 201 | V71: 1.095 | W71: 91.780822 | X71: 2026-06-04T05:29:33.672Z
A72: 46177 | B72: 120244032235930731 | C72: COLD | D72: ACTIVE | E72: OUTCOME_SALES | F72: 21.89 | G72: 7149 | H72: 5536 | I72: 1.291366 | J72: 182 | K72: 84 | L72: 2.545811 | M72: 0.120275 | N72: 3.061967 | O72: 59 | P72: 186 | Q72: 6 | R72: 6 | S72: 0 | T72: 0 | U72: 0 | W72: 0 | X72: 2026-06-05T05:29:31.779Z
A73: 46177 | B73: 120241930909210731 | C73: SUPER HOT | D73: ACTIVE | E73: OUTCOME_SALES | F73: 2.93 | G73: 752 | H73: 401 | I73: 1.875312 | J73: 30 | K73: 18 | L73: 3.989362 | M73: 0.097667 | N73: 3.896277 | O73: 13 | P73: 34 | Q73: 0 | R73: 0 | S73: 2 | T73: 2 | U73: 247.5 | V73: 1.465 | W73: 84.47099 | X73: 2026-06-05T05:29:33.775Z
A74: 46178 | B74: 120244032235930731 | C74: COLD | D74: ACTIVE | E74: OUTCOME_SALES | F74: 27.11 | G74: 6331 | H74: 4393 | I74: 1.441156 | J74: 132 | K74: 82 | L74: 2.084979 | M74: 0.205379 | N74: 4.282104 | O74: 34 | P74: 110 | Q74: 2 | R74: 1 | S74: 0 | T74: 0 | U74: 0 | W74: 0 | X74: 2026-06-06T05:29:28.268Z
A75: 46178 | B75: 120241930909210731 | C75: SUPER HOT | D75: ACTIVE | E75: OUTCOME_SALES | F75: 0.96 | G75: 336 | H75: 257 | I75: 1.307393 | J75: 5 | K75: 1 | L75: 1.488095 | M75: 0.192 | N75: 2.857143 | O75: 0 | P75: 12 | Q75: 1 | R75: 4 | S75: 6 | T75: 0 | U75: 0 | W75: 0 | X75: 2026-06-06T05:29:29.978Z
A76: 46178 | B76: 120244032235930731 | C76: COLD | D76: ACTIVE | E76: OUTCOME_SALES | F76: 27.14 | G76: 6333 | H76: 4393 | I76: 1.441612 | J76: 132 | K76: 82 | L76: 2.08432 | M76: 0.205606 | N76: 4.285489 | O76: 34 | P76: 110 | Q76: 2 | R76: 1 | S76: 0 | T76: 0 | U76: 0 | W76: 0 | X76: 2026-06-06T12:27:05.698Z
A77: 46178 | B77: 120241930909210731 | C77: SUPER HOT | D77: ACTIVE | E77: OUTCOME_SALES | F77: 0.98 | G77: 341 | H77: 260 | I77: 1.311538 | J77: 5 | K77: 1 | L77: 1.466276 | M77: 0.196 | N77: 2.8739 | O77: 0 | P77: 12 | Q77: 1 | R77: 4 | S77: 6 | T77: 0 | U77: 0 | W77: 0 | X77: 2026-06-06T12:27:07.630Z
A78: 46179 | B78: 120244032235930731 | C78: COLD | D78: ACTIVE | E78: OUTCOME_SALES | F78: 17.25 | G78: 3959 | H78: 2763 | I78: 1.432863 | J78: 112 | K78: 68 | L78: 2.828997 | M78: 0.154018 | N78: 4.357161 | O78: 43 | P78: 132 | Q78: 5 | R78: 4 | S78: 5 | T78: 2 | U78: 183.9 | V78: 8.625 | W78: 10.66087 | X78: 2026-06-07T05:29:31.328Z
A79: 46179 | B79: 120241930909210731 | C79: SUPER HOT | D79: ACTIVE | E79: OUTCOME_SALES | F79: 4.61 | G79: 1027 | H79: 658 | I79: 1.56079 | J79: 33 | K79: 22 | L79: 3.213242 | M79: 0.139697 | N79: 4.488802 | O79: 15 | P79: 36 | Q79: 3 | R79: 3 | S79: 1 | T79: 1 | U79: 120 | V79: 4.61 | W79: 26.030369 | X79: 2026-06-07T05:29:33.247Z
A80: 46180 | B80: 120244032235930731 | C80: COLD | D80: ACTIVE | E80: OUTCOME_SALES | F80: 23.79 | G80: 5521 | H80: 3055 | I80: 1.807201 | J80: 117 | K80: 78 | L80: 2.119181 | M80: 0.203333 | N80: 4.309002 | O80: 38 | P80: 119 | Q80: 1 | R80: 1 | S80: 1 | T80: 1 | U80: 75.9 | V80: 23.79 | W80: 3.1904161 | X80: 2026-06-08T05:29:30.917Z
A81: 46180 | B81: 120241930909210731 | C81: SUPER HOT | D81: ACTIVE | E81: OUTCOME_SALES | F81: 3.87 | G81: 983 | H81: 511 | I81: 1.923679 | J81: 39 | K81: 17 | L81: 3.967447 | M81: 0.099231 | N81: 3.936928 | O81: 12 | P81: 82 | Q81: 8 | R81: 8 | S81: 2 | T81: 2 | U81: 186.9 | V81: 1.935 | W81: 48.294574 | X81: 2026-06-08T05:29:32.827Z
A82: 46181 | B82: 120244032235930731 | C82: COLD | D82: ACTIVE | E82: OUTCOME_SALES | F82: 24.33 | G82: 6411 | H82: 4012 | I82: 1.597956 | J82: 153 | K82: 111 | L82: 2.386523 | M82: 0.15902 | N82: 3.79504 | O82: 57 | P82: 112 | Q82: 2 | R82: 1 | S82: 1 | T82: 1 | U82: 75.9 | V82: 24.33 | W82: 3.1196054 | X82: 2026-06-09T05:29:31.242Z
A83: 46181 | B83: 120241930909210731 | C83: SUPER HOT | D83: ACTIVE | E83: OUTCOME_SALES | F83: 2.59 | G83: 622 | H83: 346 | I83: 1.797688 | J83: 20 | K83: 11 | L83: 3.215434 | M83: 0.1295 | N83: 4.163987 | O83: 11 | P83: 47 | Q83: 1 | R83: 3 | S83: 0 | T83: 0 | U83: 0 | W83: 0 | X83: 2026-06-09T05:29:33.482Z
A84: 46182 | B84: 120244032235930731 | C84: COLD | D84: ACTIVE | E84: OUTCOME_SALES | F84: 22.46 | G84: 6251 | H84: 4278 | I84: 1.461197 | J84: 199 | K84: 108 | L84: 3.183491 | M84: 0.112864 | N84: 3.593025 | O84: 68 | P84: 316 | Q84: 15 | R84: 7 | S84: 3 | T84: 2 | U84: 258 | V84: 11.23 | W84: 11.487088 | X84: 2026-06-10T05:29:30.542Z
A85: 46182 | B85: 120241930909210731 | C85: SUPER HOT | D85: ACTIVE | E85: OUTCOME_SALES | F85: 3.74 | G85: 833 | H85: 460 | I85: 1.81087 | J85: 26 | K85: 13 | L85: 3.121249 | M85: 0.143846 | N85: 4.489796 | O85: 8 | P85: 49 | Q85: 4 | R85: 2 | S85: 1 | T85: 1 | U85: 81 | V85: 3.74 | W85: 21.657754 | X85: 2026-06-10T05:29:32.391Z
A86: 46183 | B86: 120244032235930731 | C86: COLD | D86: ACTIVE | E86: OUTCOME_SALES | F86: 31.45 | G86: 5669 | H86: 2979 | I86: 1.902988 | J86: 154 | K86: 98 | L86: 2.716528 | M86: 0.204221 | N86: 5.547716 | O86: 61 | P86: 169 | Q86: 2 | R86: 5 | S86: 2 | T86: 2 | U86: 228 | V86: 15.725 | W86: 7.2496025 | X86: 2026-06-11T05:29:30.764Z
A87: 46183 | B87: 120241930909210731 | C87: SUPER HOT | D87: ACTIVE | E87: OUTCOME_SALES | F87: 2.42 | G87: 688 | H87: 531 | I87: 1.295669 | J87: 33 | K87: 23 | L87: 4.796512 | M87: 0.073333 | N87: 3.517442 | O87: 18 | P87: 70 | Q87: 1 | R87: 0 | S87: 0 | T87: 0 | U87: 0 | W87: 0 | X87: 2026-06-11T05:29:32.812Z
A88: 46184 | B88: 120244032235930731 | C88: COLD | D88: ACTIVE | E88: OUTCOME_SALES | F88: 25.55 | G88: 6585 | H88: 4248 | I88: 1.550141 | J88: 176 | K88: 104 | L88: 2.672741 | M88: 0.14517 | N88: 3.88003 | O88: 57 | P88: 125 | Q88: 4 | R88: 4 | S88: 2 | T88: 1 | U88: 21.9 | V88: 25.55 | W88: 0.85714286 | X88: 2026-06-12T05:29:29.666Z
A89: 46184 | B89: 120241930909210731 | C89: SUPER HOT | D89: ACTIVE | E89: OUTCOME_SALES | F89: 3.24 | G89: 782 | H89: 417 | I89: 1.8753 | J89: 19 | K89: 14 | L89: 2.429668 | M89: 0.170526 | N89: 4.143223 | O89: 12 | P89: 42 | Q89: 3 | R89: 6 | S89: 3 | T89: 3 | U89: 245.7 | V89: 1.08 | W89: 75.833333 | X89: 2026-06-12T05:29:31.590Z
A90: 46185 | B90: 120244032235930731 | C90: COLD | D90: ACTIVE | E90: OUTCOME_SALES | F90: 20.97 | G90: 4728 | H90: 2850 | I90: 1.658947 | J90: 108 | K90: 67 | L90: 2.284264 | M90: 0.194167 | N90: 4.435279 | O90: 41 | P90: 90 | Q90: 4 | R90: 2 | S90: 0 | T90: 0 | U90: 0 | W90: 0 | X90: 2026-06-13T05:29:30.533Z
A91: 46185 | B91: 120241930909210731 | C91: SUPER HOT | D91: ACTIVE | E91: OUTCOME_SALES | F91: 1.86 | G91: 485 | H91: 308 | I91: 1.574675 | J91: 16 | K91: 8 | L91: 3.298969 | M91: 0.11625 | N91: 3.835052 | O91: 7 | P91: 48 | Q91: 0 | R91: 0 | S91: 0 | T91: 0 | U91: 0 | W91: 0 | X91: 2026-06-13T05:29:31.987Z
A92: 46186 | B92: 120244032235930731 | C92: COLD | D92: ACTIVE | E92: OUTCOME_SALES | F92: 26.22 | G92: 6273 | H92: 3953 | I92: 1.586896 | J92: 145 | K92: 104 | L92: 2.311494 | M92: 0.180828 | N92: 4.179818 | O92: 48 | P92: 111 | Q92: 1 | R92: 1 | S92: 0 | T92: 0 | U92: 0 | W92: 0 | X92: 2026-06-14T05:29:30.506Z
A93: 46186 | B93: 120241930909210731 | C93: SUPER HOT | D93: ACTIVE | E93: OUTCOME_SALES | F93: 2.36 | G93: 606 | H93: 434 | I93: 1.396313 | J93: 10 | K93: 6 | L93: 1.650165 | M93: 0.236 | N93: 3.894389 | O93: 6 | P93: 27 | Q93: 0 | R93: 0 | S93: 0 | T93: 0 | U93: 0 | W93: 0 | X93: 2026-06-14T05:29:32.268Z
A94: 46187 | B94: 120244032235930731 | C94: COLD | D94: ACTIVE | E94: OUTCOME_SALES | F94: 20.54 | G94: 6284 | H94: 4169 | I94: 1.507316 | J94: 170 | K94: 106 | L94: 2.705283 | M94: 0.120824 | N94: 3.268619 | O94: 56 | P94: 157 | Q94: 0 | R94: 0 | S94: 0 | T94: 0 | U94: 0 | W94: 0 | X94: 2026-06-15T05:29:32.756Z
A95: 46187 | B95: 120241930909210731 | C95: SUPER HOT | D95: ACTIVE | E95: OUTCOME_SALES | F95: 4.28 | G95: 1115 | H95: 619 | I95: 1.801292 | J95: 44 | K95: 28 | L95: 3.946188 | M95: 0.097273 | N95: 3.838565 | O95: 19 | P95: 56 | Q95: 5 | R95: 4 | S95: 3 | T95: 3 | U95: 450 | V95: 1.4266667 | W95: 105.14019 | X95: 2026-06-15T05:29:35.172Z
A96: 46187 | B96: 120244032235930731 | C96: COLD | D96: ACTIVE | E96: OUTCOME_SALES | F96: 20.54 | G96: 6286 | H96: 4171 | I96: 1.507073 | J96: 170 | K96: 106 | L96: 2.704423 | M96: 0.120824 | N96: 3.267579 | O96: 56 | P96: 157 | Q96: 0 | R96: 0 | S96: 0 | T96: 0 | U96: 0 | W96: 0 | X96: 2026-06-15T09:01:41.299Z
A97: 46187 | B97: 120241930909210731 | C97: SUPER HOT | D97: ACTIVE | E97: OUTCOME_SALES | F97: 4.28 | G97: 1116 | H97: 619 | I97: 1.802908 | J97: 44 | K97: 28 | L97: 3.942652 | M97: 0.097273 | N97: 3.835125 | O97: 19 | P97: 56 | Q97: 5 | R97: 4 | S97: 3 | T97: 3 | U97: 450 | V97: 1.4266667 | W97: 105.14019 | X97: 2026-06-15T09:01:43.664Z
A98: 46188 | B98: 120244032235930731 | C98: COLD | D98: ACTIVE | E98: OUTCOME_SALES | F98: 29.26 | G98: 6732 | H98: 3766 | I98: 1.787573 | J98: 159 | K98: 99 | L98: 2.361854 | M98: 0.184025 | N98: 4.346405 | O98: 64 | P98: 126 | Q98: 1 | R98: 2 | S98: 0 | T98: 0 | U98: 0 | W98: 0 | X98: 2026-06-16T05:29:28.015Z
A99: 46188 | B99: 120241930909210731 | C99: SUPER HOT | D99: ACTIVE | E99: OUTCOME_SALES | F99: 1.93 | G99: 718 | H99: 589 | I99: 1.219015 | J99: 24 | K99: 13 | L99: 3.342618 | M99: 0.080417 | N99: 2.688022 | O99: 9 | P99: 38 | Q99: 0 | R99: 0 | S99: 0 | T99: 0 | U99: 0 | W99: 0 | X99: 2026-06-16T05:29:30.037Z
A100: 46189 | B100: 120244032235930731 | C100: COLD | D100: ACTIVE | E100: OUTCOME_SALES | F100: 27.24 | G100: 6992 | H100: 4700 | I100: 1.48766 | J100: 170 | K100: 105 | L100: 2.43135 | M100: 0.160235 | N100: 3.895881 | O100: 50 | P100: 120 | Q100: 0 | R100: 0 | S100: 0 | T100: 0 | U100: 0 | W100: 0 | X100: 2026-06-17T05:29:31.955Z
...

Sheet CHECK
A1: SECTION | B1: CHECK NAME | C1: STATUS | D1: DETAIL | E1: LAST REFRESHED
A2: 📦 PRODUCTS
B3: ACQUISTI products not in Product_Map | C3: ✅ | D3: All Prodotto Finito items are mapped
B4: Products with COGS = 0 or blank | C4: =IF(COUNTIFS('PRODUCT_COGS&PRICE'!A2:A526,"<>",'PRODUCT_COGS&PRICE'!E2:E526,0)+COUNTIFS('PRODUCT_COGS&PRICE'!A2:A526,"<>",'PRODUCT_COGS&PRICE'!E2:E526,"")=0,"✅","❌") -> ✅ | D4: ="Products with COGS=0 or blank: "&COUNTIFS('PRODUCT_COGS&PRICE'!A2:A526,"<>",'PRODUCT_COGS&PRICE'!E2:E526,0)+COUNTIFS('PRODUCT_COGS&PRICE'!A2:A526,"<>",'PRODUCT_COGS&PRICE'!E2:E526,"") -> Products with COGS=0 or blank: 0
B5: Products with Selling Price = 0 or blank | C5: =IF(COUNTIFS('PRODUCT_COGS&PRICE'!A2:A526,"<>",'PRODUCT_COGS&PRICE'!D2:D526,0)+COUNTIFS('PRODUCT_COGS&PRICE'!A2:A526,"<>",'PRODUCT_COGS&PRICE'!D2:D526,"")=0,"✅","❌") -> ✅ | D5: ="Products with Price=0 or blank: "&COUNTIFS('PRODUCT_COGS&PRICE'!A2:A526,"<>",'PRODUCT_COGS&PRICE'!D2:D526,0)+COUNTIFS('PRODUCT_COGS&PRICE'!A2:A526,"<>",'PRODUCT_COGS&PRICE'!D2:D526,"") -> Products with Price=0 or blank: 0
B6: Duplicate CODICE_AMIIMI in Product_Map | C6: ℹ️ | D6: Duplicate CODICE rows in col B: 152 (intentional: size variants / multiple Shopify names per CODICE). Old formula pointed at empty col J.
A7: 💰 SALES
B8: DB Shopify has order data | C8: =IF(COUNTA('DB Shopify'!A2:A500)>0,"✅","❌") -> ✅ | D8: ="Shopify rows: "&COUNTA('DB Shopify'!A2:A500) -> Shopify rows: 466
B9: DB_QROMO has order data | C9: =IF(COUNTA(DB_QROMO!A2:A594)>0,"✅","❌") -> ✅ | D9: ="Qromo rows: "&COUNTA(DB_QROMO!A2:A594) -> Qromo rows: 149
B10: No stale 2025 dates in Import | C10: =IF(COUNTIF(Import!A2:A347,"*2025*")=0,"✅","❌") -> ✅ | D10: ="Rows with 2025 dates: "&COUNTIF(Import!A2:A347,"*2025*") -> Rows with 2025 dates: 0
B11: No stale 2025 years in DB_QROMO | C11: =IF(COUNTIF(DB_QROMO!A2:A594,2025)=0,"✅","❌") -> ✅ | D11: ="Rows with YEAR=2025: "&COUNTIF(DB_QROMO!A2:A594,2025) -> Rows with YEAR=2025: 0
A12: 📊 EXPENSES
B13: EXPENSES MASTER - Amimi? values valid | C13: =IF(COUNTIFS('EXPENSES MASTER'!I2:I532,"<>",'EXPENSES MASTER'!I2:I532,"<>Si",'EXPENSES MASTER'!I2:I532,"<>No")=0,"✅","❌") -> ✅ | D13: ="Invalid Amimi? values: "&COUNTIFS('EXPENSES MASTER'!I2:I532,"<>",'EXPENSES MASTER'!I2:I532,"<>Si",'EXPENSES MASTER'!I2:I532,"<>No") -> Invalid Amimi? values: 0
B14: EXPENSES MASTER - CATEGORIA values valid | C14: =IF(COUNTIFS('EXPENSES MASTER'!G2:G532,"<>",'EXPENSES MASTER'!G2:G532,"<>COGS",'EXPENSES MASTER'!G2:G532,"<>LOGISTICA",'EXPENSES MASTER'!G2:G532,"<>MARKETING",'EXPENSES MASTER'!G2:G532,"<>OPEX",'EXPENSES MASTER'!G2:G532,"<>PACKAGING",'EXPENSES MASTER'!G2:G532,"<>SALARI",'EXPENSES MASTER'!G2:G532,"<>TASSE")=0,"✅","❌") -> ✅ | D14: ="Invalid CATEGORIA values: "&COUNTIFS('EXPENSES MASTER'!G2:G532,"<>",'EXPENSES MASTER'!G2:G532,"<>COGS",'EXPENSES MASTER'!G2:G532,"<>LOGISTICA",'EXPENSES MASTER'!G2:G532,"<>MARKETING",'EXPENSES MASTER'!G2:G532,"<>OPEX",'EXPENSES MASTER'!G2:G532,"<>PACKAGING",'EXPENSES MASTER'!G2:G532,"<>SALARI",'EXPENSES MASTER'!G2:G532,"<>TASSE") -> Invalid CATEGORIA values: 0
B15: ACQUISTI - Tipologia values valid | C15: =IF(COUNTIFS(ACQUISTI!D2:D615,"<>",ACQUISTI!D2:D615,"<>Prodotto Finito",ACQUISTI!D2:D615,"<>Materia Prima")=0,"✅","❌") -> ✅ | D15: ="Invalid Tipologia: "&COUNTIFS(ACQUISTI!D2:D615,"<>",ACQUISTI!D2:D615,"<>Prodotto Finito",ACQUISTI!D2:D615,"<>Materia Prima") -> Invalid Tipologia: 0
B16: No uncategorized expenses | C16: =IF(COUNTIFS('EXPENSES MASTER'!A2:A532,"<>",'EXPENSES MASTER'!G2:G532,"")=0,"✅","❌") -> ✅ | D16: ="Expenses missing CATEGORIA: "&COUNTIFS('EXPENSES MASTER'!A2:A532,"<>",'EXPENSES MASTER'!G2:G532,"") -> Expenses missing CATEGORIA: 0
A17: 📈 CE / P&L
B18: CE_AMIMI shows revenue in at least 1 month | C18: =IF(SUMPRODUCT((CE_AMIMI!G28:R28<>0)*1)>0,"✅","❌") -> ✅ | D18: ="Months with revenue (Fatturato Lordo row 24): "&SUMPRODUCT((CE_AMIMI!G28:R28<>0)*1)&" of 12" -> Months with revenue (Fatturato Lordo row 24): 6 of 12
B19: CE_AMIMI shows COGS in at least 1 month | C19: =IF(SUMPRODUCT((CE_AMIMI!G31:R31<>0)*1)>0,"✅","❌") -> ✅ | D19: ="Months with COGS (row 27): "&SUMPRODUCT((CE_AMIMI!G31:R31<>0)*1)&" of 12" -> Months with COGS (row 27): 6 of 12
B20: GIFT_OFFLINE - no stale 2025 dates | C20: =IF(COUNTIF(GIFT_OFFLINE!A2:A201,2025)=0,"✅","❌") -> ✅ | D20: ="GIFT_OFFLINE rows with YEAR=2025: "&COUNTIF(GIFT_OFFLINE!A2:A201,2025) -> GIFT_OFFLINE rows with YEAR=2025: 0
B21: Record counts across all tabs | C21: ℹ️ | D21: ="ACQUISTI: "&COUNTA(ACQUISTI!A2:A615)&" | EXPENSES: "&COUNTA('EXPENSES MASTER'!A2:A532)&" | Shopify: "&COUNTA('DB Shopify'!A2:A500)&" | Qromo: "&COUNTA(DB_QROMO!A2:A594)&" | Gifts: "&COUNTA(GIFT_OFFLINE!A2:A201) -> ACQUISTI: 231 | EXPENSES: 278 | Shopify: 466 | Qromo: 149 | Gifts: 125
A23: OVERALL STATUS | C23: =IF(COUNTIF(C3:C21,"❌")=0,"✅","❌") -> ✅ | D23: =IF(C23="✅","All checks passed!","⚠️ "&COUNTIF(C3:C21,"❌")&" check(s) need attention - scroll up to see ❌ items") -> All checks passed!
A24: Last refreshed | D24: =NOW() -> 46205.622

Sheet CE_TOTALE
B1: AC | G1: =G2&G3 -> 20261 | H1: =H2&H3 -> 20262 | I1: =I2&I3 -> 20263 | J1: =J2&J3 -> 20264 | K1: =K2&K3 -> 20265 | L1: =L2&L3 -> 20266 | M1: =M2&M3 -> 20267 | N1: =N2&N3 -> 20268 | ... R1: =R2&R3 -> 202612
F2: YEAR | G2: 2026 | H2: 2026 | I2: 2026 | J2: 2026 | K2: 2026 | L2: 2026 | M2: 2026 | N2: 2026 | O2: 2026 | P2: 2026 | Q2: 2026 | R2: 2026
F3: MONTH | G3: 1 | H3: 2 | I3: 3 | J3: 4 | K3: 5 | L3: 6 | M3: 7 | N3: 8 | O3: 9 | P3: 10 | Q3: 11 | R3: 12
F4: QUARTER | G4: 1 | H4: 1 | I4: 1 | J4: 2 | K4: 2 | L4: 2 | M4: 3 | N4: 3 | O4: 3 | P4: 4 | Q4: 4 | R4: 4
F5: YTD | G5: YTD | H5: YTD | I5: YTD | J5: YTD | K5: YTD | L5: YTD | M5: YTD | N5: YTD | O5: YTD | P5: YTD
C6: IVA | D6: Categoria | E6: Sottocategoria | F6: Voce | G6: GENNAIO | H6: FEBBRAIO | I6: MARZO | J6: APRILE | K6: MAGGIO | L6: GIUGNO | M6: LUGLIO | N6: AGOSTO | O6: SETTEMBRE | P6: OTTOBRE | Q6: NOVEMBRE | R6: DICEMBRE | T6: FY 2026
A8: 15 | B8: =E8&F8 -> OnlineOrdini | C8: SI | D8: Fatturato | E8: Online | F8: Ordini | G8: 49 | H8: =SUMIFS('DB Shopify'!$CE:$CE,'DB Shopify'!$CC:$CC,CE_TOTALE!H$2,'DB Shopify'!$CD:$CD,CE_TOTALE!H$3)+A8 -> 32 | I8: =SUMIFS('DB Shopify'!$CE:$CE,'DB Shopify'!$CC:$CC,CE_TOTALE!I$2,'DB Shopify'!$CD:$CD,CE_TOTALE!I$3) -> 71 | J8: =SUMIFS('DB Shopify'!$CE:$CE,'DB Shopify'!$CC:$CC,CE_TOTALE!J$2,'DB Shopify'!$CD:$CD,CE_TOTALE!J$3) -> 69 | K8: =SUMIFS('DB Shopify'!$CE:$CE,'DB Shopify'!$CC:$CC,CE_TOTALE!K$2,'DB Shopify'!$CD:$CD,CE_TOTALE!K$3) -> 102 | L8: =SUMIFS('DB Shopify'!$CE:$CE,'DB Shopify'!$CC:$CC,CE_TOTALE!L$2,'DB Shopify'!$CD:$CD,CE_TOTALE!L$3) -> 168 | M8: =SUMIFS('DB Shopify'!$CE:$CE,'DB Shopify'!$CC:$CC,CE_TOTALE!M$2,'DB Shopify'!$CD:$CD,CE_TOTALE!M$3) -> 5 | N8: =SUMIFS('DB Shopify'!$CE:$CE,'DB Shopify'!$CC:$CC,CE_TOTALE!N$2,'DB Shopify'!$CD:$CD,CE_TOTALE!N$3) -> 0 | O8: =SUMIFS('DB Shopify'!$CE:$CE,'DB Shopify'!$CC:$CC,CE_TOTALE!O$2,'DB Shopify'!$CD:$CD,CE_TOTALE!O$3) -> 0 | P8: =SUMIFS('DB Shopify'!$CE:$CE,'DB Shopify'!$CC:$CC,CE_TOTALE!P$2,'DB Shopify'!$CD:$CD,CE_TOTALE!P$3) -> 0 | ... R8: =SUMIFS('DB Shopify'!$CE:$CE,'DB Shopify'!$CC:$CC,CE_TOTALE!R$2,'DB Shopify'!$CD:$CD,CE_TOTALE!R$3) -> 0 | T8: =SUM(G8:R8) -> 496
B9: =E9&F9 -> OnlinePezzi/Ordine | E9: Online | F9: Pezzi/Ordine | G9: 1.2 | H9: =iferror(H10/H8,0) -> 1.0625 | I9: =iferror(I10/I8,0) -> 1 | J9: =iferror(J10/J8,0) -> 1.0724638 | K9: =iferror(K10/K8,0) -> 1.0784314 | L9: =iferror(L10/L8,0) -> 1.0952381 | M9: =iferror(M10/M8,0) -> 1 | N9: =iferror(N10/N8,0) -> 0 | O9: =iferror(O10/O8,0) -> 0 | ... R9: =iferror(R10/R8,0) -> 0 | T9: =T10/T8 -> 1.0806452
A10: 17 | B10: =E10&F10 -> OnlinePezzi | E10: Online | F10: Pezzi | G10: 58 | H10: =SUMIFS('DB Shopify'!$CF:$CF,'DB Shopify'!$CC:$CC,CE_TOTALE!H$2,'DB Shopify'!$CD:$CD,CE_TOTALE!H$3)+A10 -> 34 | I10: =SUMIFS('DB Shopify'!$CF:$CF,'DB Shopify'!$CC:$CC,CE_TOTALE!I$2,'DB Shopify'!$CD:$CD,CE_TOTALE!I$3) -> 71 | J10: =SUMIFS('DB Shopify'!$CF:$CF,'DB Shopify'!$CC:$CC,CE_TOTALE!J$2,'DB Shopify'!$CD:$CD,CE_TOTALE!J$3) -> 74 | K10: =SUMIFS('DB Shopify'!$CF:$CF,'DB Shopify'!$CC:$CC,CE_TOTALE!K$2,'DB Shopify'!$CD:$CD,CE_TOTALE!K$3) -> 110 | L10: =SUMIFS('DB Shopify'!$CF:$CF,'DB Shopify'!$CC:$CC,CE_TOTALE!L$2,'DB Shopify'!$CD:$CD,CE_TOTALE!L$3) -> 184 | M10: =SUMIFS('DB Shopify'!$CF:$CF,'DB Shopify'!$CC:$CC,CE_TOTALE!M$2,'DB Shopify'!$CD:$CD,CE_TOTALE!M$3) -> 5 | N10: =SUMIFS('DB Shopify'!$CF:$CF,'DB Shopify'!$CC:$CC,CE_TOTALE!N$2,'DB Shopify'!$CD:$CD,CE_TOTALE!N$3) -> 0 | O10: =SUMIFS('DB Shopify'!$CF:$CF,'DB Shopify'!$CC:$CC,CE_TOTALE!O$2,'DB Shopify'!$CD:$CD,CE_TOTALE!O$3) -> 0 | P10: =SUMIFS('DB Shopify'!$CF:$CF,'DB Shopify'!$CC:$CC,CE_TOTALE!P$2,'DB Shopify'!$CD:$CD,CE_TOTALE!P$3) -> 0 | ... R10: =SUMIFS('DB Shopify'!$CF:$CF,'DB Shopify'!$CC:$CC,CE_TOTALE!R$2,'DB Shopify'!$CD:$CD,CE_TOTALE!R$3) -> 0 | T10: =SUM(G10:R10) -> 536
A11: 124 | B11: =E11&F11 -> OnlineCarrello medio | C11: SI | D11: Fatturato | E11: Online | F11: Carrello medio | G11: 119 | H11: =iferror(H16/H8,0) -> 114.91875 | I11: =iferror(I16/I8,0) -> 121.48592 | J11: =iferror(J16/J8,0) -> 115.43043 | K11: =iferror(K16/K8,0) -> 119.03039 | L11: =iferror(L16/L8,0) -> 104.73119 | M11: =iferror(M16/M8,0) -> 104.16 | N11: =iferror(N16/N8,0) -> 0 | O11: =iferror(O16/O8,0) -> 0 | ... R11: =iferror(R16/R8,0) -> 0 | T11: =T12/T8 -> 122.48669
A12: 1856 | B12: =E12&F12 -> OnlineVendite | C12: SI | D12: Fatturato | E12: Online | F12: Vendite | G12: 5852 | H12: =SUMIFS('DB Shopify'!$S:$S,'DB Shopify'!$CC:$CC,CE_TOTALE!H$2,'DB Shopify'!$CD:$CD,CE_TOTALE!H$3)+A12 -> 4201 | I12: =SUMIFS('DB Shopify'!$S:$S,'DB Shopify'!$CC:$CC,CE_TOTALE!I$2,'DB Shopify'!$CD:$CD,CE_TOTALE!I$3) -> 9463 | J12: =SUMIFS('DB Shopify'!$S:$S,'DB Shopify'!$CC:$CC,CE_TOTALE!J$2,'DB Shopify'!$CD:$CD,CE_TOTALE!J$3) -> 8632 | K12: =SUMIFS('DB Shopify'!$S:$S,'DB Shopify'!$CC:$CC,CE_TOTALE!K$2,'DB Shopify'!$CD:$CD,CE_TOTALE!K$3) -> 12907 | L12: =SUMIFS('DB Shopify'!$S:$S,'DB Shopify'!$CC:$CC,CE_TOTALE!L$2,'DB Shopify'!$CD:$CD,CE_TOTALE!L$3) -> 19138.4 | M12: =SUMIFS('DB Shopify'!$S:$S,'DB Shopify'!$CC:$CC,CE_TOTALE!M$2,'DB Shopify'!$CD:$CD,CE_TOTALE!M$3) -> 560 | N12: =SUMIFS('DB Shopify'!$S:$S,'DB Shopify'!$CC:$CC,CE_TOTALE!N$2,'DB Shopify'!$CD:$CD,CE_TOTALE!N$3) -> 0 | O12: =SUMIFS('DB Shopify'!$S:$S,'DB Shopify'!$CC:$CC,CE_TOTALE!O$2,'DB Shopify'!$CD:$CD,CE_TOTALE!O$3) -> 0 | P12: =SUMIFS('DB Shopify'!$S:$S,'DB Shopify'!$CC:$CC,CE_TOTALE!P$2,'DB Shopify'!$CD:$CD,CE_TOTALE!P$3) -> 0 | ... R12: =SUMIFS('DB Shopify'!$S:$S,'DB Shopify'!$CC:$CC,CE_TOTALE!R$2,'DB Shopify'!$CD:$CD,CE_TOTALE!R$3) -> 0 | T12: =SUM(G12:R12) -> 60753.4
A13: -419 | B13: =E13&F13 -> OnlineSconti | C13: SI | D13: Fatturato | E13: Online | F13: Sconti | G13: -1012 | H13: =-SUMIFS('DB Shopify'!$CK:$CK,'DB Shopify'!$CC:$CC,CE_TOTALE!H$2,'DB Shopify'!$CD:$CD,CE_TOTALE!H$3)+A13 -> -544 | I13: =-SUMIFS('DB Shopify'!$CK:$CK,'DB Shopify'!$CC:$CC,CE_TOTALE!I$2,'DB Shopify'!$CD:$CD,CE_TOTALE!I$3) -> -547 | J13: =-SUMIFS('DB Shopify'!$CK:$CK,'DB Shopify'!$CC:$CC,CE_TOTALE!J$2,'DB Shopify'!$CD:$CD,CE_TOTALE!J$3) -> -457.5 | K13: =-SUMIFS('DB Shopify'!$CK:$CK,'DB Shopify'!$CC:$CC,CE_TOTALE!K$2,'DB Shopify'!$CD:$CD,CE_TOTALE!K$3) -> -790 | L13: =-SUMIFS('DB Shopify'!$CK:$CK,'DB Shopify'!$CC:$CC,CE_TOTALE!L$2,'DB Shopify'!$CD:$CD,CE_TOTALE!L$3) -> -1294.14 | M13: =-SUMIFS('DB Shopify'!$CK:$CK,'DB Shopify'!$CC:$CC,CE_TOTALE!M$2,'DB Shopify'!$CD:$CD,CE_TOTALE!M$3) -> -32 | N13: =-SUMIFS('DB Shopify'!$CK:$CK,'DB Shopify'!$CC:$CC,CE_TOTALE!N$2,'DB Shopify'!$CD:$CD,CE_TOTALE!N$3) -> 0 | O13: =-SUMIFS('DB Shopify'!$CK:$CK,'DB Shopify'!$CC:$CC,CE_TOTALE!O$2,'DB Shopify'!$CD:$CD,CE_TOTALE!O$3) -> 0 | P13: =-SUMIFS('DB Shopify'!$CK:$CK,'DB Shopify'!$CC:$CC,CE_TOTALE!P$2,'DB Shopify'!$CD:$CD,CE_TOTALE!P$3) -> 0 | ... R13: =-SUMIFS('DB Shopify'!$CK:$CK,'DB Shopify'!$CC:$CC,CE_TOTALE!R$2,'DB Shopify'!$CD:$CD,CE_TOTALE!R$3) -> 0 | T13: =SUM(G13:R13) -> -4676.64
A14: -35 | B14: =E14&F14 -> OnlineFree Shipping | C14: SI | D14: Fatturato | E14: Online | F14: Free Shipping | G14: -160 | H14: =SUMIFS('DB Shopify'!$CG:$CG,'DB Shopify'!$CC:$CC,CE_TOTALE!H$2,'DB Shopify'!$CD:$CD,CE_TOTALE!H$3)+A14 -> -90 | I14: =SUMIFS('DB Shopify'!$CG:$CG,'DB Shopify'!$CC:$CC,CE_TOTALE!I$2,'DB Shopify'!$CD:$CD,CE_TOTALE!I$3) -> -325 | J14: =SUMIFS('DB Shopify'!$CG:$CG,'DB Shopify'!$CC:$CC,CE_TOTALE!J$2,'DB Shopify'!$CD:$CD,CE_TOTALE!J$3) -> -280 | K14: =SUMIFS('DB Shopify'!$CG:$CG,'DB Shopify'!$CC:$CC,CE_TOTALE!K$2,'DB Shopify'!$CD:$CD,CE_TOTALE!K$3) -> -355 | L14: =SUMIFS('DB Shopify'!$CG:$CG,'DB Shopify'!$CC:$CC,CE_TOTALE!L$2,'DB Shopify'!$CD:$CD,CE_TOTALE!L$3) -> -560 | M14: =SUMIFS('DB Shopify'!$CG:$CG,'DB Shopify'!$CC:$CC,CE_TOTALE!M$2,'DB Shopify'!$CD:$CD,CE_TOTALE!M$3) -> -15 | N14: =SUMIFS('DB Shopify'!$CG:$CG,'DB Shopify'!$CC:$CC,CE_TOTALE!N$2,'DB Shopify'!$CD:$CD,CE_TOTALE!N$3) -> 0 | O14: =SUMIFS('DB Shopify'!$CG:$CG,'DB Shopify'!$CC:$CC,CE_TOTALE!O$2,'DB Shopify'!$CD:$CD,CE_TOTALE!O$3) -> 0 | P14: =SUMIFS('DB Shopify'!$CG:$CG,'DB Shopify'!$CC:$CC,CE_TOTALE!P$2,'DB Shopify'!$CD:$CD,CE_TOTALE!P$3) -> 0 | ... R14: =SUMIFS('DB Shopify'!$CG:$CG,'DB Shopify'!$CC:$CC,CE_TOTALE!R$2,'DB Shopify'!$CD:$CD,CE_TOTALE!R$3) -> 0 | T14: =SUM(G14:R14) -> -1785
A15: 69 | B15: =E15&F15 -> OnlineSpedizioni | C15: SI | D15: Fatturato | E15: Online | F15: Spedizioni | G15: 222 | H15: =SUMIFS('DB Shopify'!$J:$J,'DB Shopify'!$CC:$CC,CE_TOTALE!H$2,'DB Shopify'!$CD:$CD,CE_TOTALE!H$3)+A15 -> 110.4 | I15: =SUMIFS('DB Shopify'!$J:$J,'DB Shopify'!$CC:$CC,CE_TOTALE!I$2,'DB Shopify'!$CD:$CD,CE_TOTALE!I$3) -> 34.5 | J15: =SUMIFS('DB Shopify'!$J:$J,'DB Shopify'!$CC:$CC,CE_TOTALE!J$2,'DB Shopify'!$CD:$CD,CE_TOTALE!J$3) -> 70.2 | K15: =SUMIFS('DB Shopify'!$J:$J,'DB Shopify'!$CC:$CC,CE_TOTALE!K$2,'DB Shopify'!$CD:$CD,CE_TOTALE!K$3) -> 379.1 | L15: =SUMIFS('DB Shopify'!$J:$J,'DB Shopify'!$CC:$CC,CE_TOTALE!L$2,'DB Shopify'!$CD:$CD,CE_TOTALE!L$3) -> 310.58 | M15: =SUMIFS('DB Shopify'!$J:$J,'DB Shopify'!$CC:$CC,CE_TOTALE!M$2,'DB Shopify'!$CD:$CD,CE_TOTALE!M$3) -> 7.8 | N15: =SUMIFS('DB Shopify'!$J:$J,'DB Shopify'!$CC:$CC,CE_TOTALE!N$2,'DB Shopify'!$CD:$CD,CE_TOTALE!N$3) -> 0 | O15: =SUMIFS('DB Shopify'!$J:$J,'DB Shopify'!$CC:$CC,CE_TOTALE!O$2,'DB Shopify'!$CD:$CD,CE_TOTALE!O$3) -> 0 | P15: =SUMIFS('DB Shopify'!$J:$J,'DB Shopify'!$CC:$CC,CE_TOTALE!P$2,'DB Shopify'!$CD:$CD,CE_TOTALE!P$3) -> 0 | ... R15: =SUMIFS('DB Shopify'!$J:$J,'DB Shopify'!$CC:$CC,CE_TOTALE!R$2,'DB Shopify'!$CD:$CD,CE_TOTALE!R$3) -> 0 | T15: =SUM(G15:R15) -> 1134.58
A16: 1471 | B16: =E16&F16 -> OnlineFatturato Lordo | C16: SI | D16: Fatturato | E16: Online | F16: Fatturato Lordo | G16: 4902 | H16: =H15+H13+H12+H14 -> 3677.4 | I16: =I15+I13+I12+I14 -> 8625.5 | J16: =J15+J13+J12+J14 -> 7964.7 | K16: =K15+K13+K12+K14 -> 12141.1 | L16: =L15+L13+L12+L14 -> 17594.84 | M16: =M15+M13+M12+M14 -> 520.8 | N16: =N15+N13+N12+N14 -> 0 | O16: =O15+O13+O12+O14 -> 0 | ... R16: =R15+R13+R12+R14 -> 0 | T16: =SUM(G16:R16) -> 55426.34
A17: 1206 | B17: =E17&F17 -> OnlineFatturato Netto | C17: NO | D17: Fatturato | E17: Online | F17: Fatturato Netto | G17: 4018 | H17: =H16/1.22 -> 3014.2623 | I17: =I16/1.22 -> 7070.082 | J17: =J16/1.22 -> 6528.4426 | K17: =K16/1.22 -> 9951.7213 | L17: =L16/1.22 -> 14422 | M17: =M16/1.22 -> 426.88525 | N17: =N16/1.22 -> 0 | O17: =O16/1.22 -> 0 | ... R17: =R16/1.22 -> 0 | T17: =SUM(G17:R17) -> 45431.393
B18: =E18&F18
B19: =E19&F19 -> Offline Pezzi | C19: SI | D19: Fatturato | E19: Offline | F19: Pezzi | G19: 6 | H19: =SUMIFS(DB_QROMO!$I:$I, DB_QROMO!$A:$A, H$2, DB_QROMO!$B:$B, H$3) + SUMIFS(GIFT_OFFLINE!$G:$G, GIFT_OFFLINE!$A:$A, H$2, GIFT_OFFLINE!$B:$B, H$3)+A19 -> 9 | I19: =SUMIFS(DB_QROMO!$I:$I, DB_QROMO!$A:$A, I$2, DB_QROMO!$B:$B, I$3) + SUMIFS(GIFT_OFFLINE!$G:$G, GIFT_OFFLINE!$A:$A, I$2, GIFT_OFFLINE!$B:$B, I$3) -> 35 | J19: =SUMIFS(DB_QROMO!$I:$I, DB_QROMO!$A:$A, J$2, DB_QROMO!$B:$B, J$3) + SUMIFS(GIFT_OFFLINE!$G:$G, GIFT_OFFLINE!$A:$A, J$2, GIFT_OFFLINE!$B:$B, J$3) -> 51 | K19: =SUMIFS(DB_QROMO!$I:$I, DB_QROMO!$A:$A, K$2, DB_QROMO!$B:$B, K$3) + SUMIFS(GIFT_OFFLINE!$G:$G, GIFT_OFFLINE!$A:$A, K$2, GIFT_OFFLINE!$B:$B, K$3) -> 30 | L19: =SUMIFS(DB_QROMO!$I:$I, DB_QROMO!$A:$A, L$2, DB_QROMO!$B:$B, L$3) + SUMIFS(GIFT_OFFLINE!$G:$G, GIFT_OFFLINE!$A:$A, L$2, GIFT_OFFLINE!$B:$B, L$3) -> 134 | M19: =SUMIFS(DB_QROMO!$I:$I, DB_QROMO!$A:$A, M$2, DB_QROMO!$B:$B, M$3) + SUMIFS(GIFT_OFFLINE!$G:$G, GIFT_OFFLINE!$A:$A, M$2, GIFT_OFFLINE!$B:$B, M$3) -> 10 | N19: =SUMIFS(DB_QROMO!$I:$I, DB_QROMO!$A:$A, N$2, DB_QROMO!$B:$B, N$3) + SUMIFS(GIFT_OFFLINE!$G:$G, GIFT_OFFLINE!$A:$A, N$2, GIFT_OFFLINE!$B:$B, N$3) -> 0 | O19: =SUMIFS(DB_QROMO!$I:$I, DB_QROMO!$A:$A, O$2, DB_QROMO!$B:$B, O$3) + SUMIFS(GIFT_OFFLINE!$G:$G, GIFT_OFFLINE!$A:$A, O$2, GIFT_OFFLINE!$B:$B, O$3) -> 0 | P19: =SUMIFS(DB_QROMO!$I:$I, DB_QROMO!$A:$A, P$2, DB_QROMO!$B:$B, P$3) + SUMIFS(GIFT_OFFLINE!$G:$G, GIFT_OFFLINE!$A:$A, P$2, GIFT_OFFLINE!$B:$B, P$3) -> 0 | ... R19: =SUMIFS(DB_QROMO!$I:$I, DB_QROMO!$A:$A, R$2, DB_QROMO!$B:$B, R$3) + SUMIFS(GIFT_OFFLINE!$G:$G, GIFT_OFFLINE!$A:$A, R$2, GIFT_OFFLINE!$B:$B, R$3) -> 0 | T19: =SUM(G19:R19) -> 275
B20: =E20&F20 -> Offline Fatturato Lordo | C20: SI | D20: Fatturato | E20: Offline | F20: Fatturato Lordo | G20: 524 | H20: =SUMIFS(DB_QROMO!$K:$K, DB_QROMO!$A:$A, H$2, DB_QROMO!$B:$B, H$3) + SUMIFS(GIFT_OFFLINE!$I:$I, GIFT_OFFLINE!$A:$A, H$2, GIFT_OFFLINE!$B:$B, H$3)+A20 -> 997 | I20: =SUMIFS(DB_QROMO!$K:$K, DB_QROMO!$A:$A, I$2, DB_QROMO!$B:$B, I$3) + SUMIFS(GIFT_OFFLINE!$I:$I, GIFT_OFFLINE!$A:$A, I$2, GIFT_OFFLINE!$B:$B, I$3) -> 2407 | J20: =SUMIFS(DB_QROMO!$K:$K, DB_QROMO!$A:$A, J$2, DB_QROMO!$B:$B, J$3) + SUMIFS(GIFT_OFFLINE!$I:$I, GIFT_OFFLINE!$A:$A, J$2, GIFT_OFFLINE!$B:$B, J$3) -> 4383 | K20: =SUMIFS(DB_QROMO!$K:$K, DB_QROMO!$A:$A, K$2, DB_QROMO!$B:$B, K$3) + SUMIFS(GIFT_OFFLINE!$I:$I, GIFT_OFFLINE!$A:$A, K$2, GIFT_OFFLINE!$B:$B, K$3) -> 2848.5 | L20: =SUMIFS(DB_QROMO!$K:$K, DB_QROMO!$A:$A, L$2, DB_QROMO!$B:$B, L$3) + SUMIFS(GIFT_OFFLINE!$I:$I, GIFT_OFFLINE!$A:$A, L$2, GIFT_OFFLINE!$B:$B, L$3) -> 7306.5 | M20: =SUMIFS(DB_QROMO!$K:$K, DB_QROMO!$A:$A, M$2, DB_QROMO!$B:$B, M$3) + SUMIFS(GIFT_OFFLINE!$I:$I, GIFT_OFFLINE!$A:$A, M$2, GIFT_OFFLINE!$B:$B, M$3) -> 1047 | N20: =SUMIFS(DB_QROMO!$K:$K, DB_QROMO!$A:$A, N$2, DB_QROMO!$B:$B, N$3) + SUMIFS(GIFT_OFFLINE!$I:$I, GIFT_OFFLINE!$A:$A, N$2, GIFT_OFFLINE!$B:$B, N$3) -> 0 | O20: =SUMIFS(DB_QROMO!$K:$K, DB_QROMO!$A:$A, O$2, DB_QROMO!$B:$B, O$3) + SUMIFS(GIFT_OFFLINE!$I:$I, GIFT_OFFLINE!$A:$A, O$2, GIFT_OFFLINE!$B:$B, O$3) -> 0 | P20: =SUMIFS(DB_QROMO!$K:$K, DB_QROMO!$A:$A, P$2, DB_QROMO!$B:$B, P$3) + SUMIFS(GIFT_OFFLINE!$I:$I, GIFT_OFFLINE!$A:$A, P$2, GIFT_OFFLINE!$B:$B, P$3) -> 0 | ... R20: =SUMIFS(DB_QROMO!$K:$K, DB_QROMO!$A:$A, R$2, DB_QROMO!$B:$B, R$3) + SUMIFS(GIFT_OFFLINE!$I:$I, GIFT_OFFLINE!$A:$A, R$2, GIFT_OFFLINE!$B:$B, R$3) -> 0 | T20: =SUM(G20:R20) -> 19513
B21: =E21&F21 -> Offline Fatturato Netto | C21: NO | D21: Fatturato | E21: Offline | F21: Fatturato Netto | G21: 430 | H21: =H20/1.22 -> 817.21311 | I21: =I20/1.22 -> 1972.9508 | J21: =J20/1.22 -> 3592.623 | K21: =K20/1.22 -> 2334.8361 | L21: =L20/1.22 -> 5988.9344 | M21: =M20/1.22 -> 858.19672 | N21: =N20/1.22 -> 0 | O21: =O20/1.22 -> 0 | ... R21: =R20/1.22 -> 0 | T21: =SUM(G21:R21) -> 15994.754
B22: =E22&F22 | T22: =T21/T29 -> 0.25962781
D23: Fatturato | E23: B2B | F23: Pezzi | G23: =SUMIFS(DB_B2B!$E:$E,DB_B2B!$B:$B,G$2,DB_B2B!$C:$C,G$3,DB_B2B!$G:$G,"venduto",DB_B2B!$Q:$Q,"<>annullato") -> 0 | H23: =SUMIFS(DB_B2B!$E:$E,DB_B2B!$B:$B,H$2,DB_B2B!$C:$C,H$3,DB_B2B!$G:$G,"venduto",DB_B2B!$Q:$Q,"<>annullato") -> 0 | I23: =SUMIFS(DB_B2B!$E:$E,DB_B2B!$B:$B,I$2,DB_B2B!$C:$C,I$3,DB_B2B!$G:$G,"venduto",DB_B2B!$Q:$Q,"<>annullato") -> 0 | J23: =SUMIFS(DB_B2B!$E:$E,DB_B2B!$B:$B,J$2,DB_B2B!$C:$C,J$3,DB_B2B!$G:$G,"venduto",DB_B2B!$Q:$Q,"<>annullato") -> 0 | K23: =SUMIFS(DB_B2B!$E:$E,DB_B2B!$B:$B,K$2,DB_B2B!$C:$C,K$3,DB_B2B!$G:$G,"venduto",DB_B2B!$Q:$Q,"<>annullato") -> 0 | L23: =SUMIFS(DB_B2B!$E:$E,DB_B2B!$B:$B,L$2,DB_B2B!$C:$C,L$3,DB_B2B!$G:$G,"venduto",DB_B2B!$Q:$Q,"<>annullato") -> 5 | M23: =SUMIFS(DB_B2B!$E:$E,DB_B2B!$B:$B,M$2,DB_B2B!$C:$C,M$3,DB_B2B!$G:$G,"venduto",DB_B2B!$Q:$Q,"<>annullato") -> 0 | N23: =SUMIFS(DB_B2B!$E:$E,DB_B2B!$B:$B,N$2,DB_B2B!$C:$C,N$3,DB_B2B!$G:$G,"venduto",DB_B2B!$Q:$Q,"<>annullato") -> 0 | ... R23: =SUMIFS(DB_B2B!$E:$E,DB_B2B!$B:$B,R$2,DB_B2B!$C:$C,R$3,DB_B2B!$G:$G,"venduto",DB_B2B!$Q:$Q,"<>annullato") -> 0
D24: Fatturato | E24: B2B | F24: Fatturato Lordo | G24: =SUMIFS(DB_B2B!$M:$M,DB_B2B!$B:$B,G$2,DB_B2B!$C:$C,G$3,DB_B2B!$G:$G,"venduto",DB_B2B!$Q:$Q,"<>annullato") -> 0 | H24: =SUMIFS(DB_B2B!$M:$M,DB_B2B!$B:$B,H$2,DB_B2B!$C:$C,H$3,DB_B2B!$G:$G,"venduto",DB_B2B!$Q:$Q,"<>annullato") -> 0 | I24: =SUMIFS(DB_B2B!$M:$M,DB_B2B!$B:$B,I$2,DB_B2B!$C:$C,I$3,DB_B2B!$G:$G,"venduto",DB_B2B!$Q:$Q,"<>annullato") -> 0 | J24: =SUMIFS(DB_B2B!$M:$M,DB_B2B!$B:$B,J$2,DB_B2B!$C:$C,J$3,DB_B2B!$G:$G,"venduto",DB_B2B!$Q:$Q,"<>annullato") -> 0 | K24: =SUMIFS(DB_B2B!$M:$M,DB_B2B!$B:$B,K$2,DB_B2B!$C:$C,K$3,DB_B2B!$G:$G,"venduto",DB_B2B!$Q:$Q,"<>annullato") -> 0 | L24: =SUMIFS(DB_B2B!$M:$M,DB_B2B!$B:$B,L$2,DB_B2B!$C:$C,L$3,DB_B2B!$G:$G,"venduto",DB_B2B!$Q:$Q,"<>annullato") -> 220 | M24: =SUMIFS(DB_B2B!$M:$M,DB_B2B!$B:$B,M$2,DB_B2B!$C:$C,M$3,DB_B2B!$G:$G,"venduto",DB_B2B!$Q:$Q,"<>annullato") -> 0 | N24: =SUMIFS(DB_B2B!$M:$M,DB_B2B!$B:$B,N$2,DB_B2B!$C:$C,N$3,DB_B2B!$G:$G,"venduto",DB_B2B!$Q:$Q,"<>annullato") -> 0 | ... R24: =SUMIFS(DB_B2B!$M:$M,DB_B2B!$B:$B,R$2,DB_B2B!$C:$C,R$3,DB_B2B!$G:$G,"venduto",DB_B2B!$Q:$Q,"<>annullato") -> 0
D25: Fatturato | E25: B2B | F25: Fatturato Netto | G25: =G24/1.22 -> 0 | H25: =H24/1.22 -> 0 | I25: =I24/1.22 -> 0 | J25: =J24/1.22 -> 0 | K25: =K24/1.22 -> 0 | L25: =L24/1.22 -> 180.32787 | M25: =M24/1.22 -> 0 | N25: =N24/1.22 -> 0 | ... R25: =R24/1.22 -> 0
A27: 19 | B27: =E27&F27 -> OmnichannelPezzi | E27: Omnichannel | F27: Pezzi | G27: 64 | H27: =H19+H10+H23 -> 43 | I27: =I19+I10+I23 -> 106 | J27: =J19+J10+J23 -> 125 | K27: =K19+K10+K23 -> 140 | L27: =L19+L10+L23 -> 323 | M27: =M19+M10+M23 -> 15 | N27: =N19+N10+N23 -> 0 | O27: =O19+O10+O23 -> 0 | ... R27: =R19+R10+R23 -> 0 | T27: =T19+T10 -> 811
A28: 1595 | B28: =E28&F28 -> OmnichannelFatturato Lordo | E28: Omnichannel | F28: Fatturato Lordo | G28: 5426 | H28: =H20+H16+H24 -> 4674.4 | I28: =I20+I16+I24 -> 11032.5 | J28: =J20+J16+J24 -> 12347.7 | K28: =K20+K16+K24 -> 14989.6 | L28: =L20+L16+L24 -> 25121.34 | M28: =M20+M16+M24 -> 1567.8 | N28: =N20+N16+N24 -> 0 | O28: =O20+O16+O24 -> 0 | ... R28: =R20+R16+R24 -> 0 | T28: =T20+T16 -> 74939.34
A29: 1307 | B29: =E29&F29 -> OmnichannelFatturato Netto | E29: Omnichannel | F29: Fatturato Netto | G29: 4448 | H29: =H28/1.22 -> 3831.4754 | I29: =I28/1.22 -> 9043.0328 | J29: =J28/1.22 -> 10121.066 | K29: =K28/1.22 -> 12286.557 | L29: =L28/1.22 -> 20591.262 | M29: =M28/1.22 -> 1285.082 | N29: =N28/1.22 -> 0 | O29: =O28/1.22 -> 0 | ... R29: =R28/1.22 -> 0 | T29: =SUM(G29:R29) -> 61606.475
B30: =E30&F30
A31: -611 | B31: =E31&F31 -> VariabiliCOGS (Cost of goods sold) | C31: NO | D31: Costi | E31: Variabili | F31: COGS (Cost of goods sold) | G31: -1802 | H31: =-SUMIFS(DB_QROMO!$L:$L, DB_QROMO!$A:$A, H$2, DB_QROMO!$B:$B, H$3) - SUMIFS(GIFT_OFFLINE!$J:$J, GIFT_OFFLINE!$A:$A, H$2, GIFT_OFFLINE!$B:$B, H$3)+A31 - SUMIFS('DB Shopify'!$CH:$CH, 'DB Shopify'!$CC:$CC, H$2, 'DB Shopify'!$CD:$CD, H$3)-SUMIFS(DB_B2B!$N:$N,DB_B2B!$B:$B,H$2,DB_B2B!$C:$C,H$3,DB_B2B!$G:$G,"venduto",DB_B2B!$Q:$Q,"<>annullato") -> -1365.41 | I31: =-SUMIFS(DB_QROMO!$L:$L, DB_QROMO!$A:$A, I$2, DB_QROMO!$B:$B, I$3) - SUMIFS(GIFT_OFFLINE!$J:$J, GIFT_OFFLINE!$A:$A, I$2, GIFT_OFFLINE!$B:$B, I$3) - SUMIFS('DB Shopify'!$CH:$CH, 'DB Shopify'!$CC:$CC, I$2, 'DB Shopify'!$CD:$CD, I$3)-SUMIFS(DB_B2B!$N:$N,DB_B2B!$B:$B,I$2,DB_B2B!$C:$C,I$3,DB_B2B!$G:$G,"venduto",DB_B2B!$Q:$Q,"<>annullato") -> -2832.42 | J31: =-SUMIFS(DB_QROMO!$L:$L, DB_QROMO!$A:$A, J$2, DB_QROMO!$B:$B, J$3) - SUMIFS(GIFT_OFFLINE!$J:$J, GIFT_OFFLINE!$A:$A, J$2, GIFT_OFFLINE!$B:$B, J$3) - SUMIFS('DB Shopify'!$CH:$CH, 'DB Shopify'!$CC:$CC, J$2, 'DB Shopify'!$CD:$CD, J$3)-SUMIFS(DB_B2B!$N:$N,DB_B2B!$B:$B,J$2,DB_B2B!$C:$C,J$3,DB_B2B!$G:$G,"venduto",DB_B2B!$Q:$Q,"<>annullato") -> -3023.65 | K31: =-SUMIFS(DB_QROMO!$L:$L, DB_QROMO!$A:$A, K$2, DB_QROMO!$B:$B, K$3) - SUMIFS(GIFT_OFFLINE!$J:$J, GIFT_OFFLINE!$A:$A, K$2, GIFT_OFFLINE!$B:$B, K$3) - SUMIFS('DB Shopify'!$CH:$CH, 'DB Shopify'!$CC:$CC, K$2, 'DB Shopify'!$CD:$CD, K$3)-SUMIFS(DB_B2B!$N:$N,DB_B2B!$B:$B,K$2,DB_B2B!$C:$C,K$3,DB_B2B!$G:$G,"venduto",DB_B2B!$Q:$Q,"<>annullato") -> -3282.36 | L31: =-SUMIFS(DB_QROMO!$L:$L, DB_QROMO!$A:$A, L$2, DB_QROMO!$B:$B, L$3) - SUMIFS(GIFT_OFFLINE!$J:$J, GIFT_OFFLINE!$A:$A, L$2, GIFT_OFFLINE!$B:$B, L$3) - SUMIFS('DB Shopify'!$CH:$CH, 'DB Shopify'!$CC:$CC, L$2, 'DB Shopify'!$CD:$CD, L$3)-SUMIFS(DB_B2B!$N:$N,DB_B2B!$B:$B,L$2,DB_B2B!$C:$C,L$3,DB_B2B!$G:$G,"venduto",DB_B2B!$Q:$Q,"<>annullato") -> -6701.86 | M31: =-SUMIFS(DB_QROMO!$L:$L, DB_QROMO!$A:$A, M$2, DB_QROMO!$B:$B, M$3) - SUMIFS(GIFT_OFFLINE!$J:$J, GIFT_OFFLINE!$A:$A, M$2, GIFT_OFFLINE!$B:$B, M$3) - SUMIFS('DB Shopify'!$CH:$CH, 'DB Shopify'!$CC:$CC, M$2, 'DB Shopify'!$CD:$CD, M$3)-SUMIFS(DB_B2B!$N:$N,DB_B2B!$B:$B,M$2,DB_B2B!$C:$C,M$3,DB_B2B!$G:$G,"venduto",DB_B2B!$Q:$Q,"<>annullato") -> -131 | N31: =-SUMIFS(DB_QROMO!$L:$L, DB_QROMO!$A:$A, N$2, DB_QROMO!$B:$B, N$3) - SUMIFS(GIFT_OFFLINE!$J:$J, GIFT_OFFLINE!$A:$A, N$2, GIFT_OFFLINE!$B:$B, N$3) - SUMIFS('DB Shopify'!$CH:$CH, 'DB Shopify'!$CC:$CC, N$2, 'DB Shopify'!$CD:$CD, N$3)-SUMIFS(DB_B2B!$N:$N,DB_B2B!$B:$B,N$2,DB_B2B!$C:$C,N$3,DB_B2B!$G:$G,"venduto",DB_B2B!$Q:$Q,"<>annullato") -> 0 | O31: =-SUMIFS(DB_QROMO!$L:$L, DB_QROMO!$A:$A, O$2, DB_QROMO!$B:$B, O$3) - SUMIFS(GIFT_OFFLINE!$J:$J, GIFT_OFFLINE!$A:$A, O$2, GIFT_OFFLINE!$B:$B, O$3) - SUMIFS('DB Shopify'!$CH:$CH, 'DB Shopify'!$CC:$CC, O$2, 'DB Shopify'!$CD:$CD, O$3)-SUMIFS(DB_B2B!$N:$N,DB_B2B!$B:$B,O$2,DB_B2B!$C:$C,O$3,DB_B2B!$G:$G,"venduto",DB_B2B!$Q:$Q,"<>annullato") -> 0 | P31: =-SUMIFS(DB_QROMO!$L:$L, DB_QROMO!$A:$A, P$2, DB_QROMO!$B:$B, P$3) - SUMIFS(GIFT_OFFLINE!$J:$J, GIFT_OFFLINE!$A:$A, P$2, GIFT_OFFLINE!$B:$B, P$3) - SUMIFS('DB Shopify'!$CH:$CH, 'DB Shopify'!$CC:$CC, P$2, 'DB Shopify'!$CD:$CD, P$3)-SUMIFS(DB_B2B!$N:$N,DB_B2B!$B:$B,P$2,DB_B2B!$C:$C,P$3,DB_B2B!$G:$G,"venduto",DB_B2B!$Q:$Q,"<>annullato") -> 0 | ... R31: =-SUMIFS(DB_QROMO!$L:$L, DB_QROMO!$A:$A, R$2, DB_QROMO!$B:$B, R$3) - SUMIFS(GIFT_OFFLINE!$J:$J, GIFT_OFFLINE!$A:$A, R$2, GIFT_OFFLINE!$B:$B, R$3) - SUMIFS('DB Shopify'!$CH:$CH, 'DB Shopify'!$CC:$CC, R$2, 'DB Shopify'!$CD:$CD, R$3)-SUMIFS(DB_B2B!$N:$N,DB_B2B!$B:$B,R$2,DB_B2B!$C:$C,R$3,DB_B2B!$G:$G,"venduto",DB_B2B!$Q:$Q,"<>annullato") -> 0 | T31: =SUM(G31:R31) -> -19138.7
A32: -75.3 | B32: =E32&F32 -> VariabiliPackaging | C32: NO | D32: Costi | E32: Variabili | F32: Packaging | G32: -250.6 | H32: =SUM(H33:H38)+A32 -> -266.83 | I32: =SUM(I33:I38) -> -464.26 | J32: =SUM(J33:J38) -> -532.75 | K32: =SUM(K33:K38) -> -621.4 | L32: =SUM(L33:L38) -> -1347.78 | M32: =SUM(M33:M38) -> -60.65 | N32: =SUM(N33:N38) -> 0 | O32: =SUM(O33:O38) -> 0 | P32: =SUM(P33:P38) -> 0 | ... R32: =SUM(R33:R38) -> 0 | T32: =SUM(G32:R32) -> -3544.27
A33: -4 | B33: =E33&F33 -> 0.5Cartolina | E33: 0.5 | F33: Cartolina | G33: -13 | H33: =-$E33*(H$19+H$10) -> -21.5 | I33: =-$E33*(I$19+I$10) -> -53 | J33: =-$E33*(J$19+J$10) -> -62.5 | K33: =-$E33*(K$19+K$10) -> -70 | L33: =-$E33*(L$19+L$10) -> -159 | M33: =-$E33*(M$19+M$10) -> -7.5 | N33: =-$E33*(N$19+N$10) -> 0 | O33: =-$E33*(O$19+O$10) -> 0 | ... R33: =-$E33*(R$19+R$10) -> 0 | T33: =SUM(G33:R33) -> -386.5
A34: -6 | B34: =E34&F34 -> 0.5Adesivi | E34: 0.5 | F34: Adesivi | G34: -19 | H34: =-$E34*(H$19+H$10) -> -21.5 | I34: =-$E34*(I$19+I$10) -> -53 | J34: =-$E34*(J$19+J$10) -> -62.5 | K34: =-$E34*(K$19+K$10) -> -70 | L34: =-$E34*(L$19+L$10) -> -159 | M34: =-$E34*(M$19+M$10) -> -7.5 | N34: =-$E34*(N$19+N$10) -> 0 | O34: =-$E34*(O$19+O$10) -> 0 | ... R34: =-$E34*(R$19+R$10) -> 0 | T34: =SUM(G34:R34) -> -392.5
A35: -30 | B35: =E35&F35 -> 1E-Commerce Box | E35: 1 | F35: E-Commerce Box | G35: -97 | H35: =-$E35*H$8 -> -32 | I35: =-$E35*I$8 -> -71 | J35: =-$E35*J$8 -> -69 | K35: =-$E35*K$8 -> -102 | L35: =-$E35*L$8 -> -168 | M35: =-$E35*M$8 -> -5 | N35: =-$E35*N$8 -> 0 | O35: =-$E35*O$8 -> 0 | ... R35: =-$E35*R$8 -> 0 | T35: =SUM(G35:R35) -> -544
A36: -10 | B36: =E36&F36 -> 0.1Carta Velina | E36: 0.1 | F36: Carta Velina | G36: -32 | H36: =-$E36*(H$19+H$10) -> -4.3 | I36: =-$E36*(I$19+I$10) -> -10.6 | J36: =-$E36*(J$19+J$10) -> -12.5 | K36: =-$E36*(K$19+K$10) -> -14 | L36: =-$E36*(L$19+L$10) -> -31.8 | M36: =-$E36*(M$19+M$10) -> -1.5 | N36: =-$E36*(N$19+N$10) -> 0 | O36: =-$E36*(O$19+O$10) -> 0 | ... R36: =-$E36*(R$19+R$10) -> 0 | T36: =SUM(G36:R36) -> -106.7
A37: -24 | B37: =E37&F37 -> 1.85Sachetto di Cotone | E37: 1.85 | F37: Sachetto di Cotone | G37: -80 | H37: =-$E37*(H$19+H$10) -> -79.55 | I37: =-$E37*(I$19+I$10) -> -196.1 | J37: =-$E37*(J$19+J$10) -> -231.25 | K37: =-$E37*(K$19+K$10) -> -259 | L37: =-$E37*(L$19+L$10) -> -588.3 | M37: =-$E37*(M$19+M$10) -> -27.75 | N37: =-$E37*(N$19+N$10) -> 0 | O37: =-$E37*(O$19+O$10) -> 0 | ... R37: =-$E37*(R$19+R$10) -> 0 | T37: =SUM(G37:R37) -> -1461.95
A38: -3 | B38: =E38&F38 -> 0.76Nastro Sigillante | E38: 0.76 | F38: Nastro Sigillante | G38: -10 | H38: =-$E38*(H$19+H$10) -> -32.68 | I38: =-$E38*(I$19+I$10) -> -80.56 | J38: =-$E38*(J$19+J$10) -> -95 | K38: =-$E38*(K$19+K$10) -> -106.4 | L38: =-$E38*(L$19+L$10) -> -241.68 | M38: =-$E38*(M$19+M$10) -> -11.4 | N38: =-$E38*(N$19+N$10) -> 0 | O38: =-$E38*(O$19+O$10) -> 0 | ... R38: =-$E38*(R$19+R$10) -> 0 | T38: =SUM(G38:R38) -> -577.72
A39: -71 | B39: =E39&F39 -> VariabiliCommissioni sui pagamenti | C39: NO | D39: Costi | E39: Variabili | F39: Commissioni sui pagamenti | G39: -212 | H39: =SUMIFS('DB Shopify'!$CI:$CI,'DB Shopify'!$CC:$CC,CE_TOTALE!H$2,'DB Shopify'!$CD:$CD,CE_TOTALE!H$3)+A39 -> -128.66523 | I39: =SUMIFS('DB Shopify'!$CI:$CI,'DB Shopify'!$CC:$CC,CE_TOTALE!I$2,'DB Shopify'!$CD:$CD,CE_TOTALE!I$3) -> -237.07651 | J39: =SUMIFS('DB Shopify'!$CI:$CI,'DB Shopify'!$CC:$CC,CE_TOTALE!J$2,'DB Shopify'!$CD:$CD,CE_TOTALE!J$3) -> -264.11422 | K39: =SUMIFS('DB Shopify'!$CI:$CI,'DB Shopify'!$CC:$CC,CE_TOTALE!K$2,'DB Shopify'!$CD:$CD,CE_TOTALE!K$3) -> -397.02702 | L39: =SUMIFS('DB Shopify'!$CI:$CI,'DB Shopify'!$CC:$CC,CE_TOTALE!L$2,'DB Shopify'!$CD:$CD,CE_TOTALE!L$3) -> -577.14261 | M39: =SUMIFS('DB Shopify'!$CI:$CI,'DB Shopify'!$CC:$CC,CE_TOTALE!M$2,'DB Shopify'!$CD:$CD,CE_TOTALE!M$3) -> -13.4382 | N39: =SUMIFS('DB Shopify'!$CI:$CI,'DB Shopify'!$CC:$CC,CE_TOTALE!N$2,'DB Shopify'!$CD:$CD,CE_TOTALE!N$3) -> 0 | O39: =SUMIFS('DB Shopify'!$CI:$CI,'DB Shopify'!$CC:$CC,CE_TOTALE!O$2,'DB Shopify'!$CD:$CD,CE_TOTALE!O$3) -> 0 | P39: =SUMIFS('DB Shopify'!$CI:$CI,'DB Shopify'!$CC:$CC,CE_TOTALE!P$2,'DB Shopify'!$CD:$CD,CE_TOTALE!P$3) -> 0 | ... R39: =SUMIFS('DB Shopify'!$CI:$CI,'DB Shopify'!$CC:$CC,CE_TOTALE!R$2,'DB Shopify'!$CD:$CD,CE_TOTALE!R$3) -> 0 | T39: =SUM(G39:R39) -> -1829.4638
A40: -207 | B40: =E40&F40 -> VariabiliLogistica | C40: NO | D40: Costi | E40: Variabili | F40: Logistica | G40: -1172 | H40: =A40+ SUMIFS('EXPENSES MASTER'!$F:$F,'EXPENSES MASTER'!$G:$G,CE_TOTALE!$F$48,'EXPENSES MASTER'!$A:$A,CE_TOTALE!H$2,'EXPENSES MASTER'!$B:$B,CE_TOTALE!H$3,'EXPENSES MASTER'!$H:$H,CE_TOTALE!$A40) -> -207 | I40: =SUMIFS('EXPENSES MASTER'!$F:$F,'EXPENSES MASTER'!$G:$G,CE_TOTALE!$F$48,'EXPENSES MASTER'!$A:$A,CE_TOTALE!I$2,'EXPENSES MASTER'!$B:$B,CE_TOTALE!I$3,'EXPENSES MASTER'!$H:$H,CE_TOTALE!$A40) -> 0 | J40: =SUMIFS('EXPENSES MASTER'!$F:$F,'EXPENSES MASTER'!$G:$G,CE_TOTALE!$F$48,'EXPENSES MASTER'!$A:$A,CE_TOTALE!J$2,'EXPENSES MASTER'!$B:$B,CE_TOTALE!J$3,'EXPENSES MASTER'!$H:$H,CE_TOTALE!$A40) -> 0 | K40: =SUMIFS('EXPENSES MASTER'!$F:$F,'EXPENSES MASTER'!$G:$G,CE_TOTALE!$F$48,'EXPENSES MASTER'!$A:$A,CE_TOTALE!K$2,'EXPENSES MASTER'!$B:$B,CE_TOTALE!K$3,'EXPENSES MASTER'!$H:$H,CE_TOTALE!$A40) -> 0 | L40: =SUMIFS('EXPENSES MASTER'!$F:$F,'EXPENSES MASTER'!$G:$G,CE_TOTALE!$F$48,'EXPENSES MASTER'!$A:$A,CE_TOTALE!L$2,'EXPENSES MASTER'!$B:$B,CE_TOTALE!L$3,'EXPENSES MASTER'!$H:$H,CE_TOTALE!$A40) -> 0 | M40: =SUMIFS('EXPENSES MASTER'!$F:$F,'EXPENSES MASTER'!$G:$G,CE_TOTALE!$F$48,'EXPENSES MASTER'!$A:$A,CE_TOTALE!M$2,'EXPENSES MASTER'!$B:$B,CE_TOTALE!M$3,'EXPENSES MASTER'!$H:$H,CE_TOTALE!$A40) -> 0 | N40: =SUMIFS('EXPENSES MASTER'!$F:$F,'EXPENSES MASTER'!$G:$G,CE_TOTALE!$F$48,'EXPENSES MASTER'!$A:$A,CE_TOTALE!N$2,'EXPENSES MASTER'!$B:$B,CE_TOTALE!N$3,'EXPENSES MASTER'!$H:$H,CE_TOTALE!$A40) -> 0 | O40: =SUMIFS('EXPENSES MASTER'!$F:$F,'EXPENSES MASTER'!$G:$G,CE_TOTALE!$F$48,'EXPENSES MASTER'!$A:$A,CE_TOTALE!O$2,'EXPENSES MASTER'!$B:$B,CE_TOTALE!O$3,'EXPENSES MASTER'!$H:$H,CE_TOTALE!$A40) -> 0 | P40: =SUMIFS('EXPENSES MASTER'!$F:$F,'EXPENSES MASTER'!$G:$G,CE_TOTALE!$F$48,'EXPENSES MASTER'!$A:$A,CE_TOTALE!P$2,'EXPENSES MASTER'!$B:$B,CE_TOTALE!P$3,'EXPENSES MASTER'!$H:$H,CE_TOTALE!$A40) -> 0 | ... R40: =SUMIFS('EXPENSES MASTER'!$F:$F,'EXPENSES MASTER'!$G:$G,CE_TOTALE!$F$48,'EXPENSES MASTER'!$A:$A,CE_TOTALE!R$2,'EXPENSES MASTER'!$B:$B,CE_TOTALE!R$3,'EXPENSES MASTER'!$H:$H,CE_TOTALE!$A40) -> 0 | T40: =SUM(G40:R40) -> -1379
A41: -220 | B41: =E41&F41 -> VariabiliResi | C41: NO | D41: Costi | E41: Variabili | F41: Resi | G41: -209 | H41: =A41-SUMIFS('DB Shopify'!$AX:$AX,'DB Shopify'!$CC:$CC,CE_TOTALE!H$2,'DB Shopify'!$CD:$CD,CE_TOTALE!H$3) -> -226.9 | I41: =-SUMIFS('DB Shopify'!$AX:$AX,'DB Shopify'!$CC:$CC,CE_TOTALE!I$2,'DB Shopify'!$CD:$CD,CE_TOTALE!I$3) -> 0 | J41: =-SUMIFS('DB Shopify'!$AX:$AX,'DB Shopify'!$CC:$CC,CE_TOTALE!J$2,'DB Shopify'!$CD:$CD,CE_TOTALE!J$3) -> 0 | K41: =-SUMIFS('DB Shopify'!$AX:$AX,'DB Shopify'!$CC:$CC,CE_TOTALE!K$2,'DB Shopify'!$CD:$CD,CE_TOTALE!K$3) -> -336 | L41: =-SUMIFS('DB Shopify'!$AX:$AX,'DB Shopify'!$CC:$CC,CE_TOTALE!L$2,'DB Shopify'!$CD:$CD,CE_TOTALE!L$3) -> -530.5 | M41: =-SUMIFS('DB Shopify'!$AX:$AX,'DB Shopify'!$CC:$CC,CE_TOTALE!M$2,'DB Shopify'!$CD:$CD,CE_TOTALE!M$3) -> 0 | N41: =-SUMIFS('DB Shopify'!$AX:$AX,'DB Shopify'!$CC:$CC,CE_TOTALE!N$2,'DB Shopify'!$CD:$CD,CE_TOTALE!N$3) -> 0 | O41: =-SUMIFS('DB Shopify'!$AX:$AX,'DB Shopify'!$CC:$CC,CE_TOTALE!O$2,'DB Shopify'!$CD:$CD,CE_TOTALE!O$3) -> 0 | P41: =-SUMIFS('DB Shopify'!$AX:$AX,'DB Shopify'!$CC:$CC,CE_TOTALE!P$2,'DB Shopify'!$CD:$CD,CE_TOTALE!P$3) -> 0 | ... R41: =-SUMIFS('DB Shopify'!$AX:$AX,'DB Shopify'!$CC:$CC,CE_TOTALE!R$2,'DB Shopify'!$CD:$CD,CE_TOTALE!R$3) -> 0 | T41: =SUM(G41:R41) -> -1302.4
A42: -1185 | B42: =E42&F42 -> VariabiliTotal | C42: NO | D42: Costi | E42: Variabili | F42: Total | G42: -3646 | H42: =H31+H32+H39+H40+H41 -> -2194.8052 | I42: =I31+I32+I39+I40+I41 -> -3533.7565 | J42: =J31+J32+J39+J40+J41 -> -3820.5142 | K42: =K31+K32+K39+K40+K41 -> -4636.787 | L42: =L31+L32+L39+L40+L41 -> -9157.2826 | M42: =M31+M32+M39+M40+M41 -> -205.0882 | N42: =N31+N32+N39+N40+N41 -> 0 | O42: =O31+O32+O39+O40+O41 -> 0 | ... R42: =R31+R32+R39+R40+R41 -> 0 | T42: =SUM(G42:R42) -> -27194.234
B43: =E43&F43 | T43: =1+T42/T29 -> 0.55858157
A44: 123 | B44: =E44&F44 -> OmnichannelMargine di Contribuzione_1 | E44: Omnichannel | F44: Margine di Contribuzione_1 | G44: =G29+G42 -> 802 | H44: =H29+H42 -> 1636.6702 | I44: =I29+I42 -> 5509.2763 | J44: =J29+J42 -> 6300.5514 | K44: =K29+K42 -> 7649.7704 | L44: =L29+L42 -> 11433.98 | M44: =M29+M42 -> 1079.9938 | N44: =N29+N42 -> 0 | ... R44: =R29+R42 -> 0 | T44: =SUM(G44:R44) -> 34412.242
B45: =E45&F45 | G45: =IFERROR(G44/G29, 0) -> 0.18030576 | H45: =IFERROR(H44/H29, 0) -> 0.42716447 | I45: =IFERROR(I44/I29, 0) -> 0.60922883 | J45: =IFERROR(J44/J29, 0) -> 0.62251858 | K45: =IFERROR(K44/K29, 0) -> 0.622613 | L45: =IFERROR(L44/L29, 0) -> 0.55528309 | M45: =IFERROR(M44/M29, 0) -> 0.84040847 | N45: =IFERROR(N44/N29, 0) -> 0 | ... R45: =IFERROR(R44/R29, 0) -> 0 | T45: =T44/T29 -> 0.55858157
B46: =E46&F46 -> FissiSALARI | C46: NO | D46: Costi | E46: Fissi | F46: SALARI | G46: =SUMIFS('EXPENSES MASTER'!$F:$F,'EXPENSES MASTER'!$G:$G,CE_TOTALE!$F46,'EXPENSES MASTER'!$B:$B,CE_TOTALE!G$3,'EXPENSES MASTER'!$A:$A,CE_TOTALE!G$2) -> 0 | H46: =SUMIFS('EXPENSES MASTER'!$F:$F,'EXPENSES MASTER'!$G:$G,CE_TOTALE!$F46,'EXPENSES MASTER'!$B:$B,CE_TOTALE!H$3,'EXPENSES MASTER'!$A:$A,CE_TOTALE!H$2) -> -270 | I46: =SUMIFS('EXPENSES MASTER'!$F:$F,'EXPENSES MASTER'!$G:$G,CE_TOTALE!$F46,'EXPENSES MASTER'!$B:$B,CE_TOTALE!I$3,'EXPENSES MASTER'!$A:$A,CE_TOTALE!I$2) -> -1630 | J46: =SUMIFS('EXPENSES MASTER'!$F:$F,'EXPENSES MASTER'!$G:$G,CE_TOTALE!$F46,'EXPENSES MASTER'!$B:$B,CE_TOTALE!J$3,'EXPENSES MASTER'!$A:$A,CE_TOTALE!J$2) -> -1552 | K46: =SUMIFS('EXPENSES MASTER'!$F:$F,'EXPENSES MASTER'!$G:$G,CE_TOTALE!$F46,'EXPENSES MASTER'!$B:$B,CE_TOTALE!K$3,'EXPENSES MASTER'!$A:$A,CE_TOTALE!K$2) -> 0 | L46: =SUMIFS('EXPENSES MASTER'!$F:$F,'EXPENSES MASTER'!$G:$G,CE_TOTALE!$F46,'EXPENSES MASTER'!$B:$B,CE_TOTALE!L$3,'EXPENSES MASTER'!$A:$A,CE_TOTALE!L$2) -> 0 | M46: =SUMIFS('EXPENSES MASTER'!$F:$F,'EXPENSES MASTER'!$G:$G,CE_TOTALE!$F46,'EXPENSES MASTER'!$B:$B,CE_TOTALE!M$3,'EXPENSES MASTER'!$A:$A,CE_TOTALE!M$2) -> 0 | N46: =SUMIFS('EXPENSES MASTER'!$F:$F,'EXPENSES MASTER'!$G:$G,CE_TOTALE!$F46,'EXPENSES MASTER'!$B:$B,CE_TOTALE!N$3,'EXPENSES MASTER'!$A:$A,CE_TOTALE!N$2) -> 0 | ... R46: =SUMIFS('EXPENSES MASTER'!$F:$F,'EXPENSES MASTER'!$G:$G,CE_TOTALE!$F46,'EXPENSES MASTER'!$B:$B,CE_TOTALE!R$3,'EXPENSES MASTER'!$A:$A,CE_TOTALE!R$2) -> 0 | T46: =SUM(G46:R46) -> -3452
B47: =E47&F47 -> FissiTASSE | C47: NO | D47: Costi | E47: Fissi | F47: TASSE | G47: =SUMIFS('EXPENSES MASTER'!$F:$F,'EXPENSES MASTER'!$G:$G,CE_TOTALE!$F47,'EXPENSES MASTER'!$B:$B,CE_TOTALE!G$3,'EXPENSES MASTER'!$A:$A,CE_TOTALE!G$2) -> 0 | H47: =SUMIFS('EXPENSES MASTER'!$F:$F,'EXPENSES MASTER'!$G:$G,CE_TOTALE!$F47,'EXPENSES MASTER'!$B:$B,CE_TOTALE!H$3,'EXPENSES MASTER'!$A:$A,CE_TOTALE!H$2) -> 0 | I47: =SUMIFS('EXPENSES MASTER'!$F:$F,'EXPENSES MASTER'!$G:$G,CE_TOTALE!$F47,'EXPENSES MASTER'!$B:$B,CE_TOTALE!I$3,'EXPENSES MASTER'!$A:$A,CE_TOTALE!I$2) -> -1321.87 | J47: =SUMIFS('EXPENSES MASTER'!$F:$F,'EXPENSES MASTER'!$G:$G,CE_TOTALE!$F47,'EXPENSES MASTER'!$B:$B,CE_TOTALE!J$3,'EXPENSES MASTER'!$A:$A,CE_TOTALE!J$2) -> -236.57 | K47: =SUMIFS('EXPENSES MASTER'!$F:$F,'EXPENSES MASTER'!$G:$G,CE_TOTALE!$F47,'EXPENSES MASTER'!$B:$B,CE_TOTALE!K$3,'EXPENSES MASTER'!$A:$A,CE_TOTALE!K$2) -> -800.41 | L47: =SUMIFS('EXPENSES MASTER'!$F:$F,'EXPENSES MASTER'!$G:$G,CE_TOTALE!$F47,'EXPENSES MASTER'!$B:$B,CE_TOTALE!L$3,'EXPENSES MASTER'!$A:$A,CE_TOTALE!L$2) -> -1848.99 | M47: =SUMIFS('EXPENSES MASTER'!$F:$F,'EXPENSES MASTER'!$G:$G,CE_TOTALE!$F47,'EXPENSES MASTER'!$B:$B,CE_TOTALE!M$3,'EXPENSES MASTER'!$A:$A,CE_TOTALE!M$2) -> 0 | N47: =SUMIFS('EXPENSES MASTER'!$F:$F,'EXPENSES MASTER'!$G:$G,CE_TOTALE!$F47,'EXPENSES MASTER'!$B:$B,CE_TOTALE!N$3,'EXPENSES MASTER'!$A:$A,CE_TOTALE!N$2) -> 0 | ... R47: =SUMIFS('EXPENSES MASTER'!$F:$F,'EXPENSES MASTER'!$G:$G,CE_TOTALE!$F47,'EXPENSES MASTER'!$B:$B,CE_TOTALE!R$3,'EXPENSES MASTER'!$A:$A,CE_TOTALE!R$2) -> 0 | T47: =SUM(G47:R47) -> -4207.84
A48: MAGAZZINO | B48: =E48&F48 -> FissiLOGISTICA | C48: NO | D48: Costi | E48: Fissi | F48: LOGISTICA | G48: =SUMIFS('EXPENSES MASTER'!$F:$F,'EXPENSES MASTER'!$G:$G,CE_TOTALE!$F$48,'EXPENSES MASTER'!$A:$A,CE_TOTALE!G$2,'EXPENSES MASTER'!$B:$B,CE_TOTALE!G$3,'EXPENSES MASTER'!$H:$H,CE_TOTALE!$A48) -> 0 | H48: =SUMIFS('EXPENSES MASTER'!$F:$F,'EXPENSES MASTER'!$G:$G,CE_TOTALE!$F$48,'EXPENSES MASTER'!$A:$A,CE_TOTALE!H$2,'EXPENSES MASTER'!$B:$B,CE_TOTALE!H$3,'EXPENSES MASTER'!$H:$H,CE_TOTALE!$A48) -> 0 | I48: =SUMIFS('EXPENSES MASTER'!$F:$F,'EXPENSES MASTER'!$G:$G,CE_TOTALE!$F$48,'EXPENSES MASTER'!$A:$A,CE_TOTALE!I$2,'EXPENSES MASTER'!$B:$B,CE_TOTALE!I$3,'EXPENSES MASTER'!$H:$H,CE_TOTALE!$A48) -> 0 | J48: =SUMIFS('EXPENSES MASTER'!$F:$F,'EXPENSES MASTER'!$G:$G,CE_TOTALE!$F$48,'EXPENSES MASTER'!$A:$A,CE_TOTALE!J$2,'EXPENSES MASTER'!$B:$B,CE_TOTALE!J$3,'EXPENSES MASTER'!$H:$H,CE_TOTALE!$A48) -> -555.06 | K48: =SUMIFS('EXPENSES MASTER'!$F:$F,'EXPENSES MASTER'!$G:$G,CE_TOTALE!$F$48,'EXPENSES MASTER'!$A:$A,CE_TOTALE!K$2,'EXPENSES MASTER'!$B:$B,CE_TOTALE!K$3,'EXPENSES MASTER'!$H:$H,CE_TOTALE!$A48) -> -355.23 | L48: =SUMIFS('EXPENSES MASTER'!$F:$F,'EXPENSES MASTER'!$G:$G,CE_TOTALE!$F$48,'EXPENSES MASTER'!$A:$A,CE_TOTALE!L$2,'EXPENSES MASTER'!$B:$B,CE_TOTALE!L$3,'EXPENSES MASTER'!$H:$H,CE_TOTALE!$A48) -> 0 | M48: =SUMIFS('EXPENSES MASTER'!$F:$F,'EXPENSES MASTER'!$G:$G,CE_TOTALE!$F$48,'EXPENSES MASTER'!$A:$A,CE_TOTALE!M$2,'EXPENSES MASTER'!$B:$B,CE_TOTALE!M$3,'EXPENSES MASTER'!$H:$H,CE_TOTALE!$A48) -> 0 | N48: =SUMIFS('EXPENSES MASTER'!$F:$F,'EXPENSES MASTER'!$G:$G,CE_TOTALE!$F$48,'EXPENSES MASTER'!$A:$A,CE_TOTALE!N$2,'EXPENSES MASTER'!$B:$B,CE_TOTALE!N$3,'EXPENSES MASTER'!$H:$H,CE_TOTALE!$A48) -> 0 | ... R48: =SUMIFS('EXPENSES MASTER'!$F:$F,'EXPENSES MASTER'!$G:$G,CE_TOTALE!$F$48,'EXPENSES MASTER'!$A:$A,CE_TOTALE!R$2,'EXPENSES MASTER'!$B:$B,CE_TOTALE!R$3,'EXPENSES MASTER'!$H:$H,CE_TOTALE!$A48) -> 0 | T48: =SUM(G48:R48) -> -910.29
B49: =E49&F49 -> FissiOPEX | C49: NO | D49: Costi | E49: Fissi | F49: OPEX | G49: =SUM(G50:G54) -> -1410.15 | H49: =SUM(H50:H54) -> -926.53 | I49: =SUM(I50:I54) -> -2410.54 | J49: =SUM(J50:J54) -> -1294.31 | K49: =SUM(K50:K54) -> -3289.47 | L49: =SUM(L50:L54) -> -1288.96 | M49: =SUM(M50:M54) -> 0 | N49: =SUM(N50:N54) -> 0 | ... R49: =SUM(R50:R54) -> 0 | T49: =SUM(G49:R49) -> -10619.96
B50: =E50&F50 -> Legale_Commercialista | F50: Legale_Commercialista | G50: =SUMIFS('EXPENSES MASTER'!$F:$F,'EXPENSES MASTER'!$G:$G,CE_TOTALE!$F$49,'EXPENSES MASTER'!$A:$A,CE_TOTALE!G$2,'EXPENSES MASTER'!$B:$B,CE_TOTALE!G$3,'EXPENSES MASTER'!$H:$H,CE_TOTALE!$F50) -> 0 | H50: =SUMIFS('EXPENSES MASTER'!$F:$F,'EXPENSES MASTER'!$G:$G,CE_TOTALE!$F$49,'EXPENSES MASTER'!$A:$A,CE_TOTALE!H$2,'EXPENSES MASTER'!$B:$B,CE_TOTALE!H$3,'EXPENSES MASTER'!$H:$H,CE_TOTALE!$F50) -> 0 | I50: =SUMIFS('EXPENSES MASTER'!$F:$F,'EXPENSES MASTER'!$G:$G,CE_TOTALE!$F$49,'EXPENSES MASTER'!$A:$A,CE_TOTALE!I$2,'EXPENSES MASTER'!$B:$B,CE_TOTALE!I$3,'EXPENSES MASTER'!$H:$H,CE_TOTALE!$F50) -> 0 | J50: =SUMIFS('EXPENSES MASTER'!$F:$F,'EXPENSES MASTER'!$G:$G,CE_TOTALE!$F$49,'EXPENSES MASTER'!$A:$A,CE_TOTALE!J$2,'EXPENSES MASTER'!$B:$B,CE_TOTALE!J$3,'EXPENSES MASTER'!$H:$H,CE_TOTALE!$F50) -> -1020.68 | K50: =SUMIFS('EXPENSES MASTER'!$F:$F,'EXPENSES MASTER'!$G:$G,CE_TOTALE!$F$49,'EXPENSES MASTER'!$A:$A,CE_TOTALE!K$2,'EXPENSES MASTER'!$B:$B,CE_TOTALE!K$3,'EXPENSES MASTER'!$H:$H,CE_TOTALE!$F50) -> -2341 | L50: =SUMIFS('EXPENSES MASTER'!$F:$F,'EXPENSES MASTER'!$G:$G,CE_TOTALE!$F$49,'EXPENSES MASTER'!$A:$A,CE_TOTALE!L$2,'EXPENSES MASTER'!$B:$B,CE_TOTALE!L$3,'EXPENSES MASTER'!$H:$H,CE_TOTALE!$F50) -> 0 | M50: =SUMIFS('EXPENSES MASTER'!$F:$F,'EXPENSES MASTER'!$G:$G,CE_TOTALE!$F$49,'EXPENSES MASTER'!$A:$A,CE_TOTALE!M$2,'EXPENSES MASTER'!$B:$B,CE_TOTALE!M$3,'EXPENSES MASTER'!$H:$H,CE_TOTALE!$F50) -> 0 | N50: =SUMIFS('EXPENSES MASTER'!$F:$F,'EXPENSES MASTER'!$G:$G,CE_TOTALE!$F$49,'EXPENSES MASTER'!$A:$A,CE_TOTALE!N$2,'EXPENSES MASTER'!$B:$B,CE_TOTALE!N$3,'EXPENSES MASTER'!$H:$H,CE_TOTALE!$F50) -> 0 | ... R50: =SUMIFS('EXPENSES MASTER'!$F:$F,'EXPENSES MASTER'!$G:$G,CE_TOTALE!$F$49,'EXPENSES MASTER'!$A:$A,CE_TOTALE!R$2,'EXPENSES MASTER'!$B:$B,CE_TOTALE!R$3,'EXPENSES MASTER'!$H:$H,CE_TOTALE!$F50) -> 0 | T50: =SUM(G50:R50) -> -3361.68
B51: =E51&F51 -> Campionatura | F51: Campionatura | G51: =SUMIFS('EXPENSES MASTER'!$F:$F,'EXPENSES MASTER'!$G:$G,CE_TOTALE!$F$49,'EXPENSES MASTER'!$A:$A,CE_TOTALE!G$2,'EXPENSES MASTER'!$B:$B,CE_TOTALE!G$3,'EXPENSES MASTER'!$H:$H,CE_TOTALE!$F51) -> 0 | H51: =SUMIFS('EXPENSES MASTER'!$F:$F,'EXPENSES MASTER'!$G:$G,CE_TOTALE!$F$49,'EXPENSES MASTER'!$A:$A,CE_TOTALE!H$2,'EXPENSES MASTER'!$B:$B,CE_TOTALE!H$3,'EXPENSES MASTER'!$H:$H,CE_TOTALE!$F51) -> 0 | I51: =SUMIFS('EXPENSES MASTER'!$F:$F,'EXPENSES MASTER'!$G:$G,CE_TOTALE!$F$49,'EXPENSES MASTER'!$A:$A,CE_TOTALE!I$2,'EXPENSES MASTER'!$B:$B,CE_TOTALE!I$3,'EXPENSES MASTER'!$H:$H,CE_TOTALE!$F51) -> 0 | J51: =SUMIFS('EXPENSES MASTER'!$F:$F,'EXPENSES MASTER'!$G:$G,CE_TOTALE!$F$49,'EXPENSES MASTER'!$A:$A,CE_TOTALE!J$2,'EXPENSES MASTER'!$B:$B,CE_TOTALE!J$3,'EXPENSES MASTER'!$H:$H,CE_TOTALE!$F51) -> 0 | K51: =SUMIFS('EXPENSES MASTER'!$F:$F,'EXPENSES MASTER'!$G:$G,CE_TOTALE!$F$49,'EXPENSES MASTER'!$A:$A,CE_TOTALE!K$2,'EXPENSES MASTER'!$B:$B,CE_TOTALE!K$3,'EXPENSES MASTER'!$H:$H,CE_TOTALE!$F51) -> 0 | L51: =SUMIFS('EXPENSES MASTER'!$F:$F,'EXPENSES MASTER'!$G:$G,CE_TOTALE!$F$49,'EXPENSES MASTER'!$A:$A,CE_TOTALE!L$2,'EXPENSES MASTER'!$B:$B,CE_TOTALE!L$3,'EXPENSES MASTER'!$H:$H,CE_TOTALE!$F51) -> 0 | M51: =SUMIFS('EXPENSES MASTER'!$F:$F,'EXPENSES MASTER'!$G:$G,CE_TOTALE!$F$49,'EXPENSES MASTER'!$A:$A,CE_TOTALE!M$2,'EXPENSES MASTER'!$B:$B,CE_TOTALE!M$3,'EXPENSES MASTER'!$H:$H,CE_TOTALE!$F51) -> 0 | N51: =SUMIFS('EXPENSES MASTER'!$F:$F,'EXPENSES MASTER'!$G:$G,CE_TOTALE!$F$49,'EXPENSES MASTER'!$A:$A,CE_TOTALE!N$2,'EXPENSES MASTER'!$B:$B,CE_TOTALE!N$3,'EXPENSES MASTER'!$H:$H,CE_TOTALE!$F51) -> 0 | ... R51: =SUMIFS('EXPENSES MASTER'!$F:$F,'EXPENSES MASTER'!$G:$G,CE_TOTALE!$F$49,'EXPENSES MASTER'!$A:$A,CE_TOTALE!R$2,'EXPENSES MASTER'!$B:$B,CE_TOTALE!R$3,'EXPENSES MASTER'!$H:$H,CE_TOTALE!$F51) -> 0 | T51: =SUM(G51:R51) -> 0
B52: Ufficio | F52: Ufficio | G52: =SUMIFS('EXPENSES MASTER'!$F:$F,'EXPENSES MASTER'!$G:$G,CE_TOTALE!$F$49,'EXPENSES MASTER'!$A:$A,CE_TOTALE!G$2,'EXPENSES MASTER'!$B:$B,CE_TOTALE!G$3,'EXPENSES MASTER'!$H:$H,CE_TOTALE!$F52) -> 0 | H52: =SUMIFS('EXPENSES MASTER'!$F:$F,'EXPENSES MASTER'!$G:$G,CE_TOTALE!$F$49,'EXPENSES MASTER'!$A:$A,CE_TOTALE!H$2,'EXPENSES MASTER'!$B:$B,CE_TOTALE!H$3,'EXPENSES MASTER'!$H:$H,CE_TOTALE!$F52) -> -400 | I52: =SUMIFS('EXPENSES MASTER'!$F:$F,'EXPENSES MASTER'!$G:$G,CE_TOTALE!$F$49,'EXPENSES MASTER'!$A:$A,CE_TOTALE!I$2,'EXPENSES MASTER'!$B:$B,CE_TOTALE!I$3,'EXPENSES MASTER'!$H:$H,CE_TOTALE!$F52) -> -400 | J52: =SUMIFS('EXPENSES MASTER'!$F:$F,'EXPENSES MASTER'!$G:$G,CE_TOTALE!$F$49,'EXPENSES MASTER'!$A:$A,CE_TOTALE!J$2,'EXPENSES MASTER'!$B:$B,CE_TOTALE!J$3,'EXPENSES MASTER'!$H:$H,CE_TOTALE!$F52) -> 0 | K52: =SUMIFS('EXPENSES MASTER'!$F:$F,'EXPENSES MASTER'!$G:$G,CE_TOTALE!$F$49,'EXPENSES MASTER'!$A:$A,CE_TOTALE!K$2,'EXPENSES MASTER'!$B:$B,CE_TOTALE!K$3,'EXPENSES MASTER'!$H:$H,CE_TOTALE!$F52) -> -19.76 | L52: =SUMIFS('EXPENSES MASTER'!$F:$F,'EXPENSES MASTER'!$G:$G,CE_TOTALE!$F$49,'EXPENSES MASTER'!$A:$A,CE_TOTALE!L$2,'EXPENSES MASTER'!$B:$B,CE_TOTALE!L$3,'EXPENSES MASTER'!$H:$H,CE_TOTALE!$F52) -> -23.59 | M52: =SUMIFS('EXPENSES MASTER'!$F:$F,'EXPENSES MASTER'!$G:$G,CE_TOTALE!$F$49,'EXPENSES MASTER'!$A:$A,CE_TOTALE!M$2,'EXPENSES MASTER'!$B:$B,CE_TOTALE!M$3,'EXPENSES MASTER'!$H:$H,CE_TOTALE!$F52) -> 0 | N52: =SUMIFS('EXPENSES MASTER'!$F:$F,'EXPENSES MASTER'!$G:$G,CE_TOTALE!$F$49,'EXPENSES MASTER'!$A:$A,CE_TOTALE!N$2,'EXPENSES MASTER'!$B:$B,CE_TOTALE!N$3,'EXPENSES MASTER'!$H:$H,CE_TOTALE!$F52) -> 0 | ... R52: =SUMIFS('EXPENSES MASTER'!$F:$F,'EXPENSES MASTER'!$G:$G,CE_TOTALE!$F$49,'EXPENSES MASTER'!$A:$A,CE_TOTALE!R$2,'EXPENSES MASTER'!$B:$B,CE_TOTALE!R$3,'EXPENSES MASTER'!$H:$H,CE_TOTALE!$F52) -> 0 | T52: =SUM(G52:R52) -> -843.35
B53: =E53&F53 -> Vivaio | F53: Vivaio | G53: =SUMIFS('EXPENSES MASTER'!$F:$F,'EXPENSES MASTER'!$G:$G,CE_TOTALE!$F$49,'EXPENSES MASTER'!$A:$A,CE_TOTALE!G$2,'EXPENSES MASTER'!$B:$B,CE_TOTALE!G$3,'EXPENSES MASTER'!$H:$H,CE_TOTALE!$F53) -> 0 | H53: =SUMIFS('EXPENSES MASTER'!$F:$F,'EXPENSES MASTER'!$G:$G,CE_TOTALE!$F$49,'EXPENSES MASTER'!$A:$A,CE_TOTALE!H$2,'EXPENSES MASTER'!$B:$B,CE_TOTALE!H$3,'EXPENSES MASTER'!$H:$H,CE_TOTALE!$F53) -> 0 | I53: =SUMIFS('EXPENSES MASTER'!$F:$F,'EXPENSES MASTER'!$G:$G,CE_TOTALE!$F$49,'EXPENSES MASTER'!$A:$A,CE_TOTALE!I$2,'EXPENSES MASTER'!$B:$B,CE_TOTALE!I$3,'EXPENSES MASTER'!$H:$H,CE_TOTALE!$F53) -> 0 | J53: =SUMIFS('EXPENSES MASTER'!$F:$F,'EXPENSES MASTER'!$G:$G,CE_TOTALE!$F$49,'EXPENSES MASTER'!$A:$A,CE_TOTALE!J$2,'EXPENSES MASTER'!$B:$B,CE_TOTALE!J$3,'EXPENSES MASTER'!$H:$H,CE_TOTALE!$F53) -> 0 | K53: =SUMIFS('EXPENSES MASTER'!$F:$F,'EXPENSES MASTER'!$G:$G,CE_TOTALE!$F$49,'EXPENSES MASTER'!$A:$A,CE_TOTALE!K$2,'EXPENSES MASTER'!$B:$B,CE_TOTALE!K$3,'EXPENSES MASTER'!$H:$H,CE_TOTALE!$F53) -> 0 | L53: =SUMIFS('EXPENSES MASTER'!$F:$F,'EXPENSES MASTER'!$G:$G,CE_TOTALE!$F$49,'EXPENSES MASTER'!$A:$A,CE_TOTALE!L$2,'EXPENSES MASTER'!$B:$B,CE_TOTALE!L$3,'EXPENSES MASTER'!$H:$H,CE_TOTALE!$F53) -> 0 | M53: =SUMIFS('EXPENSES MASTER'!$F:$F,'EXPENSES MASTER'!$G:$G,CE_TOTALE!$F$49,'EXPENSES MASTER'!$A:$A,CE_TOTALE!M$2,'EXPENSES MASTER'!$B:$B,CE_TOTALE!M$3,'EXPENSES MASTER'!$H:$H,CE_TOTALE!$F53) -> 0 | N53: =SUMIFS('EXPENSES MASTER'!$F:$F,'EXPENSES MASTER'!$G:$G,CE_TOTALE!$F$49,'EXPENSES MASTER'!$A:$A,CE_TOTALE!N$2,'EXPENSES MASTER'!$B:$B,CE_TOTALE!N$3,'EXPENSES MASTER'!$H:$H,CE_TOTALE!$F53) -> 0 | ... R53: =SUMIFS('EXPENSES MASTER'!$F:$F,'EXPENSES MASTER'!$G:$G,CE_TOTALE!$F$49,'EXPENSES MASTER'!$A:$A,CE_TOTALE!R$2,'EXPENSES MASTER'!$B:$B,CE_TOTALE!R$3,'EXPENSES MASTER'!$H:$H,CE_TOTALE!$F53) -> 0 | T53: =SUM(G53:R53) -> 0
B54: =E54&F54 -> Others | F54: Others | G54: =SUMIFS('EXPENSES MASTER'!$F:$F,'EXPENSES MASTER'!$G:$G,CE_TOTALE!$F$49,'EXPENSES MASTER'!$A:$A,CE_TOTALE!G$2,'EXPENSES MASTER'!$B:$B,CE_TOTALE!G$3,'EXPENSES MASTER'!$H:$H,CE_TOTALE!$F54) -> -1410.15 | H54: =SUMIFS('EXPENSES MASTER'!$F:$F,'EXPENSES MASTER'!$G:$G,CE_TOTALE!$F$49,'EXPENSES MASTER'!$A:$A,CE_TOTALE!H$2,'EXPENSES MASTER'!$B:$B,CE_TOTALE!H$3,'EXPENSES MASTER'!$H:$H,CE_TOTALE!$F54) -> -526.53 | I54: =SUMIFS('EXPENSES MASTER'!$F:$F,'EXPENSES MASTER'!$G:$G,CE_TOTALE!$F$49,'EXPENSES MASTER'!$A:$A,CE_TOTALE!I$2,'EXPENSES MASTER'!$B:$B,CE_TOTALE!I$3,'EXPENSES MASTER'!$H:$H,CE_TOTALE!$F54) -> -2010.54 | J54: =SUMIFS('EXPENSES MASTER'!$F:$F,'EXPENSES MASTER'!$G:$G,CE_TOTALE!$F$49,'EXPENSES MASTER'!$A:$A,CE_TOTALE!J$2,'EXPENSES MASTER'!$B:$B,CE_TOTALE!J$3,'EXPENSES MASTER'!$H:$H,CE_TOTALE!$F54) -> -273.63 | K54: =SUMIFS('EXPENSES MASTER'!$F:$F,'EXPENSES MASTER'!$G:$G,CE_TOTALE!$F$49,'EXPENSES MASTER'!$A:$A,CE_TOTALE!K$2,'EXPENSES MASTER'!$B:$B,CE_TOTALE!K$3,'EXPENSES MASTER'!$H:$H,CE_TOTALE!$F54) -> -928.71 | L54: =SUMIFS('EXPENSES MASTER'!$F:$F,'EXPENSES MASTER'!$G:$G,CE_TOTALE!$F$49,'EXPENSES MASTER'!$A:$A,CE_TOTALE!L$2,'EXPENSES MASTER'!$B:$B,CE_TOTALE!L$3,'EXPENSES MASTER'!$H:$H,CE_TOTALE!$F54) -> -1265.37 | M54: =SUMIFS('EXPENSES MASTER'!$F:$F,'EXPENSES MASTER'!$G:$G,CE_TOTALE!$F$49,'EXPENSES MASTER'!$A:$A,CE_TOTALE!M$2,'EXPENSES MASTER'!$B:$B,CE_TOTALE!M$3,'EXPENSES MASTER'!$H:$H,CE_TOTALE!$F54) -> 0 | N54: =SUMIFS('EXPENSES MASTER'!$F:$F,'EXPENSES MASTER'!$G:$G,CE_TOTALE!$F$49,'EXPENSES MASTER'!$A:$A,CE_TOTALE!N$2,'EXPENSES MASTER'!$B:$B,CE_TOTALE!N$3,'EXPENSES MASTER'!$H:$H,CE_TOTALE!$F54) -> 0 | ... R54: =SUMIFS('EXPENSES MASTER'!$F:$F,'EXPENSES MASTER'!$G:$G,CE_TOTALE!$F$49,'EXPENSES MASTER'!$A:$A,CE_TOTALE!R$2,'EXPENSES MASTER'!$B:$B,CE_TOTALE!R$3,'EXPENSES MASTER'!$H:$H,CE_TOTALE!$F54) -> 0 | T54: =SUM(G54:R54) -> -6414.93
B55: =E55&F55 -> FissiEVENTI | C55: NO | D55: Costi | E55: Fissi | F55: EVENTI | G55: =SUMIFS('EXPENSES MASTER'!$F:$F,'EXPENSES MASTER'!$G:$G,CE_TOTALE!$F$55,'EXPENSES MASTER'!$A:$A,CE_TOTALE!G$2,'EXPENSES MASTER'!$B:$B,CE_TOTALE!G$3) -> 0 | H55: =SUMIFS('EXPENSES MASTER'!$F:$F,'EXPENSES MASTER'!$G:$G,CE_TOTALE!$F$55,'EXPENSES MASTER'!$A:$A,CE_TOTALE!H$2,'EXPENSES MASTER'!$B:$B,CE_TOTALE!H$3) -> 0 | I55: =SUMIFS('EXPENSES MASTER'!$F:$F,'EXPENSES MASTER'!$G:$G,CE_TOTALE!$F$55,'EXPENSES MASTER'!$A:$A,CE_TOTALE!I$2,'EXPENSES MASTER'!$B:$B,CE_TOTALE!I$3) -> 0 | J55: =SUMIFS('EXPENSES MASTER'!$F:$F,'EXPENSES MASTER'!$G:$G,CE_TOTALE!$F$55,'EXPENSES MASTER'!$A:$A,CE_TOTALE!J$2,'EXPENSES MASTER'!$B:$B,CE_TOTALE!J$3) -> 0 | K55: =SUMIFS('EXPENSES MASTER'!$F:$F,'EXPENSES MASTER'!$G:$G,CE_TOTALE!$F$55,'EXPENSES MASTER'!$A:$A,CE_TOTALE!K$2,'EXPENSES MASTER'!$B:$B,CE_TOTALE!K$3) -> 0 | L55: =SUMIFS('EXPENSES MASTER'!$F:$F,'EXPENSES MASTER'!$G:$G,CE_TOTALE!$F$55,'EXPENSES MASTER'!$A:$A,CE_TOTALE!L$2,'EXPENSES MASTER'!$B:$B,CE_TOTALE!L$3) -> 0 | M55: =SUMIFS('EXPENSES MASTER'!$F:$F,'EXPENSES MASTER'!$G:$G,CE_TOTALE!$F$55,'EXPENSES MASTER'!$A:$A,CE_TOTALE!M$2,'EXPENSES MASTER'!$B:$B,CE_TOTALE!M$3) -> 0 | N55: =SUMIFS('EXPENSES MASTER'!$F:$F,'EXPENSES MASTER'!$G:$G,CE_TOTALE!$F$55,'EXPENSES MASTER'!$A:$A,CE_TOTALE!N$2,'EXPENSES MASTER'!$B:$B,CE_TOTALE!N$3) -> 0 | ... R55: =SUMIFS('EXPENSES MASTER'!$F:$F,'EXPENSES MASTER'!$G:$G,CE_TOTALE!$F$55,'EXPENSES MASTER'!$A:$A,CE_TOTALE!R$2,'EXPENSES MASTER'!$B:$B,CE_TOTALE!R$3) -> 0 | T55: =SUM(G55:R55) -> 0
B56: =E56&F56 -> FissiMARKETING | C56: NO | D56: Costi | E56: Fissi | F56: MARKETING | G56: =SUM(G57:G59) -> -1461.66 | H56: =SUM(H57:H59) -> -707.47 | I56: =SUM(I57:I59) -> -596.96 | J56: =SUM(J57:J59) -> -3236.3 | K56: =SUM(K57:K59) -> -1742.97 | L56: =SUM(L57:L59) -> -795.18 | M56: =SUM(M57:M59) -> 0 | N56: =SUM(N57:N59) -> 0 | ... R56: =SUM(R57:R59) -> 0 | T56: =SUM(G56:R56) -> -8540.54
B57: =E57&F57 -> Shooting | F57: Shooting | G57: =SUMIFS('EXPENSES MASTER'!$F:$F,'EXPENSES MASTER'!$G:$G,CE_TOTALE!$F$56,'EXPENSES MASTER'!$A:$A,CE_TOTALE!G$2,'EXPENSES MASTER'!$B:$B,CE_TOTALE!G$3,'EXPENSES MASTER'!$H:$H,CE_TOTALE!$F57) -> -324.48 | H57: =SUMIFS('EXPENSES MASTER'!$F:$F,'EXPENSES MASTER'!$G:$G,CE_TOTALE!$F$56,'EXPENSES MASTER'!$A:$A,CE_TOTALE!H$2,'EXPENSES MASTER'!$B:$B,CE_TOTALE!H$3,'EXPENSES MASTER'!$H:$H,CE_TOTALE!$F57) -> 0 | I57: =SUMIFS('EXPENSES MASTER'!$F:$F,'EXPENSES MASTER'!$G:$G,CE_TOTALE!$F$56,'EXPENSES MASTER'!$A:$A,CE_TOTALE!I$2,'EXPENSES MASTER'!$B:$B,CE_TOTALE!I$3,'EXPENSES MASTER'!$H:$H,CE_TOTALE!$F57) -> 0 | J57: =SUMIFS('EXPENSES MASTER'!$F:$F,'EXPENSES MASTER'!$G:$G,CE_TOTALE!$F$56,'EXPENSES MASTER'!$A:$A,CE_TOTALE!J$2,'EXPENSES MASTER'!$B:$B,CE_TOTALE!J$3,'EXPENSES MASTER'!$H:$H,CE_TOTALE!$F57) -> -1366.4 | K57: =SUMIFS('EXPENSES MASTER'!$F:$F,'EXPENSES MASTER'!$G:$G,CE_TOTALE!$F$56,'EXPENSES MASTER'!$A:$A,CE_TOTALE!K$2,'EXPENSES MASTER'!$B:$B,CE_TOTALE!K$3,'EXPENSES MASTER'!$H:$H,CE_TOTALE!$F57) -> 0 | L57: =SUMIFS('EXPENSES MASTER'!$F:$F,'EXPENSES MASTER'!$G:$G,CE_TOTALE!$F$56,'EXPENSES MASTER'!$A:$A,CE_TOTALE!L$2,'EXPENSES MASTER'!$B:$B,CE_TOTALE!L$3,'EXPENSES MASTER'!$H:$H,CE_TOTALE!$F57) -> -707.6 | M57: =SUMIFS('EXPENSES MASTER'!$F:$F,'EXPENSES MASTER'!$G:$G,CE_TOTALE!$F$56,'EXPENSES MASTER'!$A:$A,CE_TOTALE!M$2,'EXPENSES MASTER'!$B:$B,CE_TOTALE!M$3,'EXPENSES MASTER'!$H:$H,CE_TOTALE!$F57) -> 0 | N57: =SUMIFS('EXPENSES MASTER'!$F:$F,'EXPENSES MASTER'!$G:$G,CE_TOTALE!$F$56,'EXPENSES MASTER'!$A:$A,CE_TOTALE!N$2,'EXPENSES MASTER'!$B:$B,CE_TOTALE!N$3,'EXPENSES MASTER'!$H:$H,CE_TOTALE!$F57) -> 0 | ... R57: =SUMIFS('EXPENSES MASTER'!$F:$F,'EXPENSES MASTER'!$G:$G,CE_TOTALE!$F$56,'EXPENSES MASTER'!$A:$A,CE_TOTALE!R$2,'EXPENSES MASTER'!$B:$B,CE_TOTALE!R$3,'EXPENSES MASTER'!$H:$H,CE_TOTALE!$F57) -> 0 | T57: =SUM(G57:R57) -> -2398.48
B58: =E58&F58 -> Meta Ads | F58: Meta Ads | G58: =SUMIFS('EXPENSES MASTER'!$F:$F,'EXPENSES MASTER'!$G:$G,CE_TOTALE!$F$56,'EXPENSES MASTER'!$A:$A,CE_TOTALE!G$2,'EXPENSES MASTER'!$B:$B,CE_TOTALE!G$3,'EXPENSES MASTER'!$H:$H,CE_TOTALE!$F58) -> -1077.49 | H58: =SUMIFS('EXPENSES MASTER'!$F:$F,'EXPENSES MASTER'!$G:$G,CE_TOTALE!$F$56,'EXPENSES MASTER'!$A:$A,CE_TOTALE!H$2,'EXPENSES MASTER'!$B:$B,CE_TOTALE!H$3,'EXPENSES MASTER'!$H:$H,CE_TOTALE!$F58) -> 0 | I58: =SUMIFS('EXPENSES MASTER'!$F:$F,'EXPENSES MASTER'!$G:$G,CE_TOTALE!$F$56,'EXPENSES MASTER'!$A:$A,CE_TOTALE!I$2,'EXPENSES MASTER'!$B:$B,CE_TOTALE!I$3,'EXPENSES MASTER'!$H:$H,CE_TOTALE!$F58) -> -527.54 | J58: =SUMIFS('EXPENSES MASTER'!$F:$F,'EXPENSES MASTER'!$G:$G,CE_TOTALE!$F$56,'EXPENSES MASTER'!$A:$A,CE_TOTALE!J$2,'EXPENSES MASTER'!$B:$B,CE_TOTALE!J$3,'EXPENSES MASTER'!$H:$H,CE_TOTALE!$F58) -> -43.46 | K58: =SUMIFS('EXPENSES MASTER'!$F:$F,'EXPENSES MASTER'!$G:$G,CE_TOTALE!$F$56,'EXPENSES MASTER'!$A:$A,CE_TOTALE!K$2,'EXPENSES MASTER'!$B:$B,CE_TOTALE!K$3,'EXPENSES MASTER'!$H:$H,CE_TOTALE!$F58) -> -649.71 | L58: =SUMIFS('EXPENSES MASTER'!$F:$F,'EXPENSES MASTER'!$G:$G,CE_TOTALE!$F$56,'EXPENSES MASTER'!$A:$A,CE_TOTALE!L$2,'EXPENSES MASTER'!$B:$B,CE_TOTALE!L$3,'EXPENSES MASTER'!$H:$H,CE_TOTALE!$F58) -> 0 | M58: =SUMIFS('EXPENSES MASTER'!$F:$F,'EXPENSES MASTER'!$G:$G,CE_TOTALE!$F$56,'EXPENSES MASTER'!$A:$A,CE_TOTALE!M$2,'EXPENSES MASTER'!$B:$B,CE_TOTALE!M$3,'EXPENSES MASTER'!$H:$H,CE_TOTALE!$F58) -> 0 | N58: =SUMIFS('EXPENSES MASTER'!$F:$F,'EXPENSES MASTER'!$G:$G,CE_TOTALE!$F$56,'EXPENSES MASTER'!$A:$A,CE_TOTALE!N$2,'EXPENSES MASTER'!$B:$B,CE_TOTALE!N$3,'EXPENSES MASTER'!$H:$H,CE_TOTALE!$F58) -> 0 | ... R58: =SUMIFS('EXPENSES MASTER'!$F:$F,'EXPENSES MASTER'!$G:$G,CE_TOTALE!$F$56,'EXPENSES MASTER'!$A:$A,CE_TOTALE!R$2,'EXPENSES MASTER'!$B:$B,CE_TOTALE!R$3,'EXPENSES MASTER'!$H:$H,CE_TOTALE!$F58) -> 0 | T58: =SUM(G58:R58) -> -2298.2
B59: =E59&F59 -> Others | F59: Others | G59: =SUMIFS('EXPENSES MASTER'!$F:$F,'EXPENSES MASTER'!$G:$G,CE_TOTALE!$F$56,'EXPENSES MASTER'!$A:$A,CE_TOTALE!G$2,'EXPENSES MASTER'!$B:$B,CE_TOTALE!G$3,'EXPENSES MASTER'!$H:$H,CE_TOTALE!$F59) -> -59.69 | H59: =SUMIFS('EXPENSES MASTER'!$F:$F,'EXPENSES MASTER'!$G:$G,CE_TOTALE!$F$56,'EXPENSES MASTER'!$A:$A,CE_TOTALE!H$2,'EXPENSES MASTER'!$B:$B,CE_TOTALE!H$3,'EXPENSES MASTER'!$H:$H,CE_TOTALE!$F59) -> -707.47 | I59: =SUMIFS('EXPENSES MASTER'!$F:$F,'EXPENSES MASTER'!$G:$G,CE_TOTALE!$F$56,'EXPENSES MASTER'!$A:$A,CE_TOTALE!I$2,'EXPENSES MASTER'!$B:$B,CE_TOTALE!I$3,'EXPENSES MASTER'!$H:$H,CE_TOTALE!$F59) -> -69.42 | J59: =SUMIFS('EXPENSES MASTER'!$F:$F,'EXPENSES MASTER'!$G:$G,CE_TOTALE!$F$56,'EXPENSES MASTER'!$A:$A,CE_TOTALE!J$2,'EXPENSES MASTER'!$B:$B,CE_TOTALE!J$3,'EXPENSES MASTER'!$H:$H,CE_TOTALE!$F59) -> -1826.44 | K59: =SUMIFS('EXPENSES MASTER'!$F:$F,'EXPENSES MASTER'!$G:$G,CE_TOTALE!$F$56,'EXPENSES MASTER'!$A:$A,CE_TOTALE!K$2,'EXPENSES MASTER'!$B:$B,CE_TOTALE!K$3,'EXPENSES MASTER'!$H:$H,CE_TOTALE!$F59) -> -1093.26 | L59: =SUMIFS('EXPENSES MASTER'!$F:$F,'EXPENSES MASTER'!$G:$G,CE_TOTALE!$F$56,'EXPENSES MASTER'!$A:$A,CE_TOTALE!L$2,'EXPENSES MASTER'!$B:$B,CE_TOTALE!L$3,'EXPENSES MASTER'!$H:$H,CE_TOTALE!$F59) -> -87.58 | M59: =SUMIFS('EXPENSES MASTER'!$F:$F,'EXPENSES MASTER'!$G:$G,CE_TOTALE!$F$56,'EXPENSES MASTER'!$A:$A,CE_TOTALE!M$2,'EXPENSES MASTER'!$B:$B,CE_TOTALE!M$3,'EXPENSES MASTER'!$H:$H,CE_TOTALE!$F59) -> 0 | N59: =SUMIFS('EXPENSES MASTER'!$F:$F,'EXPENSES MASTER'!$G:$G,CE_TOTALE!$F$56,'EXPENSES MASTER'!$A:$A,CE_TOTALE!N$2,'EXPENSES MASTER'!$B:$B,CE_TOTALE!N$3,'EXPENSES MASTER'!$H:$H,CE_TOTALE!$F59) -> 0 | ... R59: =SUMIFS('EXPENSES MASTER'!$F:$F,'EXPENSES MASTER'!$G:$G,CE_TOTALE!$F$56,'EXPENSES MASTER'!$A:$A,CE_TOTALE!R$2,'EXPENSES MASTER'!$B:$B,CE_TOTALE!R$3,'EXPENSES MASTER'!$H:$H,CE_TOTALE!$F59) -> 0 | T59: =SUM(G59:R59) -> -3843.86
B60: =E60&F60 -> FissiTotal | C60: NO | D60: Costi | E60: Fissi | F60: Total | G60: =G55+G49+G48+G47+G46+G56 -> -2871.81 | H60: =H55+H49+H48+H47+H46+H56 -> -1904 | I60: =I55+I49+I48+I47+I46+I56 -> -5959.37 | J60: =J55+J49+J48+J47+J46+J56 -> -6874.24 | K60: =K55+K49+K48+K47+K46+K56 -> -6188.08 | L60: =L55+L49+L48+L47+L46+L56 -> -3933.13 | M60: =M55+M49+M48+M47+M46+M56 -> 0 | N60: =N55+N49+N48+N47+N46+N56 -> 0 | ... R60: =R55+R49+R48+R47+R46+R56 -> 0 | T60: =SUM(G60:R60) -> -27730.63
B61: =E61&F61
B62: =E62&F62 -> OmnichannelMargine di Contribuzione_2 | E62: Omnichannel | F62: Margine di Contribuzione_2 | G62: =G44+G60 -> -2069.81 | H62: =H44+H60 -> -267.32982 | I62: =I44+I60 -> -450.09372 | J62: =J44+J60 -> -573.68865 | K62: =K44+K60 -> 1461.6904 | L62: =L44+L60 -> 7500.8497 | M62: =M44+M60 -> 1079.9938 | N62: =N44+N60 -> 0 | ... R62: =R44+R60 -> 0 | T62: =SUM(G62:R62) -> 6681.6116
G63: =IFERROR(G62/G29, 0) -> -0.46533498 | H63: =IFERROR(H62/H29, 0) -> -0.069772031 | I63: =IFERROR(I62/I29, 0) -> -0.049772431 | J63: =IFERROR(J62/J29, 0) -> -0.056682633 | K63: =IFERROR(K62/K29, 0) -> 0.11896663 | L63: =IFERROR(L62/L29, 0) -> 0.36427343 | M63: =IFERROR(M62/M29, 0) -> 0.84040847 | N63: =IFERROR(N62/N29, 0) -> 0 | ... R63: =IFERROR(R62/R29, 0) -> 0 | T63: =T62/T29 -> 0.10845632
F65: IVA | G65: =SUMIFS('EXPENSES MASTER'!$F:$F, 'EXPENSES MASTER'!$G:$G, AC!$F$61, 'EXPENSES MASTER'!$B:$B, AC!H$3) -> 0 | H65: =SUMIFS('EXPENSES MASTER'!$F:$F, 'EXPENSES MASTER'!$G:$G, AC!$F$61, 'EXPENSES MASTER'!$B:$B, AC!I$3) -> 0 | I65: =SUMIFS('EXPENSES MASTER'!$F:$F, 'EXPENSES MASTER'!$G:$G, AC!$F$61, 'EXPENSES MASTER'!$B:$B, AC!J$3) -> 0 | J65: =SUMIFS('EXPENSES MASTER'!$F:$F, 'EXPENSES MASTER'!$G:$G, AC!$F$61, 'EXPENSES MASTER'!$B:$B, AC!K$3) -> 0 | K65: =SUMIFS('EXPENSES MASTER'!$F:$F, 'EXPENSES MASTER'!$G:$G, AC!$F$61, 'EXPENSES MASTER'!$B:$B, AC!L$3) -> 0 | L65: =SUMIFS('EXPENSES MASTER'!$F:$F, 'EXPENSES MASTER'!$G:$G, AC!$F$61, 'EXPENSES MASTER'!$B:$B, AC!M$3) -> 0 | M65: =SUMIFS('EXPENSES MASTER'!$F:$F, 'EXPENSES MASTER'!$G:$G, AC!$F$61, 'EXPENSES MASTER'!$B:$B, AC!N$3) -> 0 | N65: =SUMIFS('EXPENSES MASTER'!$F:$F, 'EXPENSES MASTER'!$G:$G, AC!$F$61, 'EXPENSES MASTER'!$B:$B, AC!O$3) -> 0 | ... T65: =SUMIFS('EXPENSES MASTER'!$F:$F, 'EXPENSES MASTER'!$G:$G, AC!$F$61, 'EXPENSES MASTER'!$B:$B, AC!U$3) -> 0

Sheet CE_AMIMI
B1: AC | G1: =G2&G3 -> 20261 | H1: =H2&H3 -> 20262 | I1: =I2&I3 -> 20263 | J1: =J2&J3 -> 20264 | K1: =K2&K3 -> 20265 | L1: =L2&L3 -> 20266 | M1: =M2&M3 -> 20267 | N1: =N2&N3 -> 20268 | ... R1: =R2&R3 -> 202612
F2: YEAR | G2: 2026 | H2: 2026 | I2: 2026 | J2: 2026 | K2: 2026 | L2: 2026 | M2: 2026 | N2: 2026 | O2: 2026 | P2: 2026 | Q2: 2026 | R2: 2026
F3: MONTH | G3: 1 | H3: 2 | I3: 3 | J3: 4 | K3: 5 | L3: 6 | M3: 7 | N3: 8 | O3: 9 | P3: 10 | Q3: 11 | R3: 12
F4: QUARTER | G4: 1 | H4: 1 | I4: 1 | J4: 2 | K4: 2 | L4: 2 | M4: 3 | N4: 3 | O4: 3 | P4: 4 | Q4: 4 | R4: 4
F5: YTD | G5: YTD | H5: YTD | I5: YTD | J5: YTD | K5: YTD | L5: YTD | M5: YTD | N5: YTD | O5: YTD | P5: YTD
C6: IVA | D6: Categoria | E6: Sottocategoria | F6: Voce | G6: GENNAIO | H6: FEBBRAIO | I6: MARZO | J6: APRILE | K6: MAGGIO | L6: GIUGNO | M6: LUGLIO | N6: AGOSTO | O6: SETTEMBRE | P6: OTTOBRE | Q6: NOVEMBRE | R6: DICEMBRE | T6: FY 2026
B8: =E8&F8 -> OnlineOrdini | C8: SI | D8: Fatturato | E8: Online | F8: Ordini | G8: =SUMIFS('DB Shopify'!$CE:$CE,'DB Shopify'!$CC:$CC,CE_AMIMI!G$2,'DB Shopify'!$CD:$CD,CE_AMIMI!G$3) -> 0 | H8: =SUMIFS('DB Shopify'!$CE:$CE,'DB Shopify'!$CC:$CC,CE_AMIMI!H$2,'DB Shopify'!$CD:$CD,CE_AMIMI!H$3) -> 17 | I8: =SUMIFS('DB Shopify'!$CE:$CE,'DB Shopify'!$CC:$CC,CE_AMIMI!I$2,'DB Shopify'!$CD:$CD,CE_AMIMI!I$3) -> 71 | J8: =SUMIFS('DB Shopify'!$CE:$CE,'DB Shopify'!$CC:$CC,CE_AMIMI!J$2,'DB Shopify'!$CD:$CD,CE_AMIMI!J$3) -> 69 | K8: =SUMIFS('DB Shopify'!$CE:$CE,'DB Shopify'!$CC:$CC,CE_AMIMI!K$2,'DB Shopify'!$CD:$CD,CE_AMIMI!K$3) -> 102 | L8: =SUMIFS('DB Shopify'!$CE:$CE,'DB Shopify'!$CC:$CC,CE_AMIMI!L$2,'DB Shopify'!$CD:$CD,CE_AMIMI!L$3) -> 168 | M8: =SUMIFS('DB Shopify'!$CE:$CE,'DB Shopify'!$CC:$CC,CE_AMIMI!M$2,'DB Shopify'!$CD:$CD,CE_AMIMI!M$3) -> 5 | N8: =SUMIFS('DB Shopify'!$CE:$CE,'DB Shopify'!$CC:$CC,CE_AMIMI!N$2,'DB Shopify'!$CD:$CD,CE_AMIMI!N$3) -> 0 | ... R8: =SUMIFS('DB Shopify'!$CE:$CE,'DB Shopify'!$CC:$CC,CE_AMIMI!R$2,'DB Shopify'!$CD:$CD,CE_AMIMI!R$3) -> 0 | T8: =SUM(G8:R8) -> 432
B9: =E9&F9 -> OnlinePezzi/Ordine | E9: Online | F9: Pezzi/Ordine | G9: =iferror(G10/G8,0) -> 0 | H9: =iferror(H10/H8,0) -> 1 | I9: =iferror(I10/I8,0) -> 1 | J9: =iferror(J10/J8,0) -> 1.0724638 | K9: =iferror(K10/K8,0) -> 1.0784314 | L9: =iferror(L10/L8,0) -> 1.0952381 | M9: =iferror(M10/M8,0) -> 1 | N9: =iferror(N10/N8,0) -> 0 | ... R9: =iferror(R10/R8,0) -> 0 | T9: =T10/T8 -> 1.0671296
B10: =E10&F10 -> OnlinePezzi | E10: Online | F10: Pezzi | G10: =SUMIFS('DB Shopify'!$CF:$CF,'DB Shopify'!$CC:$CC,CE_AMIMI!G$2,'DB Shopify'!$CD:$CD,CE_AMIMI!G$3) -> 0 | H10: =SUMIFS('DB Shopify'!$CF:$CF,'DB Shopify'!$CC:$CC,CE_AMIMI!H$2,'DB Shopify'!$CD:$CD,CE_AMIMI!H$3) -> 17 | I10: =SUMIFS('DB Shopify'!$CF:$CF,'DB Shopify'!$CC:$CC,CE_AMIMI!I$2,'DB Shopify'!$CD:$CD,CE_AMIMI!I$3) -> 71 | J10: =SUMIFS('DB Shopify'!$CF:$CF,'DB Shopify'!$CC:$CC,CE_AMIMI!J$2,'DB Shopify'!$CD:$CD,CE_AMIMI!J$3) -> 74 | K10: =SUMIFS('DB Shopify'!$CF:$CF,'DB Shopify'!$CC:$CC,CE_AMIMI!K$2,'DB Shopify'!$CD:$CD,CE_AMIMI!K$3) -> 110 | L10: =SUMIFS('DB Shopify'!$CF:$CF,'DB Shopify'!$CC:$CC,CE_AMIMI!L$2,'DB Shopify'!$CD:$CD,CE_AMIMI!L$3) -> 184 | M10: =SUMIFS('DB Shopify'!$CF:$CF,'DB Shopify'!$CC:$CC,CE_AMIMI!M$2,'DB Shopify'!$CD:$CD,CE_AMIMI!M$3) -> 5 | N10: =SUMIFS('DB Shopify'!$CF:$CF,'DB Shopify'!$CC:$CC,CE_AMIMI!N$2,'DB Shopify'!$CD:$CD,CE_AMIMI!N$3) -> 0 | ... R10: =SUMIFS('DB Shopify'!$CF:$CF,'DB Shopify'!$CC:$CC,CE_AMIMI!R$2,'DB Shopify'!$CD:$CD,CE_AMIMI!R$3) -> 0 | T10: =SUM(G10:R10) -> 461
B11: =E11&F11 -> OnlineCarrello medio | C11: SI | D11: Fatturato | E11: Online | F11: Carrello medio | G11: =iferror(G16/G8,0) -> 0 | H11: =iferror(H16/H8,0) -> 129.78824 | I11: =iferror(I16/I8,0) -> 121.48592 | J11: =iferror(J16/J8,0) -> 115.43043 | K11: =iferror(K16/K8,0) -> 119.03039 | L11: =iferror(L16/L8,0) -> 104.73119 | M11: =iferror(M16/M8,0) -> 104.16 | N11: =iferror(N16/N8,0) -> 0 | ... R11: =iferror(R16/R8,0) -> 0 | T11: =T12/T8 -> 122.79028
B12: =E12&F12 -> OnlineVendite | C12: SI | D12: Fatturato | E12: Online | F12: Vendite | G12: =SUMIFS('DB Shopify'!$S:$S,'DB Shopify'!$CC:$CC,CE_AMIMI!G$2,'DB Shopify'!$CD:$CD,CE_AMIMI!G$3) -> 0 | H12: =SUMIFS('DB Shopify'!$S:$S,'DB Shopify'!$CC:$CC,CE_AMIMI!H$2,'DB Shopify'!$CD:$CD,CE_AMIMI!H$3) -> 2345 | I12: =SUMIFS('DB Shopify'!$S:$S,'DB Shopify'!$CC:$CC,CE_AMIMI!I$2,'DB Shopify'!$CD:$CD,CE_AMIMI!I$3) -> 9463 | J12: =SUMIFS('DB Shopify'!$S:$S,'DB Shopify'!$CC:$CC,CE_AMIMI!J$2,'DB Shopify'!$CD:$CD,CE_AMIMI!J$3) -> 8632 | K12: =SUMIFS('DB Shopify'!$S:$S,'DB Shopify'!$CC:$CC,CE_AMIMI!K$2,'DB Shopify'!$CD:$CD,CE_AMIMI!K$3) -> 12907 | L12: =SUMIFS('DB Shopify'!$S:$S,'DB Shopify'!$CC:$CC,CE_AMIMI!L$2,'DB Shopify'!$CD:$CD,CE_AMIMI!L$3) -> 19138.4 | M12: =SUMIFS('DB Shopify'!$S:$S,'DB Shopify'!$CC:$CC,CE_AMIMI!M$2,'DB Shopify'!$CD:$CD,CE_AMIMI!M$3) -> 560 | N12: =SUMIFS('DB Shopify'!$S:$S,'DB Shopify'!$CC:$CC,CE_AMIMI!N$2,'DB Shopify'!$CD:$CD,CE_AMIMI!N$3) -> 0 | ... R12: =SUMIFS('DB Shopify'!$S:$S,'DB Shopify'!$CC:$CC,CE_AMIMI!R$2,'DB Shopify'!$CD:$CD,CE_AMIMI!R$3) -> 0 | T12: =SUM(G12:R12) -> 53045.4
